Workbook

Sheet 差し替え品番
B1: ＊金額順
B2: 2024年在庫確保品番 | E2: 2026年 | G2: 2025年7月 確保数改修
C3: 変更前（24年9月まで） | D3: 変更後（24年10月以降） | E3: 変更後（26年8月以降） | G3: 品番 | H3: 改修前 | I3: 改修後 | J3: 内容
B4: 1 | C4: fisi-05 | D4: fisi-05 | E4: si-05 | F4: 3250 | G4: fisi-05 | H4: 3315 | I4: 3500 | J4: amazon販売増に伴い、伸び率を前期130%に再調整
B5: 2 | C5: si-07 | D5: flm-001 | E5: flc-002 | F5: 2186 | G5: flm-001 | H5: 1899 | I5: 2200 | J5: amazon販売増に伴い、伸び率を前期120%に再調整
B6: 3 | C6: flc-002 | D6: fll-006 | E6: flm-001 | F6: 2218 | G6: si-10 | H6: 898 | I6: 1000 | J6: 在庫切れ無し（転換率を昨年平均）で計算した場合、伸び率を前期120%が見込めるため再調整
B7: 4 | C7: flm-006 | D7: flm-006 | E7: fll-3004 | F7: 2325 | G7: si-13 | H7: 507 | I7: 1100 | J7: 今期販売の伸びがUP。今期の視覚化データの想定に合わせ再調整
B8: 5 | C8: flm-001 | D8: flm-002 | E8: fll-006 | F8: 1881 | G8: 5135(5336p) | H8: 955 | I8: 1550 | J8: 今期販売の伸びがUP。今期の視覚化データの想定に合わせ再調整
B9: 6 | C9: fll-006 | D9: flc-002 | E9: si-13 | F9: 1022 | G9: ph5099 | H9: 670 | I9: 1000 | J9: 今期販売の伸びがUP。今期の視覚化データの想定に合わせ再調整
B10: 7 | C10: si-01sa | D10: si-10 | E10: si-13ph(併せて発注のため繰り上げ) | F10: 506
B11: 8 | C11: spc-007 | D11: si-13（si-13PH） | E11: si-01sa | F11: 1503
B12: 9 | C12: bdr-1002 | D12: spc-007 | E12: ph5099 | F12: 1721
B13: 10 | C13: si-09 | D13: si-01sa（si-01sap） | E13: flm-006 | F13: 1294
B14: 11 | C14: gg5099 | D14: fll-3004 | E14: flm-002 | F14: 1368
B15: 12 | C15: bdr-1003 | D15: si-07 | E15: si-10 | F15: 973
B16: 13 | C16: si-10 | D16: gg5099 | E16: spc-007 | F16: 1243
B17: 14 | C17: si-08r | D17: fll-3000 | E17: flh-001ph | F17: 623
B18: 15 | C18: flm-002 | D18: flh-001ph | E18: fll-3000 | F18: 1052
B19: 16 | C19: si-03 | D19: si-09 | E19: flk-001 | F19: 597
B20: 17 | C20: 5135(5336P) | D20: bdr-1002 | E20: fl-3000 | F20: 1817 | G20: ＊状況を見て年間販売想定数を更新する必要有り
B21: 18 | C21: gg3087 | D21: bdr-1003 | E21: si-09 | F21: 805
B22: 19 | C22: fll-3000 | D22: 5135(5336P) | E22: spc-006 | F22: 691
B23: 20 | C23: flr-001 | D23: ph5099 | E23: fll-4000 | F23: 757 | G23: ＊状況を見て年間販売想定数を更新する必要有り
B24: 21 | C24: spc-008 | D24: si-08（si-08r） | E24: flw-001-002 | F24: 350
E25: si-11 | F25: 448
E26: si-08r | F26: 341
B31: 選定除外品番
B32: 選定追加品番
B33: 念の為在庫確認品番

Sheet 在庫推移 (2026.08～)
U1: 欠品
C2: ＊FL-3000の在庫も確認する！（次回発注あるかどうか：振り分け表にて） | AH2: 欠品 | AN2: 7月確認月 | AS2: 入荷済み | AV2: 仕様替え | CI2: 仕様替え | CK2: 納期変更分 | CM2: 入荷済み
C3: 在庫確保による販売試算表 | H3: 2025年12月変更分 | J3: 46224 | AN3: ↓ | BK3: プライムデー | BQ3: プライム感謝祭 | BS3: ブラックフライデー | BU3: スーパーセール
C4: 売上上位品番 | F4: 2024年販売想定ベース | H4: 調整データ | J4: 在庫確保数 | AH4: 補充完了日 | AS4: 45566 | AU4: 45597 | AW4: 45627 | AY4: 45658 | BA4: 45689 | BC4: 45717 | BE4: 45748 | BG4: 45778 | BI4: 45809 | BK4: 45839 | BM4: 45870 | BO4: 45901 | BQ4: 45931 | BS4: 45962 | BU4: 45992 | BW4: 46023 | BY4: 46054 | CA4: 46082 | CC4: 46113 | CE4: 46143 | CG4: 46174 | CI4: 46204 | CK4: 46235 | CM4: 46266 | CO4: 46296 | CQ4: 46327 | CS4: 46357 | CU4: 46388 | CW4: 46054 | CY4: 46082
B5: 優先順位 | C5: 品番 | D5: カラー | E5: 度数 | F5: 年間販売数 | G5: 年間売上額 | H5: 年間販売想定数 | I5: 年間売上想定額 | J5: フリー在庫 | K5: EC合計 | L5: 楽天・Yahoo!・auPAY(RSL) | M5: Amazon(FBA) | N5: ECストック | O5: 10/17~ | P5: 11月 | Q5: 12月 | R5: 1月 | S5: 2月 | T5: 3月 | U5: 4月 | V5: 5月 | W5: 6月 | X5: 7月 | Y5: 8月 | Z5: 9月 | AA5: 10月 | AB5: 11月 | AC5: 12月 | AD5: 1月 | AE5: 2月 | AF5: 3月 | AG5: 4月 | AH5: 5月 | AI5: 7月 | AJ5: 8月 | AK5: 9月 | AL5: 10月 | AM5: 11月 | AN5: 12月 | AO5: 1月 | AP5: 2月 | AQ5: 3月 | AS5: 必要数 | AT5: 入荷品確保 | AU5: 必要数 | AV5: 入荷品確保 | AW5: 必要数 | AX5: 入荷品確保 | AY5: 必要数 | AZ5: 入荷品確保 | BA5: 必要数 | BB5: 入荷品確保 | BC5: 必要数 | BD5: 入荷品確保 | BE5: 必要数 | BF5: 入荷品確保 | BG5: 必要数 | BH5: 入荷品確保 | BI5: 必要数 | BJ5: 入荷品確保 | BK5: 必要数 | BL5: 入荷品確保 | BM5: 必要数 | BN5: 入荷品確保 | BO5: 必要数 | BP5: 入荷品確保 | BQ5: 必要数 | BR5: 入荷品確保 | BS5: 必要数 | BT5: 入荷品確保 | BU5: 必要数 | BV5: 入荷品確保 | BW5: 必要数 | BX5: 入荷品確保 | BY5: 必要数 | BZ5: 入荷品確保 | CA5: 必要数 | CB5: 入荷品確保 | CC5: 必要数 | CD5: 入荷品確保 | CE5: 必要数 | CF5: 入荷品確保 | CG5: 必要数 | CH5: 入荷品確保 | CI5: 必要数 | CJ5: 入荷品確保 | CK5: 必要数 | CL5: 入荷品確保 | CM5: 必要数 | CN5: 入荷品確保 | CO5: 必要数 | CP5: 入荷品確保 | CQ5: 必要数 | CR5: 入荷品確保 | CS5: 必要数 | CT5: 入荷品確保 | CU5: 必要数 | CV5: 入荷品確保 | CW5: 必要数 | CX5: 入荷品確保 | CY5: 必要数 | CZ5: 入荷品確保
B6: 1 | C6: fisi-05 ＊欲しい月の2カ月前入荷想定で考える | F6: =SUM(F7:F26) -> 1314 | G6: =SUM(G7:G26) -> 5781600 | H6: 3500 | I6: =SUM(I7:I26) -> 15400000 | J6: =SUM(J7:J26) -> 95 | K6: =SUM(K7:K26) -> 876 | L6: =SUM(L7:L26) -> 123 | M6: =SUM(M7:M26) -> 55 | N6: =SUM(N7:N26) -> 698 | AS6: =SUM(AS7:AS26) -> 350 | AT6: =SUM(AT7:AT26) -> 0 | AU6: =SUM(AU7:AU26) -> 315 | AV6: =SUM(AV7:AV26) -> 432 | AW6: =SUM(AW7:AW26) -> 350 | AX6: =SUM(AX7:AX26) -> 784 | AY6: =SUM(AY7:AY26) -> 213.13031 | AZ6: =SUM(AZ7:AZ26) -> 0 | ... CZ6: =SUM(CZ7:CZ26) -> 0
C7: 入荷： 7月 1210枚 8月 600枚 11月 600枚 | D7: 1 | E7: +1.00 | F7: 48 | G7: =F7*4400 -> 211200 | H7: =F7*($H$6/$F$6) -> 127.85388 | I7: =H7*4400 -> 562557.08 | J7: 3 | K7: =SUM(L7:N7) -> 35 | L7: 10 | M7: 0 | N7: 25 | P7: 45622 | Q7: 45646 | V7: 45792 | Y7: 45884 | AC7: 45662 | AI7: =SUM(J7:K7)-CI7+CJ7 -> 47.771689 | AJ7: =AI7-CK7+CL7 -> 63.033479 | AK7: =AJ7-CM7+CN7 -> 47.691013 | AL7: =AK7-CO7+CP7 -> 34.905625 | AM7: =AL7-CQ7+CR7 -> 48.398775 | AN7: =AM7-CS7+CT7 -> 35.613387 | AO7: =AN7-CU7+CV7 -> 27.827805 | AP7: =AO7-CW7+CX7 -> 20.716173 | AQ7: =AP7-CY7+CZ7 -> 10.487863 | AS7: =$H$7*月別販売比率!AG5 -> 12.785388 | AU7: =$H$7*月別販売比率!AL5 -> 11.506849 | AV7: 12 | AW7: =$H$7*月別販売比率!AQ5 -> 12.785388 | AX7: 46 | AY7: =$H$7*月別販売比率!AV5 -> 7.7855823 | BA7: =$H$7*月別販売比率!BA5 -> 7.1116319 | BB7: 10 | BC7: =$H$7*月別販売比率!BF5 -> 10.228311 | BE7: =$H$7*月別販売比率!C21 -> 9.0602695 | BG7: =$H$7*月別販売比率!H21 -> 8.9497717 | BH7: 26 | BI7: =$H$7*月別販売比率!M21 -> 12.921385 | BJ7: 30 | BK7: =$H$7*月別販売比率!R21 -> 10.228311 | BM7: =$H$7*月別販売比率!W21 -> 9.7382108 | BN7: 25 | BO7: =$H$7*月別販売比率!AB21 -> 15.342466 | BP7: 20 | BQ7: =$H$7*月別販売比率!AG21 -> 12.785388 | BS7: =$H$7*月別販売比率!AL21 -> 11.506849 | BT7: 40 | BU7: =$H$7*月別販売比率!AQ21 -> 12.785388 | BV7: 10 | BW7: =$H$7*月別販売比率!AV21 -> 7.7855823 | BY7: =$H$7*月別販売比率!BA21 -> 7.1116319 | BZ7: 20 | CA7: =$H$7*月別販売比率!BF21 -> 10.228311 | CC7: =H7*月別販売比率!$C$21 -> 9.0602695 | CE7: =H7*月別販売比率!$H$21 -> 8.9497717 | CF7: 30 | CG7: =$H$7*月別販売比率!M21 -> 12.921385 | CH7: 25 | CI7: =H7*月別販売比率!$R$21 -> 10.228311 | CJ7: 20 | CK7: =H7*月別販売比率!$W$21 -> 9.7382108 | CL7: 25 | CM7: =H7*月別販売比率!$AB$21 -> 15.342466 | CO7: =H7*月別販売比率!$AG$21 -> 12.785388 | CQ7: =H7*月別販売比率!$AL$21 -> 11.506849 | CR7: 25 | CS7: =H7*月別販売比率!$AQ$21 -> 12.785388 | CU7: =H7*月別販売比率!$AV$21 -> 7.7855823 | CW7: =H7*月別販売比率!$BA$21 -> 7.1116319 | CY7: =H7*月別販売比率!$BF$21 -> 10.228311
E8: +1.50 | F8: 144 | G8: =F8*4400 -> 633600 | H8: =F8*($H$6/$F$6) -> 383.56164 | I8: =H8*4400 -> 1687671.2 | J8: 5 | K8: =SUM(L8:N8) -> 85 | L8: 10 | M8: 5 | N8: 70 | P8: 45622 | Q8: 45646 | AB8: 45979 | AI8: =SUM(J8:K8)-CI8+CJ8 -> 124.31507 | AJ8: =AI8-CK8+CL8 -> 185.10044 | AK8: =AJ8-CM8+CN8 -> 139.07304 | AL8: =AK8-CO8+CP8 -> 100.71687 | AM8: =AL8-CQ8+CR8 -> 131.19633 | AN8: =AM8-CS8+CT8 -> 92.840162 | AO8: =AN8-CU8+CV8 -> 69.483415 | AP8: =AO8-CW8+CX8 -> 48.14852 | AQ8: =AP8-CY8+CZ8 -> 17.463588 | AS8: =$H$8*月別販売比率!AG5 -> 38.356164 | AU8: =$H$8*月別販売比率!AL5 -> 34.520548 | AV8: 37 | AW8: =$H$8*月別販売比率!AQ5 -> 38.356164 | AX8: 81 | AY8: =$H$8*月別販売比率!AV5 -> 23.356747 | BA8: =$H$8*月別販売比率!BA5 -> 21.334896 | BB8: 75 | BC8: =$H$8*月別販売比率!BF5 -> 30.684932 | BE8: =$H$8*月別販売比率!C21 -> 27.180809 | BG8: =$H$8*月別販売比率!H21 -> 26.849315 | BH8: 50 | BI8: =$H$8*月別販売比率!M21 -> 38.764155 | BJ8: 55 | BK8: =$H$8*月別販売比率!R21 -> 30.684932 | BM8: =$H$8*月別販売比率!W21 -> 29.214632 | BN8: 30 | BO8: =$H$8*月別販売比率!AB21 -> 46.027397 | BP8: 50 | BQ8: =$H$8*月別販売比率!AG21 -> 38.356164 | BR8: 79 | BS8: =$H$8*月別販売比率!AL21 -> 34.520548 | BT8: 85 | BU8: =$H$8*月別販売比率!AQ21 -> 38.356164 | BV8: 50 | BW8: =$H$8*月別販売比率!AV21 -> 23.356747 | BY8: =$H$8*月別販売比率!BA21 -> 21.334896 | BZ8: 8 | CA8: =$H$8*月別販売比率!BF21 -> 30.684932 | CC8: =H8*月別販売比率!$C$21 -> 27.180809 | CE8: =H8*月別販売比率!$H$21 -> 26.849315 | CF8: 80 | CG8: =$H$8*月別販売比率!M21 -> 38.764155 | CH8: 70 | CI8: =H8*月別販売比率!$R$21 -> 30.684932 | CJ8: 65 | CK8: =H8*月別販売比率!$W$21 -> 29.214632 | CL8: 90 | CM8: =H8*月別販売比率!$AB$21 -> 46.027397 | CO8: =H8*月別販売比率!$AG$21 -> 38.356164 | CQ8: =H8*月別販売比率!$AL$21 -> 34.520548 | CR8: 65 | CS8: =H8*月別販売比率!$AQ$21 -> 38.356164 | CU8: =H8*月別販売比率!$AV$21 -> 23.356747 | CW8: =H8*月別販売比率!$BA$21 -> 21.334896 | CY8: =H8*月別販売比率!$BF$21 -> 30.684932
E9: +2.00 | F9: 127 | G9: =F9*4400 -> 558800 | H9: =F9*($H$6/$F$6) -> 338.28006 | I9: =H9*4400 -> 1488432.3 | J9: 29 | K9: =SUM(L9:N9) -> 134 | L9: 9 | M9: 15 | N9: 110 | P9: 45622 | AB9: 45979 | AI9: =SUM(J9:K9)-CI9+CJ9 -> 160.9376 | AJ9: =AI9-CK9+CL9 -> 200.17191 | AK9: =AJ9-CM9+CN9 -> 159.57831 | AL9: =AK9-CO9+CP9 -> 125.7503 | AM9: =AL9-CQ9+CR9 -> 140.30509 | AN9: =AM9-CS9+CT9 -> 106.47709 | AO9: =AN9-CU9+CV9 -> 85.877734 | AP9: =AO9-CW9+CX9 -> 67.061542 | AQ9: =AP9-CY9+CZ9 -> 39.999137 | AS9: =$H$9*月別販売比率!AG5 -> 33.828006 | AU9: =$H$9*月別販売比率!AL5 -> 30.445205 | AV9: 55 | AW9: =$H$9*月別販売比率!AQ5 -> 33.828006 | AX9: 71 | AY9: =$H$9*月別販売比率!AV5 -> 20.599353 | BA9: =$H$9*月別販売比率!BA5 -> 18.816193 | BB9: 65 | BC9: =$H$9*月別販売比率!BF5 -> 27.062405 | BE9: =$H$9*月別販売比率!C21 -> 23.971963 | BG9: =$H$9*月別販売比率!H21 -> 23.679604 | BH9: 45 | BI9: =$H$9*月別販売比率!M21 -> 34.187831 | BJ9: 45 | BK9: =$H$9*月別販売比率!R21 -> 27.062405 | BM9: =$H$9*月別販売比率!W21 -> 25.765683 | BN9: 10 | BO9: =$H$9*月別販売比率!AB21 -> 40.593607 | BQ9: =$H$9*月別販売比率!AG21 -> 33.828006 | BR9: 90 | BS9: =$H$9*月別販売比率!AL21 -> 30.445205 | BT9: 48 | BU9: =$H$9*月別販売比率!AQ21 -> 33.828006 | BV9: 25 | BW9: =$H$9*月別販売比率!AV21 -> 20.599353 | BY9: =$H$9*月別販売比率!BA21 -> 18.816193 | BZ9: 8 | CA9: =$H$9*月別販売比率!BF21 -> 27.062405 | CC9: =H9*月別販売比率!$C$21 -> 23.971963 | CE9: =H9*月別販売比率!$H$21 -> 23.679604 | CF9: 100 | CG9: =$H$9*月別販売比率!M21 -> 34.187831 | CH9: 65 | CI9: =H9*月別販売比率!$R$21 -> 27.062405 | CJ9: 25 | CK9: =H9*月別販売比率!$W$21 -> 25.765683 | CL9: 65 | CM9: =H9*月別販売比率!$AB$21 -> 40.593607 | CO9: =H9*月別販売比率!$AG$21 -> 33.828006 | CQ9: =H9*月別販売比率!$AL$21 -> 30.445205 | CR9: 45 | CS9: =H9*月別販売比率!$AQ$21 -> 33.828006 | CU9: =H9*月別販売比率!$AV$21 -> 20.599353 | CW9: =H9*月別販売比率!$BA$21 -> 18.816193 | CY9: =H9*月別販売比率!$BF$21 -> 27.062405
E10: +2.50 | F10: 46 | G10: =F10*4400 -> 202400 | H10: =F10*($H$6/$F$6) -> 122.52664 | I10: =H10*4400 -> 539117.2 | J10: 23 | K10: =SUM(L10:N10) -> 35 | L10: 10 | M10: 0 | N10: 25 | P10: 45622 | V10: 45792 | Y10: 45884 | AC10: 46017 | AI10: =SUM(J10:K10)-CI10+CJ10 -> 68.197869 | AJ10: =AI10-CK10+CL10 -> 78.865417 | AK10: =AJ10-CM10+CN10 -> 64.162221 | AL10: =AK10-CO10+CP10 -> 51.909557 | AM10: =AL10-CQ10+CR10 -> 60.88216 | AN10: =AM10-CS10+CT10 -> 48.629496 | AO10: =AN10-CU10+CV10 -> 41.168313 | AP10: =AO10-CW10+CX10 -> 34.352999 | AQ10: =AP10-CY10+CZ10 -> 24.550868 | AS10: =$H$10*月別販売比率!AG5 -> 12.252664 | AU10: =$H$10*月別販売比率!AL5 -> 11.027397 | AV10: 20 | AW10: =$H$10*月別販売比率!AQ5 -> 12.252664 | AX10: 26 | AY10: =$H$10*月別販売比率!AV5 -> 7.461183 | BA10: =$H$10*月別販売比率!BA5 -> 6.8153139 | BB10: 20 | BC10: =$H$10*月別販売比率!BF5 -> 9.8021309 | BE10: =$H$10*月別販売比率!C21 -> 8.6827583 | BG10: =$H$10*月別販売比率!H21 -> 8.5768645 | BH10: 20 | BI10: =$H$10*月別販売比率!M21 -> 12.382994 | BJ10: 20 | BK10: =$H$10*月別販売比率!R21 -> 9.8021309 | BM10: =$H$10*月別販売比率!W21 -> 9.332452 | BN10: 10 | BO10: =$H$10*月別販売比率!AB21 -> 14.703196 | BP10: 35 | BQ10: =$H$10*月別販売比率!AG21 -> 12.252664 | BS10: =$H$10*月別販売比率!AL21 -> 11.027397 | BT10: 17 | BU10: =$H$10*月別販売比率!AQ21 -> 12.252664 | BV10: 10 | BW10: =$H$10*月別販売比率!AV21 -> 7.461183 | BY10: =$H$10*月別販売比率!BA21 -> 6.8153139 | BZ10: 23 | CA10: =$H$10*月別販売比率!BF21 -> 9.8021309 | CC10: =H10*月別販売比率!$C$21 -> 8.6827583 | CE10: =H10*月別販売比率!$H$21 -> 8.5768645 | CF10: 30 | CG10: =$H$10*月別販売比率!M21 -> 12.382994 | CH10: 25 | CI10: =H10*月別販売比率!$R$21 -> 9.8021309 | CJ10: 20 | CK10: =H10*月別販売比率!$W$21 -> 9.332452 | CL10: 20 | CM10: =H10*月別販売比率!$AB$21 -> 14.703196 | CO10: =H10*月別販売比率!$AG$21 -> 12.252664 | CQ10: =H10*月別販売比率!$AL$21 -> 11.027397 | CR10: 20 | CS10: =H10*月別販売比率!$AQ$21 -> 12.252664 | CU10: =H10*月別販売比率!$AV$21 -> 7.461183 | CW10: =H10*月別販売比率!$BA$21 -> 6.8153139 | CY10: =H10*月別販売比率!$BF$21 -> 9.8021309
E11: +3.00 | F11: 30 | G11: =F11*4400 -> 132000 | H11: =F11*($H$6/$F$6) -> 79.908676 | I11: =H11*4400 -> 351598.17 | J11: 0 | K11: =SUM(L11:N11) -> 31 | L11: 7 | M11: 0 | N11: 24 | S11: 45707 | V11: 45792 | AI11: =SUM(J11:K11)-CI11+CJ11 -> 24.607306 | AJ11: =AI11-CK11+CL11 -> 33.520924 | AK11: =AJ11-CM11+CN11 -> 23.931883 | AL11: =AK11-CO11+CP11 -> 15.941015 | AM11: =AL11-CQ11+CR11 -> 23.749235 | AN11: =AM11-CS11+CT11 -> 15.758367 | AO11: =AN11-CU11+CV11 -> 10.892378 | AP11: =AO11-CW11+CX11 -> 6.4476083 | AQ11: =AP11-CY11+CZ11 -> 0.054914204 | AS11: =$H$11*月別販売比率!AG5 -> 7.9908676 | AU11: =$H$11*月別販売比率!AL5 -> 7.1917808 | AW11: =$H$11*月別販売比率!AQ5 -> 7.9908676 | AY11: =$H$11*月別販売比率!AV5 -> 4.8659889 | BA11: =$H$11*月別販売比率!BA5 -> 4.4447699 | BB11: 15 | BC11: =$H$11*月別販売比率!BF5 -> 6.3926941 | BE11: =$H$11*月別販売比率!C21 -> 5.6626685 | BG11: =$H$11*月別販売比率!H21 -> 5.5936073 | BH11: 10 | BI11: =$H$11*月別販売比率!M21 -> 8.0758656 | BJ11: 10 | BK11: =$H$11*月別販売比率!R21 -> 6.3926941 | BM11: =$H$11*月別販売比率!W21 -> 6.0863818 | BN11: 10 | BO11: =$H$11*月別販売比率!AB21 -> 9.5890411 | BP11: 20 | BQ11: =$H$11*月別販売比率!AG21 -> 7.9908676 | BS11: =$H$11*月別販売比率!AL21 -> 7.1917808 | BT11: 30 | BU11: =$H$11*月別販売比率!AQ21 -> 7.9908676 | BV11: 5 | BW11: =$H$11*月別販売比率!AV21 -> 4.8659889 | BY11: =$H$11*月別販売比率!BA21 -> 4.4447699 | BZ11: 5 | CA11: =$H$11*月別販売比率!BF21 -> 6.3926941 | CC11: =H11*月別販売比率!$C$21 -> 5.6626685 | CE11: =H11*月別販売比率!$H$21 -> 5.5936073 | CF11: 20 | CG11: =$H$11*月別販売比率!M21 -> 8.0758656 | CH11: 24 | CI11: =H11*月別販売比率!$R$21 -> 6.3926941 | CK11: =H11*月別販売比率!$W$21 -> 6.0863818 | CL11: 15 | CM11: =H11*月別販売比率!$AB$21 -> 9.5890411 | CO11: =H11*月別販売比率!$AG$21 -> 7.9908676 | CQ11: =H11*月別販売比率!$AL$21 -> 7.1917808 | CR11: 15 | CS11: =H11*月別販売比率!$AQ$21 -> 7.9908676 | CU11: =H11*月別販売比率!$AV$21 -> 4.8659889 | CW11: =H11*月別販売比率!$BA$21 -> 4.4447699 | CY11: =H11*月別販売比率!$BF$21 -> 6.3926941
D12: 2 | E12: +1.00 | F12: 84 | G12: =F12*4400 -> 369600 | H12: =F12*($H$6/$F$6) -> 223.74429 | I12: =H12*4400 -> 984474.89 | J12: 0 | K12: =SUM(L12:N12) -> 45 | L12: 0 | M12: 0 | N12: 45 | P12: 45622 | Q12: 45646 | V12: 45792 | Y12: 45884 | AB12: 45979 | AI12: =SUM(J12:K12)-CI12+CJ12 -> 82.100457 | AJ12: =AI12-CK12+CL12 -> 100.05859 | AK12: =AJ12-CM12+CN12 -> 73.209273 | AL12: =AK12-CO12+CP12 -> 50.834843 | AM12: =AL12-CQ12+CR12 -> 65.697857 | AN12: =AM12-CS12+CT12 -> 43.323428 | AO12: =AN12-CU12+CV12 -> 29.698659 | AP12: =AO12-CW12+CX12 -> 17.253303 | AQ12: =AP12-CY12+CZ12 -> -0.64624023 | AS12: =$H$12*月別販売比率!AG5 -> 22.374429 | AU12: =$H$12*月別販売比率!AL5 -> 20.136986 | AV12: 36 | AW12: =$H$12*月別販売比率!AQ5 -> 22.374429 | AX12: 60 | AY12: =$H$12*月別販売比率!AV5 -> 13.624769 | BA12: =$H$12*月別販売比率!BA5 -> 12.445356 | BB12: 35 | BC12: =$H$12*月別販売比率!BF5 -> 17.899543 | BE12: =$H$12*月別販売比率!C21 -> 15.855472 | BG12: =$H$12*月別販売比率!H21 -> 15.6621 | BH12: 27 | BI12: =$H$12*月別販売比率!M21 -> 22.612424 | BJ12: 20 | BK12: =$H$12*月別販売比率!R21 -> 17.899543 | BM12: =$H$12*月別販売比率!W21 -> 17.041869 | BN12: 35 | BO12: =$H$12*月別販売比率!AB21 -> 26.849315 | BP12: 30 | BQ12: =$H$12*月別販売比率!AG21 -> 22.374429 | BR12: 25 | BS12: =$H$12*月別販売比率!AL21 -> 20.136986 | BT12: 75 | BU12: =$H$12*月別販売比率!AQ21 -> 22.374429 | BV12: 35 | BW12: =$H$12*月別販売比率!AV21 -> 13.624769 | BY12: =$H$12*月別販売比率!BA21 -> 12.445356 | BZ12: 16 | CA12: =$H$12*月別販売比率!BF21 -> 17.899543 | CC12: =H12*月別販売比率!$C$21 -> 15.855472 | CE12: =H12*月別販売比率!$H$21 -> 15.6621 | CF12: 30 | CG12: =$H$12*月別販売比率!M21 -> 22.612424 | CH12: 45 | CI12: =H12*月別販売比率!$R$21 -> 17.899543 | CJ12: 55 | CK12: =H12*月別販売比率!$W$21 -> 17.041869 | CL12: 35 | CM12: =H12*月別販売比率!$AB$21 -> 26.849315 | CO12: =H12*月別販売比率!$AG$21 -> 22.374429 | CQ12: =H12*月別販売比率!$AL$21 -> 20.136986 | CR12: 35 | CS12: =H12*月別販売比率!$AQ$21 -> 22.374429 | CU12: =H12*月別販売比率!$AV$21 -> 13.624769 | CW12: =H12*月別販売比率!$BA$21 -> 12.445356 | CY12: =H12*月別販売比率!$BF$21 -> 17.899543
E13: +1.50 | F13: 116 | G13: =F13*4400 -> 510400 | H13: =F13*($H$6/$F$6) -> 308.98021 | I13: =H13*4400 -> 1359512.9 | J13: 0 | K13: =SUM(L13:N13) -> 29 | L13: 0 | M13: 0 | N13: 29 | P13: 45622 | Q13: 45646 | V13: 45792 | Y13: 45884 | AB13: 45979 | AC13: 45662 | AI13: =SUM(J13:K13)-CI13+CJ13 -> 98.281583 | AJ13: =AI13-CK13+CL13 -> 144.74757 | AK13: =AJ13-CM13+CN13 -> 107.66995 | AL13: =AK13-CO13+CP13 -> 76.771927 | AM13: =AL13-CQ13+CR13 -> 81.963707 | AN13: =AM13-CS13+CT13 -> 51.065686 | AO13: =AN13-CU13+CV13 -> 32.250529 | AP13: =AO13-CW13+CX13 -> 15.064085 | AQ13: =AP13-CY13+CZ13 -> -9.6543317 | AS13: =$H$13*月別販売比率!AG5 -> 30.898021 | AU13: =$H$13*月別販売比率!AL5 -> 27.808219 | AV13: 47 | AW13: =$H$13*月別販売比率!AQ5 -> 30.898021 | AX13: 115 | AY13: =$H$13*月別販売比率!AV5 -> 18.815157 | BA13: =$H$13*月別販売比率!BA5 -> 17.186444 | BB13: 40 | BC13: =$H$13*月別販売比率!BF5 -> 24.718417 | BE13: =$H$13*月別販売比率!C21 -> 21.895651 | BG13: =$H$13*月別販売比率!H21 -> 21.628615 | BH13: 35 | BI13: =$H$13*月別販売比率!M21 -> 31.22668 | BJ13: 25 | BK13: =$H$13*月別販売比率!R21 -> 24.718417 | BM13: =$H$13*月別販売比率!W21 -> 23.534009 | BN13: 80 | BO13: =$H$13*月別販売比率!AB21 -> 37.077626 | BQ13: =$H$13*月別販売比率!AG21 -> 30.898021 | BR13: 60 | BS13: =$H$13*月別販売比率!AL21 -> 27.808219 | BT13: 30 | BU13: =$H$13*月別販売比率!AQ21 -> 30.898021 | BV13: 45 | BW13: =$H$13*月別販売比率!AV21 -> 18.815157 | BY13: =$H$13*月別販売比率!BA21 -> 17.186444 | BZ13: 83 | CA13: =$H$13*月別販売比率!BF21 -> 24.718417 | CC13: =H13*月別販売比率!$C$21 -> 21.895651 | CE13: =H13*月別販売比率!$H$21 -> 21.628615 | CF13: 30 | CG13: =$H$13*月別販売比率!M21 -> 31.22668 | CH13: 29 | CI13: =H13*月別販売比率!$R$21 -> 24.718417 | CJ13: 94 | CK13: =H13*月別販売比率!$W$21 -> 23.534009 | CL13: 70 | CM13: =H13*月別販売比率!$AB$21 -> 37.077626 | CO13: =H13*月別販売比率!$AG$21 -> 30.898021 | CQ13: =H13*月別販売比率!$AL$21 -> 27.808219 | CR13: 33 | CS13: =H13*月別販売比率!$AQ$21 -> 30.898021 | CU13: =H13*月別販売比率!$AV$21 -> 18.815157 | CW13: =H13*月別販売比率!$BA$21 -> 17.186444 | CY13: =H13*月別販売比率!$BF$21 -> 24.718417
E14: +2.00 | F14: 184 | G14: =F14*4400 -> 809600 | H14: =F14*($H$6/$F$6) -> 490.10654 | I14: =H14*4400 -> 2156468.8 | J14: 0 | K14: =SUM(L14:N14) -> 33 | L14: 9 | M14: 2 | N14: 22 | P14: 45622 | Q14: 45646 | AB14: 45979 | AI14: =SUM(J14:K14)-CI14+CJ14 -> 143.79148 | AJ14: =AI14-CK14+CL14 -> 196.46167 | AK14: =AJ14-CM14+CN14 -> 137.64888 | AL14: =AK14-CO14+CP14 -> 88.638228 | AM14: =AL14-CQ14+CR14 -> 149.52864 | AN14: =AM14-CS14+CT14 -> 100.51798 | AO14: =AN14-CU14+CV14 -> 70.673253 | AP14: =AO14-CW14+CX14 -> 43.411997 | AQ14: =AP14-CY14+CZ14 -> 4.2034738 | AS14: =$H$14*月別販売比率!AG5 -> 49.010654 | AU14: =$H$14*月別販売比率!AL5 -> 44.109589 | AV14: 72 | AW14: =$H$14*月別販売比率!AQ5 -> 49.010654 | AX14: 120 | AY14: =$H$14*月別販売比率!AV5 -> 29.844732 | BA14: =$H$14*月別販売比率!BA5 -> 27.261256 | BB14: 90 | BC14: =$H$14*月別販売比率!BF5 -> 39.208524 | BE14: =$H$14*月別販売比率!C21 -> 34.731033 | BG14: =$H$14*月別販売比率!H21 -> 34.307458 | BH14: 65 | BI14: =$H$14*月別販売比率!M21 -> 49.531975 | BJ14: 55 | BK14: =$H$14*月別販売比率!R21 -> 39.208524 | BM14: =$H$14*月別販売比率!W21 -> 37.329808 | BN14: 20 | BO14: =$H$14*月別販売比率!AB21 -> 58.812785 | BP14: 50 | BQ14: =$H$14*月別販売比率!AG21 -> 49.010654 | BR14: 50 | BS14: =$H$14*月別販売比率!AL21 -> 44.109589 | BT14: 124 | BU14: =$H$14*月別販売比率!AQ21 -> 49.010654 | BV14: 105 | BW14: =$H$14*月別販売比率!AV21 -> 29.844732 | BY14: =$H$14*月別販売比率!BA21 -> 27.261256 | BZ14: 33 | CA14: =$H$14*月別販売比率!BF21 -> 39.208524 | CC14: =H14*月別販売比率!$C$21 -> 34.731033 | CE14: =H14*月別販売比率!$H$21 -> 34.307458 | CF14: 70 | CG14: =$H$14*月別販売比率!M21 -> 49.531975 | CH14: 22 | CI14: =H14*月別販売比率!$R$21 -> 39.208524 | CJ14: 150 | CK14: =H14*月別販売比率!$W$21 -> 37.329808 | CL14: 90 | CM14: =H14*月別販売比率!$AB$21 -> 58.812785 | CO14: =H14*月別販売比率!$AG$21 -> 49.010654 | CQ14: =H14*月別販売比率!$AL$21 -> 44.109589 | CR14: 105 | CS14: =H14*月別販売比率!$AQ$21 -> 49.010654 | CU14: =H14*月別販売比率!$AV$21 -> 29.844732 | CW14: =H14*月別販売比率!$BA$21 -> 27.261256 | CY14: =H14*月別販売比率!$BF$21 -> 39.208524
E15: +2.50 | F15: 54 | G15: =F15*4400 -> 237600 | H15: =F15*($H$6/$F$6) -> 143.83562 | I15: =H15*4400 -> 632876.71 | J15: 4 | K15: =SUM(L15:N15) -> 27 | L15: 8 | M15: 4 | N15: 15 | Q15: 45646 | V15: 45792 | Y15: 45884 | AC15: 46017 | AI15: =SUM(J15:K15)-CI15+CJ15 -> 49.493151 | AJ15: =AI15-CK15+CL15 -> 58.537664 | AK15: =AJ15-CM15+CN15 -> 41.27739 | AL15: =AK15-CO15+CP15 -> 26.893828 | AM15: =AL15-CQ15+CR15 -> 43.948622 | AN15: =AM15-CS15+CT15 -> 29.565061 | AO15: =AN15-CU15+CV15 -> 20.806281 | AP15: =AO15-CW15+CX15 -> 12.805695 | AQ15: =AP15-CY15+CZ15 -> 1.2988456 | AS15: =$H$15*月別販売比率!AG5 -> 14.383562 | AU15: =$H$15*月別販売比率!AL5 -> 12.945205 | AV15: 11 | AW15: =$H$15*月別販売比率!AQ5 -> 14.383562 | AX15: 30 | AY15: =$H$15*月別販売比率!AV5 -> 8.75878 | BA15: =$H$15*月別販売比率!BA5 -> 8.0005859 | BB15: 20 | BC15: =$H$15*月別販売比率!BF5 -> 11.506849 | BE15: =$H$15*月別販売比率!C21 -> 10.192803 | BG15: =$H$15*月別販売比率!H21 -> 10.068493 | BH15: 20 | BI15: =$H$15*月別販売比率!M21 -> 14.536558 | BJ15: 25 | BK15: =$H$15*月別販売比率!R21 -> 11.506849 | BM15: =$H$15*月別販売比率!W21 -> 10.955487 | BN15: 20 | BO15: =$H$15*月別販売比率!AB21 -> 17.260274 | BP15: 20 | BQ15: =$H$15*月別販売比率!AG21 -> 14.383562 | BS15: =$H$15*月別販売比率!AL21 -> 12.945205 | BT15: 39 | BU15: =$H$15*月別販売比率!AQ21 -> 14.383562 | BV15: 10 | BW15: =$H$15*月別販売比率!AV21 -> 8.75878 | BY15: =$H$15*月別販売比率!BA21 -> 8.0005859 | BZ15: 40 | CA15: =$H$15*月別販売比率!BF21 -> 11.506849 | CC15: =H15*月別販売比率!$C$21 -> 10.192803 | CE15: =H15*月別販売比率!$H$21 -> 10.068493 | CF15: 40 | CG15: =$H$15*月別販売比率!M21 -> 14.536558 | CH15: 15 | CI15: =H15*月別販売比率!$R$21 -> 11.506849 | CJ15: 30 | CK15: =H15*月別販売比率!$W$21 -> 10.955487 | CL15: 20 | CM15: =H15*月別販売比率!$AB$21 -> 17.260274 | CO15: =H15*月別販売比率!$AG$21 -> 14.383562 | CQ15: =H15*月別販売比率!$AL$21 -> 12.945205 | CR15: 30 | CS15: =H15*月別販売比率!$AQ$21 -> 14.383562 | CU15: =H15*月別販売比率!$AV$21 -> 8.75878 | CW15: =H15*月別販売比率!$BA$21 -> 8.0005859 | CY15: =H15*月別販売比率!$BF$21 -> 11.506849
E16: +3.00 | F16: 26 | G16: =F16*4400 -> 114400 | H16: =F16*($H$6/$F$6) -> 69.254186 | I16: =H16*4400 -> 304718.42 | J16: 0 | K16: =SUM(L16:N16) -> 29 | L16: 6 | M16: 14 | N16: 9 | AC16: 45662 | AI16: =SUM(J16:K16)-CI16+CJ16 -> 28.459665 | AJ16: =AI16-CK16+CL16 -> 38.184801 | AK16: =AJ16-CM16+CN16 -> 29.874299 | AL16: =AK16-CO16+CP16 -> 22.94888 | AM16: =AL16-CQ16+CR16 -> 31.716003 | AN16: =AM16-CS16+CT16 -> 24.790585 | AO16: =AN16-CU16+CV16 -> 20.573394 | AP16: =AO16-CW16+CX16 -> 16.72126 | AQ16: =AP16-CY16+CZ16 -> 11.180926 | AS16: =$H$16*月別販売比率!AG5 -> 6.9254186 | AU16: =$H$16*月別販売比率!AL5 -> 6.2328767 | AV16: 10 | AW16: =$H$16*月別販売比率!AQ5 -> 6.9254186 | AY16: =$H$16*月別販売比率!AV5 -> 4.2171904 | BA16: =$H$16*月別販売比率!BA5 -> 3.8521339 | BC16: =$H$16*月別販売比率!BF5 -> 5.5403349 | BE16: =$H$16*月別販売比率!C21 -> 4.907646 | BG16: =$H$16*月別販売比率!H21 -> 4.847793 | BH16: 5 | BI16: =$H$16*月別販売比率!M21 -> 6.9990835 | BJ16: 5 | BK16: =$H$16*月別販売比率!R21 -> 5.5403349 | BM16: =$H$16*月別販売比率!W21 -> 5.2748642 | BN16: 5 | BO16: =$H$16*月別販売比率!AB21 -> 8.3105023 | BP16: 20 | BQ16: =$H$16*月別販売比率!AG21 -> 6.9254186 | BS16: =$H$16*月別販売比率!AL21 -> 6.2328767 | BT16: 15 | BU16: =$H$16*月別販売比率!AQ21 -> 6.9254186 | BV16: 5 | BW16: =$H$16*月別販売比率!AV21 -> 4.2171904 | BY16: =$H$16*月別販売比率!BA21 -> 3.8521339 | BZ16: 5 | CA16: =$H$16*月別販売比率!BF21 -> 5.5403349 | CC16: =H16*月別販売比率!$C$21 -> 4.907646 | CE16: =H16*月別販売比率!$H$21 -> 4.847793 | CF16: 20 | CG16: =$H$16*月別販売比率!M21 -> 6.9990835 | CH16: 9 | CI16: =H16*月別販売比率!$R$21 -> 5.5403349 | CJ16: 5 | CK16: =H16*月別販売比率!$W$21 -> 5.2748642 | CL16: 15 | CM16: =H16*月別販売比率!$AB$21 -> 8.3105023 | CO16: =H16*月別販売比率!$AG$21 -> 6.9254186 | CQ16: =H16*月別販売比率!$AL$21 -> 6.2328767 | CR16: 15 | CS16: =H16*月別販売比率!$AQ$21 -> 6.9254186 | CU16: =H16*月別販売比率!$AV$21 -> 4.2171904 | CW16: =H16*月別販売比率!$BA$21 -> 3.8521339 | CY16: =H16*月別販売比率!$BF$21 -> 5.5403349
D17: 3 (廃番) | E17: +1.00 | F17: 25 | G17: =F17*4400 -> 110000 | H17: =F17*($H$6/$F$6) -> 66.590563 | I17: =H17*4400 -> 292998.48 | J17: 0 | K17: =SUM(L17:N17) -> 34 | L17: 0 | M17: 0 | N17: 34 | S17: 45707 | Y17: 45884 | AB17: 45979 | AI17: =SUM(J17:K17)-CI17+CJ17 -> 28.672755 | AJ17: =AI17-CK17+CL17 -> 23.60077 | AK17: =AJ17-CM17+CN17 -> 15.609903 | AL17: =AK17-CO17+CP17 -> 8.9508462 | AM17: =AL17-CQ17+CR17 -> 2.9576956 | AN17: =AM17-CS17+CT17 -> -3.7013608 | AO17: =AN17-CU17+CV17 -> -7.7563515 | AP17: =AO17-CW17+CX17 -> -11.460326 | AQ17: =AP17-CY17+CZ17 -> -16.787571 | AS17: =$H$17*月別販売比率!AG5 -> 6.6590563 | AU17: =$H$17*月別販売比率!AL5 -> 5.9931507 | AW17: =$H$17*月別販売比率!AQ5 -> 6.6590563 | AY17: =$H$17*月別販売比率!AV5 -> 4.0549908 | BA17: =$H$17*月別販売比率!BA5 -> 3.7039749 | BB17: 40 | BC17: =$H$17*月別販売比率!BF5 -> 5.3272451 | BE17: =$H$17*月別販売比率!C21 -> 4.7188904 | BG17: =$H$17*月別販売比率!H21 -> 4.6613394 | BI17: =$H$17*月別販売比率!M21 -> 6.729888 | BK17: =$H$17*月別販売比率!R21 -> 5.3272451 | BM17: =$H$17*月別販売比率!W21 -> 5.0719848 | BN17: 15 | BO17: =$H$17*月別販売比率!AB21 -> 7.9908676 | BP17: 15 | BQ17: =$H$17*月別販売比率!AG21 -> 6.6590563 | BS17: =$H$17*月別販売比率!AL21 -> 5.9931507 | BT17: 20 | BU17: =$H$17*月別販売比率!AQ21 -> 6.6590563 | BW17: =$H$17*月別販売比率!AV21 -> 4.0549908 | BY17: =$H$17*月別販売比率!BA21 -> 3.7039749 | CA17: =$H$17*月別販売比率!BF21 -> 5.3272451 | CC17: =H17*月別販売比率!$C$21 -> 4.7188904 | CE17: =H17*月別販売比率!$H$21 -> 4.6613394 | CG17: =$H$17*月別販売比率!M21 -> 6.729888 | CH17: 35 | CI17: =H17*月別販売比率!$R$21 -> 5.3272451 | CK17: =H17*月別販売比率!$W$21 -> 5.0719848 | CM17: =H17*月別販売比率!$AB$21 -> 7.9908676 | CO17: =H17*月別販売比率!$AG$21 -> 6.6590563 | CQ17: =H17*月別販売比率!$AL$21 -> 5.9931507 | CS17: =H17*月別販売比率!$AQ$21 -> 6.6590563 | CU17: =H17*月別販売比率!$AV$21 -> 4.0549908 | CW17: =H17*月別販売比率!$BA$21 -> 3.7039749 | CY17: =H17*月別販売比率!$BF$21 -> 5.3272451
E18: +1.50 | F18: 10 | G18: =F18*4400 -> 44000 | H18: =F18*($H$6/$F$6) -> 26.636225 | I18: =H18*4400 -> 117199.39 | J18: 0 | K18: =SUM(L18:N18) -> 15 | L18: 0 | M18: 0 | N18: 15 | S18: 45707 | V18: 45792 | Y18: 45884 | AB18: 45979 | AI18: =SUM(J18:K18)-CI18+CJ18 -> 12.869102 | AJ18: =AI18-CK18+CL18 -> 10.840308 | AK18: =AJ18-CM18+CN18 -> 7.643961 | AL18: =AK18-CO18+CP18 -> 4.9803385 | AM18: =AL18-CQ18+CR18 -> 2.5830782 | AN18: =AM18-CS18+CT18 -> -0.080544301 | AO18: =AN18-CU18+CV18 -> -1.7025406 | AP18: =AO18-CW18+CX18 -> -3.1841306 | AQ18: =AP18-CY18+CZ18 -> -5.3150286 | AS18: =$H$18*月別販売比率!AG5 -> 2.6636225 | AU18: =$H$18*月別販売比率!AL5 -> 2.3972603 | AW18: =$H$18*月別販売比率!AQ5 -> 2.6636225 | AY18: =$H$18*月別販売比率!AV5 -> 1.6219963 | BA18: =$H$18*月別販売比率!BA5 -> 1.48159 | BB18: 30 | BC18: =$H$18*月別販売比率!BF5 -> 2.130898 | BE18: =$H$18*月別販売比率!C21 -> 1.8875562 | BG18: =$H$18*月別販売比率!H21 -> 1.8645358 | BI18: =$H$18*月別販売比率!M21 -> 2.6919552 | BK18: =$H$18*月別販売比率!R21 -> 2.130898 | BM18: =$H$18*月別販売比率!W21 -> 2.0287939 | BN18: 10 | BO18: =$H$18*月別販売比率!AB21 -> 3.196347 | BP18: 15 | BQ18: =$H$18*月別販売比率!AG21 -> 2.6636225 | BS18: =$H$18*月別販売比率!AL21 -> 2.3972603 | BT18: 25 | BU18: =$H$18*月別販売比率!AQ21 -> 2.6636225 | BW18: =$H$18*月別販売比率!AV21 -> 1.6219963 | BY18: =$H$18*月別販売比率!BA21 -> 1.48159 | CA18: =$H$18*月別販売比率!BF21 -> 2.130898 | CC18: =H18*月別販売比率!$C$21 -> 1.8875562 | CE18: =H18*月別販売比率!$H$21 -> 1.8645358 | CG18: =$H$18*月別販売比率!M21 -> 2.6919552 | CH18: 15 | CI18: =H18*月別販売比率!$R$21 -> 2.130898 | CK18: =H18*月別販売比率!$W$21 -> 2.0287939 | CM18: =H18*月別販売比率!$AB$21 -> 3.196347 | CO18: =H18*月別販売比率!$AG$21 -> 2.6636225 | CQ18: =H18*月別販売比率!$AL$21 -> 2.3972603 | CS18: =H18*月別販売比率!$AQ$21 -> 2.6636225 | CU18: =H18*月別販売比率!$AV$21 -> 1.6219963 | CW18: =H18*月別販売比率!$BA$21 -> 1.48159 | CY18: =H18*月別販売比率!$BF$21 -> 2.130898
E19: +2.00 | F19: 15 | G19: =F19*4400 -> 66000 | H19: =F19*($H$6/$F$6) -> 39.954338 | I19: =H19*4400 -> 175799.09 | J19: 0 | K19: =SUM(L19:N19) -> 20 | L19: 0 | M19: 0 | N19: 20 | S19: 45707 | Y19: 45884 | AB19: 45979 | AI19: =SUM(J19:K19)-CI19+CJ19 -> 16.803653 | AJ19: =AI19-CK19+CL19 -> 13.760462 | AK19: =AJ19-CM19+CN19 -> 8.9659415 | AL19: =AK19-CO19+CP19 -> 4.9705077 | AM19: =AL19-CQ19+CR19 -> 1.3746173 | AN19: =AM19-CS19+CT19 -> -2.6208165 | AO19: =AN19-CU19+CV19 -> -5.0538109 | AP19: =AO19-CW19+CX19 -> -7.2761959 | AQ19: =AP19-CY19+CZ19 -> -10.472543 | AS19: =$H$19*月別販売比率!AG5 -> 3.9954338 | AU19: =$H$19*月別販売比率!AL5 -> 3.5958904 | AW19: =$H$19*月別販売比率!AQ5 -> 3.9954338 | AY19: =$H$19*月別販売比率!AV5 -> 2.4329945 | BA19: =$H$19*月別販売比率!BA5 -> 2.222385 | BB19: 30 | BC19: =$H$19*月別販売比率!BF5 -> 3.196347 | BE19: =$H$19*月別販売比率!C21 -> 2.8313342 | BG19: =$H$19*月別販売比率!H21 -> 2.7968037 | BI19: =$H$19*月別販売比率!M21 -> 4.0379328 | BK19: =$H$19*月別販売比率!R21 -> 3.196347 | BM19: =$H$19*月別販売比率!W21 -> 3.0431909 | BN19: 20 | BO19: =$H$19*月別販売比率!AB21 -> 4.7945205 | BP19: 10 | BQ19: =$H$19*月別販売比率!AG21 -> 3.9954338 | BS19: =$H$19*月別販売比率!AL21 -> 3.5958904 | BT19: 25 | BU19: =$H$19*月別販売比率!AQ21 -> 3.9954338 | BW19: =$H$19*月別販売比率!AV21 -> 2.4329945 | BY19: =$H$19*月別販売比率!BA21 -> 2.222385 | CA19: =$H$19*月別販売比率!BF21 -> 3.196347 | CC19: =H19*月別販売比率!$C$21 -> 2.8313342 | CE19: =H19*月別販売比率!$H$21 -> 2.7968037 | CG19: =$H$19*月別販売比率!M21 -> 4.0379328 | CH19: 20 | CI19: =H19*月別販売比率!$R$21 -> 3.196347 | CK19: =H19*月別販売比率!$W$21 -> 3.0431909 | CM19: =H19*月別販売比率!$AB$21 -> 4.7945205 | CO19: =H19*月別販売比率!$AG$21 -> 3.9954338 | CQ19: =H19*月別販売比率!$AL$21 -> 3.5958904 | CS19: =H19*月別販売比率!$AQ$21 -> 3.9954338 | CU19: =H19*月別販売比率!$AV$21 -> 2.4329945 | CW19: =H19*月別販売比率!$BA$21 -> 2.222385 | CY19: =H19*月別販売比率!$BF$21 -> 3.196347
E20: +2.50 | F20: 29 | G20: =F20*4400 -> 127600 | H20: =F20*($H$6/$F$6) -> 77.245053 | I20: =H20*4400 -> 339878.23 | J20: 0 | K20: =SUM(L20:N20) -> 33 | L20: 4 | M20: 0 | N20: 29 | S20: 45707 | AI20: =SUM(J20:K20)-CI20+CJ20 -> 26.820396 | AJ20: =AI20-CK20+CL20 -> 20.936893 | AK20: =AJ20-CM20+CN20 -> 11.667487 | AL20: =AK20-CO20+CP20 -> 3.9429816 | AM20: =AL20-CQ20+CR20 -> -3.0090731 | AN20: =AM20-CS20+CT20 -> -10.733578 | AO20: =AN20-CU20+CV20 -> -15.437368 | AP20: =AO20-CW20+CX20 -> -19.733979 | AQ20: =AP20-CY20+CZ20 -> -25.913583 | AS20: =$H$20*月別販売比率!AG5 -> 7.7245053 | AU20: =$H$20*月別販売比率!AL5 -> 6.9520548 | AW20: =$H$20*月別販売比率!AQ5 -> 7.7245053 | AY20: =$H$20*月別販売比率!AV5 -> 4.7037893 | BA20: =$H$20*月別販売比率!BA5 -> 4.2966109 | BB20: 40 | BC20: =$H$20*月別販売比率!BF5 -> 6.1796043 | BE20: =$H$20*月別販売比率!C21 -> 5.4739129 | BG20: =$H$20*月別販売比率!H21 -> 5.4071537 | BI20: =$H$20*月別販売比率!M21 -> 7.8066701 | BK20: =$H$20*月別販売比率!R21 -> 6.1796043 | BM20: =$H$20*月別販売比率!W21 -> 5.8835024 | BN20: 55 | BO20: =$H$20*月別販売比率!AB21 -> 9.2694064 | BP20: 5 | BQ20: =$H$20*月別販売比率!AG21 -> 7.7245053 | BS20: =$H$20*月別販売比率!AL21 -> 6.9520548 | BT20: 10 | BU20: =$H$20*月別販売比率!AQ21 -> 7.7245053 | BW20: =$H$20*月別販売比率!AV21 -> 4.7037893 | BY20: =$H$20*月別販売比率!BA21 -> 4.2966109 | CA20: =$H$20*月別販売比率!BF21 -> 6.1796043 | CC20: =H20*月別販売比率!$C$21 -> 5.4739129 | CE20: =H20*月別販売比率!$H$21 -> 5.4071537 | CG20: =$H$20*月別販売比率!M21 -> 7.8066701 | CH20: 30 | CI20: =H20*月別販売比率!$R$21 -> 6.1796043 | CK20: =H20*月別販売比率!$W$21 -> 5.8835024 | CM20: =H20*月別販売比率!$AB$21 -> 9.2694064 | CO20: =H20*月別販売比率!$AG$21 -> 7.7245053 | CQ20: =H20*月別販売比率!$AL$21 -> 6.9520548 | CS20: =H20*月別販売比率!$AQ$21 -> 7.7245053 | CU20: =H20*月別販売比率!$AV$21 -> 4.7037893 | CW20: =H20*月別販売比率!$BA$21 -> 4.2966109 | CY20: =H20*月別販売比率!$BF$21 -> 6.1796043
E21: +3.00 | F21: 18 | G21: =F21*4400 -> 79200 | H21: =F21*($H$6/$F$6) -> 47.945205 | I21: =H21*4400 -> 210958.9 | J21: 0 | K21: =SUM(L21:N21) -> 13 | L21: 4 | M21: 0 | N21: 9 | S21: 45707 | Y21: 45884 | AI21: =SUM(J21:K21)-CI21+CJ21 -> 9.1643836 | AJ21: =AI21-CK21+CL21 -> 5.5125545 | AK21: =AJ21-CM21+CN21 -> -0.24087015 | AL21: =AK21-CO21+CP21 -> -5.0353907 | AM21: =AL21-CQ21+CR21 -> -9.3504592 | AN21: =AM21-CS21+CT21 -> -14.14498 | AO21: =AN21-CU21+CV21 -> -17.064573 | AP21: =AO21-CW21+CX21 -> -19.731435 | AQ21: =AP21-CY21+CZ21 -> -23.567051 | AS21: =$H$21*月別販売比率!AG5 -> 4.7945205 | AU21: =$H$21*月別販売比率!AL5 -> 4.3150685 | AW21: =$H$21*月別販売比率!AQ5 -> 4.7945205 | AY21: =$H$21*月別販売比率!AV5 -> 2.9195933 | BA21: =$H$21*月別販売比率!BA5 -> 2.666862 | BB21: 15 | BC21: =$H$21*月別販売比率!BF5 -> 3.8356164 | BE21: =$H$21*月別販売比率!C21 -> 3.3976011 | BG21: =$H$21*月別販売比率!H21 -> 3.3561644 | BI21: =$H$21*月別販売比率!M21 -> 4.8455193 | BK21: =$H$21*月別販売比率!R21 -> 3.8356164 | BM21: =$H$21*月別販売比率!W21 -> 3.6518291 | BN21: 35 | BO21: =$H$21*月別販売比率!AB21 -> 5.7534247 | BQ21: =$H$21*月別販売比率!AG21 -> 4.7945205 | BS21: =$H$21*月別販売比率!AL21 -> 4.3150685 | BT21: 10 | BU21: =$H$21*月別販売比率!AQ21 -> 4.7945205 | BW21: =$H$21*月別販売比率!AV21 -> 2.9195933 | BY21: =$H$21*月別販売比率!BA21 -> 2.666862 | CA21: =$H$21*月別販売比率!BF21 -> 3.8356164 | CC21: =H21*月別販売比率!$C$21 -> 3.3976011 | CE21: =H21*月別販売比率!$H$21 -> 3.3561644 | CG21: =$H$21*月別販売比率!M21 -> 4.8455193 | CH21: 15 | CI21: =H21*月別販売比率!$R$21 -> 3.8356164 | CK21: =H21*月別販売比率!$W$21 -> 3.6518291 | CM21: =H21*月別販売比率!$AB$21 -> 5.7534247 | CO21: =H21*月別販売比率!$AG$21 -> 4.7945205 | CQ21: =H21*月別販売比率!$AL$21 -> 4.3150685 | CS21: =H21*月別販売比率!$AQ$21 -> 4.7945205 | CU21: =H21*月別販売比率!$AV$21 -> 2.9195933 | CW21: =H21*月別販売比率!$BA$21 -> 2.666862 | CY21: =H21*月別販売比率!$BF$21 -> 3.8356164
D22: 4 | E22: +1.00 | F22: 100 | G22: =F22*4400 -> 440000 | H22: =F22*($H$6/$F$6) -> 266.36225 | I22: =H22*4400 -> 1171993.9 | J22: 2 | K22: =SUM(L22:N22) -> 75 | L22: 10 | M22: 0 | N22: 65 | AI22: =SUM(J22:K22)-CI22+CJ22 -> 105.69102 | AJ22: =AI22-CK22+CL22 -> 135.40308 | AK22: =AJ22-CM22+CN22 -> 103.43961 | AL22: =AK22-CO22+CP22 -> 76.803385 | AM22: =AL22-CQ22+CR22 -> 87.830782 | AN22: =AM22-CS22+CT22 -> 61.194557 | AO22: =AN22-CU22+CV22 -> 44.974594 | AP22: =AO22-CW22+CX22 -> 30.158694 | AQ22: =AP22-CY22+CZ22 -> 8.849714 | AS22: =$H$22*月別販売比率!AG5 -> 26.636225 | AU22: =$H$22*月別販売比率!AL5 -> 23.972603 | AV22: 40 | AW22: =$H$22*月別販売比率!AQ5 -> 26.636225 | AX22: 50 | AY22: =$H$22*月別販売比率!AV5 -> 16.219963 | BA22: =$H$22*月別販売比率!BA5 -> 14.8159 | BC22: =$H$22*月別販売比率!BF5 -> 21.30898 | BD22: 45 | BE22: =$H$22*月別販売比率!C21 -> 18.875562 | BG22: =$H$22*月別販売比率!H21 -> 18.645358 | BH22: 40 | BI22: =$H$22*月別販売比率!M21 -> 26.919552 | BJ22: 35 | BK22: =$H$22*月別販売比率!R21 -> 21.30898 | BM22: =$H$22*月別販売比率!W21 -> 20.287939 | BN22: 40 | BO22: =$H$22*月別販売比率!AB21 -> 31.96347 | BQ22: =$H$22*月別販売比率!AG21 -> 26.636225 | BR22: 15 | BS22: =$H$22*月別販売比率!AL21 -> 23.972603 | BT22: 75 | BU22: =$H$22*月別販売比率!AQ21 -> 26.636225 | BV22: 30 | BW22: =$H$22*月別販売比率!AV21 -> 16.219963 | BY22: =$H$22*月別販売比率!BA21 -> 14.8159 | CA22: =$H$22*月別販売比率!BF21 -> 21.30898 | CC22: =H22*月別販売比率!$C$21 -> 18.875562 | CE22: =H22*月別販売比率!$H$21 -> 18.645358 | CF22: 30 | CG22: =$H$22*月別販売比率!M21 -> 26.919552 | CH22: 65 | CI22: =H22*月別販売比率!$R$21 -> 21.30898 | CJ22: 50 | CK22: =H22*月別販売比率!$W$21 -> 20.287939 | CL22: 50 | CM22: =H22*月別販売比率!$AB$21 -> 31.96347 | CO22: =H22*月別販売比率!$AG$21 -> 26.636225 | CQ22: =H22*月別販売比率!$AL$21 -> 23.972603 | CR22: 35 | CS22: =H22*月別販売比率!$AQ$21 -> 26.636225 | CU22: =H22*月別販売比率!$AV$21 -> 16.219963 | CW22: =H22*月別販売比率!$BA$21 -> 14.8159 | CY22: =H22*月別販売比率!$BF$21 -> 21.30898
E23: +1.50 | F23: 133 | G23: =F23*4400 -> 585200 | H23: =F23*($H$6/$F$6) -> 354.2618 | I23: =H23*4400 -> 1558751.9 | J23: 19 | K23: =SUM(L23:N23) -> 129 | L23: 10 | M23: 10 | N23: 109 | P23: 45622 | Q23: 45646 | AI23: =SUM(J23:K23)-CI23+CJ23 -> 134.65906 | AJ23: =AI23-CK23+CL23 -> 167.6761 | AK23: =AJ23-CM23+CN23 -> 125.16468 | AL23: =AK23-CO23+CP23 -> 89.738502 | AM23: =AL23-CQ23+CR23 -> 142.85494 | AN23: =AM23-CS23+CT23 -> 107.42876 | AO23: =AN23-CU23+CV23 -> 85.85621 | AP23: =AO23-CW23+CX23 -> 66.151063 | AQ23: =AP23-CY23+CZ23 -> 37.81012 | AS23: =$H$23*月別販売比率!AG5 -> 35.42618 | AU23: =$H$23*月別販売比率!AL5 -> 31.883562 | AV23: 50 | AW23: =$H$23*月別販売比率!AQ5 -> 35.42618 | AX23: 65 | AY23: =$H$23*月別販売比率!AV5 -> 21.572551 | BA23: =$H$23*月別販売比率!BA5 -> 19.705147 | BC23: =$H$23*月別販売比率!BF5 -> 28.340944 | BD23: 70 | BE23: =$H$23*月別販売比率!C21 -> 25.104497 | BG23: =$H$23*月別販売比率!H21 -> 24.798326 | BH23: 55 | BI23: =$H$23*月別販売比率!M21 -> 35.803004 | BJ23: 50 | BK23: =$H$23*月別販売比率!R21 -> 28.340944 | BM23: =$H$23*月別販売比率!W21 -> 26.982959 | BN23: 70 | BO23: =$H$23*月別販売比率!AB21 -> 42.511416 | BQ23: =$H$23*月別販売比率!AG21 -> 35.42618 | BR23: 10 | BS23: =$H$23*月別販売比率!AL21 -> 31.883562 | BT23: 54 | BU23: =$H$23*月別販売比率!AQ21 -> 35.42618 | BV23: 20 | BW23: =$H$23*月別販売比率!AV21 -> 21.572551 | BY23: =$H$23*月別販売比率!BA21 -> 19.705147 | BZ23: 40 | CA23: =$H$23*月別販売比率!BF21 -> 28.340944 | CC23: =H23*月別販売比率!$C$21 -> 25.104497 | CE23: =H23*月別販売比率!$H$21 -> 24.798326 | CF23: 120 | CG23: =$H$23*月別販売比率!M21 -> 35.803004 | CH23: 59 | CI23: =H23*月別販売比率!$R$21 -> 28.340944 | CJ23: 15 | CK23: =H23*月別販売比率!$W$21 -> 26.982959 | CL23: 60 | CM23: =H23*月別販売比率!$AB$21 -> 42.511416 | CO23: =H23*月別販売比率!$AG$21 -> 35.42618 | CQ23: =H23*月別販売比率!$AL$21 -> 31.883562 | CR23: 85 | CS23: =H23*月別販売比率!$AQ$21 -> 35.42618 | CU23: =H23*月別販売比率!$AV$21 -> 21.572551 | CW23: =H23*月別販売比率!$BA$21 -> 19.705147 | CY23: =H23*月別販売比率!$BF$21 -> 28.340944
E24: +2.00 | F24: 62 | G24: =F24*4400 -> 272800 | H24: =F24*($H$6/$F$6) -> 165.1446 | I24: =H24*4400 -> 726636.23 | J24: 5 | K24: =SUM(L24:N24) -> 38 | L24: 9 | M24: 0 | N24: 29 | P24: 45622 | U24: 45752 | AC24: 46017 | AI24: =SUM(J24:K24)-CI24+CJ24 -> 59.788432 | AJ24: =AI24-CK24+CL24 -> 72.20991 | AK24: =AJ24-CM24+CN24 -> 52.392558 | AL24: =AK24-CO24+CP24 -> 35.878099 | AM24: =AL24-CQ24+CR24 -> 61.015085 | AN24: =AM24-CS24+CT24 -> 44.500625 | AO24: =AN24-CU24+CV24 -> 34.444248 | AP24: =AO24-CW24+CX24 -> 25.25839 | AQ24: =AP24-CY24+CZ24 -> 12.046823 | AS24: =$H$24*月別販売比率!AG5 -> 16.51446 | AU24: =$H$24*月別販売比率!AL5 -> 14.863014 | AV24: 30 | AW24: =$H$24*月別販売比率!AQ5 -> 16.51446 | AX24: 50 | AY24: =$H$24*月別販売比率!AV5 -> 10.056377 | BA24: =$H$24*月別販売比率!BA5 -> 9.1858578 | BC24: =$H$24*月別販売比率!BF5 -> 13.211568 | BD24: 25 | BE24: =$H$24*月別販売比率!C21 -> 11.702848 | BG24: =$H$24*月別販売比率!H21 -> 11.560122 | BH24: 20 | BI24: =$H$24*月別販売比率!M21 -> 16.690122 | BJ24: 12 | BK24: =$H$24*月別販売比率!R21 -> 13.211568 | BM24: =$H$24*月別販売比率!W21 -> 12.578522 | BN24: 40 | BO24: =$H$24*月別販売比率!AB21 -> 19.817352 | BQ24: =$H$24*月別販売比率!AG21 -> 16.51446 | BR24: 10 | BS24: =$H$24*月別販売比率!AL21 -> 14.863014 | BT24: 34 | BU24: =$H$24*月別販売比率!AQ21 -> 16.51446 | BV24: 15 | BW24: =$H$24*月別販売比率!AV21 -> 10.056377 | BY24: =$H$24*月別販売比率!BA21 -> 9.1858578 | BZ24: 25 | CA24: =$H$24*月別販売比率!BF21 -> 13.211568 | CC24: =H24*月別販売比率!$C$21 -> 11.702848 | CE24: =H24*月別販売比率!$H$21 -> 11.560122 | CF24: 30 | CG24: =$H$24*月別販売比率!M21 -> 16.690122 | CH24: 29 | CI24: =H24*月別販売比率!$R$21 -> 13.211568 | CJ24: 30 | CK24: =H24*月別販売比率!$W$21 -> 12.578522 | CL24: 25 | CM24: =H24*月別販売比率!$AB$21 -> 19.817352 | CO24: =H24*月別販売比率!$AG$21 -> 16.51446 | CQ24: =H24*月別販売比率!$AL$21 -> 14.863014 | CR24: 40 | CS24: =H24*月別販売比率!$AQ$21 -> 16.51446 | CU24: =H24*月別販売比率!$AV$21 -> 10.056377 | CW24: =H24*月別販売比率!$BA$21 -> 9.1858578 | CY24: =H24*月別販売比率!$BF$21 -> 13.211568
E25: +2.50 | F25: 31 | G25: =F25*4400 -> 136400 | H25: =F25*($H$6/$F$6) -> 82.572298 | I25: =H25*4400 -> 363318.11 | J25: 5 | K25: =SUM(L25:N25) -> 9 | L25: 9 | M25: 0 | P25: 45622 | Q25: 45646 | Y25: 45884 | AB25: 45979 | AC25: 45662 | AI25: =SUM(J25:K25)-CI25+CJ25 -> 24.394216 | AJ25: =AI25-CK25+CL25 -> 28.104955 | AK25: =AJ25-CM25+CN25 -> 18.196279 | AL25: =AK25-CO25+CP25 -> 9.9390493 | AM25: =AL25-CQ25+CR25 -> 27.507542 | AN25: =AM25-CS25+CT25 -> 19.250313 | AO25: =AN25-CU25+CV25 -> 14.222124 | AP25: =AO25-CW25+CX25 -> 9.6291952 | AQ25: =AP25-CY25+CZ25 -> 3.0234113 | AS25: =$H$25*月別販売比率!AG5 -> 8.2572298 | AU25: =$H$25*月別販売比率!AL5 -> 7.4315068 | AV25: 12 | AW25: =$H$25*月別販売比率!AQ5 -> 8.2572298 | AX25: 50 | AY25: =$H$25*月別販売比率!AV5 -> 5.0281885 | BA25: =$H$25*月別販売比率!BA5 -> 4.5929289 | BC25: =$H$25*月別販売比率!BF5 -> 6.6057839 | BE25: =$H$25*月別販売比率!C21 -> 5.8514241 | BG25: =$H$25*月別販売比率!H21 -> 5.7800609 | BH25: 10 | BI25: =$H$25*月別販売比率!M21 -> 8.3450611 | BJ25: 4 | BK25: =$H$25*月別販売比率!R21 -> 6.6057839 | BM25: =$H$25*月別販売比率!W21 -> 6.2892612 | BN25: 25 | BO25: =$H$25*月別販売比率!AB21 -> 9.9086758 | BQ25: =$H$25*月別販売比率!AG21 -> 8.2572298 | BR25: 5 | BS25: =$H$25*月別販売比率!AL21 -> 7.4315068 | BT25: 20 | BU25: =$H$25*月別販売比率!AQ21 -> 8.2572298 | BW25: =$H$25*月別販売比率!AV21 -> 5.0281885 | BY25: =$H$25*月別販売比率!BA21 -> 4.5929289 | BZ25: 33 | CA25: =$H$25*月別販売比率!BF21 -> 6.6057839 | CC25: =H25*月別販売比率!$C$21 -> 5.8514241 | CE25: =H25*月別販売比率!$H$21 -> 5.7800609 | CF25: 20 | CG25: =$H$25*月別販売比率!M21 -> 8.3450611 | CH25: 0 | CI25: =H25*月別販売比率!$R$21 -> 6.6057839 | CJ25: 17 | CK25: =H25*月別販売比率!$W$21 -> 6.2892612 | CL25: 10 | CM25: =H25*月別販売比率!$AB$21 -> 9.9086758 | CO25: =H25*月別販売比率!$AG$21 -> 8.2572298 | CQ25: =H25*月別販売比率!$AL$21 -> 7.4315068 | CR25: 25 | CS25: =H25*月別販売比率!$AQ$21 -> 8.2572298 | CU25: =H25*月別販売比率!$AV$21 -> 5.0281885 | CW25: =H25*月別販売比率!$BA$21 -> 4.5929289 | CY25: =H25*月別販売比率!$BF$21 -> 6.6057839
E26: +3.00 | F26: 32 | G26: =F26*4400 -> 140800 | H26: =F26*($H$6/$F$6) -> 85.235921 | I26: =H26*4400 -> 375038.05 | J26: 0 | K26: =SUM(L26:N26) -> 27 | L26: 8 | M26: 5 | N26: 14 | AI26: =SUM(J26:K26)-CI26+CJ26 -> 35.181126 | AJ26: =AI26-CK26+CL26 -> 38.688986 | AK26: =AJ26-CM26+CN26 -> 28.460675 | AL26: =AK26-CO26+CP26 -> 19.937083 | AM26: =AL26-CQ26+CR26 -> 32.26585 | AN26: =AM26-CS26+CT26 -> 23.742258 | AO26: =AN26-CU26+CV26 -> 18.55187 | AP26: =AO26-CW26+CX26 -> 13.810782 | AQ26: =AP26-CY26+CZ26 -> 6.9919085 | AS26: =$H$26*月別販売比率!AG5 -> 8.5235921 | AU26: =$H$26*月別販売比率!AL5 -> 7.6712329 | AW26: =$H$26*月別販売比率!AQ5 -> 8.5235921 | AX26: 20 | AY26: =$H$26*月別販売比率!AV5 -> 5.1903882 | BA26: =$H$26*月別販売比率!BA5 -> 4.7410879 | BC26: =$H$26*月別販売比率!BF5 -> 6.8188737 | BE26: =$H$26*月別販売比率!C21 -> 6.0401797 | BG26: =$H$26*月別販売比率!H21 -> 5.9665145 | BH26: 10 | BI26: =$H$26*月別販売比率!M21 -> 8.6142566 | BJ26: 5 | BK26: =$H$26*月別販売比率!R21 -> 6.8188737 | BM26: =$H$26*月別販売比率!W21 -> 6.4921405 | BN26: 10 | BO26: =$H$26*月別販売比率!AB21 -> 10.228311 | BQ26: =$H$26*月別販売比率!AG21 -> 8.5235921 | BR26: 10 | BS26: =$H$26*月別販売比率!AL21 -> 7.6712329 | BT26: 5 | BU26: =$H$26*月別販売比率!AQ21 -> 8.5235921 | BW26: =$H$26*月別販売比率!AV21 -> 5.1903882 | BY26: =$H$26*月別販売比率!BA21 -> 4.7410879 | BZ26: 20 | CA26: =$H$26*月別販売比率!BF21 -> 6.8188737 | CC26: =H26*月別販売比率!$C$21 -> 6.0401797 | CE26: =H26*月別販売比率!$H$21 -> 5.9665145 | CF26: 20 | CG26: =$H$26*月別販売比率!M21 -> 8.6142566 | CH26: 14 | CI26: =H26*月別販売比率!$R$21 -> 6.8188737 | CJ26: 15 | CK26: =H26*月別販売比率!$W$21 -> 6.4921405 | CL26: 10 | CM26: =H26*月別販売比率!$AB$21 -> 10.228311 | CO26: =H26*月別販売比率!$AG$21 -> 8.5235921 | CQ26: =H26*月別販売比率!$AL$21 -> 7.6712329 | CR26: 20 | CS26: =H26*月別販売比率!$AQ$21 -> 8.5235921 | CU26: =H26*月別販売比率!$AV$21 -> 5.1903882 | CW26: =H26*月別販売比率!$BA$21 -> 4.7410879 | CY26: =H26*月別販売比率!$BF$21 -> 6.8188737
B27: 2 | C27: flc-002 | F27: =SUM(F28:F37) -> 453 | G27: =SUM(G28:G37) -> 1644390 | H27: 2323 | I27: =SUM(I28:I37) -> 9625790.4 | J27: =SUM(J28:J37) -> 559 | K27: =SUM(K28:K37) -> 224 | L27: =SUM(L28:L37) -> 58 | M27: =SUM(M28:M37) -> 166 | N27: =SUM(N28:N37) -> 0 | AS27: =SUM(AS28:AS37) -> 265.17329 | AT27: =SUM(AT28:AT37) -> 0 | AU27: =SUM(AU28:AU37) -> 238.65596 | AV27: =SUM(AV28:AV37) -> 0 | AW27: =SUM(AW28:AW37) -> 265.17329 | AX27: =SUM(AX28:AX37) -> 300 | AY27: =SUM(AY28:AY37) -> 161.47562 | AZ27: =SUM(AZ28:AZ37) -> 300 | ... BE27: =SUM(BE28:BE37) -> 187.91307 | BG27: =SUM(BG28:BG37) -> 185.6213 | BH27: =SUM(BH28:BH37) -> 0 | BI27: =SUM(BI28:BI37) -> 267.99391 | BJ27: =SUM(BJ28:BJ37) -> 300 | BK27: =SUM(BK28:BK37) -> 212.13863 | BL27: =SUM(BL28:BL37) -> 600 | BM27: =SUM(BM28:BM37) -> 201.9738 | BN27: =SUM(BN28:BN37) -> 0 | ... CT27: =SUM(CT28:CT37) -> 345 | CU27: 161.47562 | CV27: =SUM(CV28:CV37) -> 0 | CW27: =SUM(CW28:CW37) -> 147.49766 | CX27: =SUM(CX28:CX37) -> 0 | CY27: =SUM(CY28:CY37) -> 212.13863 | CZ27: =SUM(CZ28:CZ37) -> 0
C28: 入荷：5月 568枚 8月 330枚 10月 280枚 11月 300枚 11月 900枚（累進) 12月 300枚 | D28: 1 | E28: +1.00 | F28: 31 | G28: =F28*3630 -> 112530 | H28: 200 | I28: =H28*3630 -> 726000 | J28: 0 | K28: =SUM(L28:N28) -> 10 | L28: 0 | M28: 10 | S28: 45693 | X28: 45869 | AD28: 46045 | AI28: =SUM(J28:K28)-CI28+CJ28 -> -6 | AJ28: =0-CK28+CL28 -> 14.766656 | AK28: =AJ28-CM28+CN28 -> -9.2333441 | AL28: =0-CO28+CP28 -> 20 | AM28: =AL28-CQ28+CR28 -> 37 | AN28: =AM28-CS28+CT28 -> 42 | AO28: =AN28-CU28+CV28 -> 29.821125 | AP28: =AO28-CW28+CX28 -> 18.696501 | AQ28: =AP28-CY28+CZ28 -> 2.6965008 | AS28: =$H$28*月別販売比率!AG5 -> 20 | AU28: =$H$28*月別販売比率!AL5 -> 18 | AW28: =$H$28*月別販売比率!AQ5 -> 20 | AX28: 20 | AY28: =$H$28*月別販売比率!AV5 -> 12.178875 | AZ28: 42 | BA28: =$H$28*月別販売比率!BA5 -> 11.124624 | BB28: 42 | BC28: =$H$28*月別販売比率!BF5 -> 16 | BE28: =$H$28*月別販売比率!C21 -> 14.17285 | BG28: =$H$28*月別販売比率!H21 -> 14 | BI28: =$H$28*月別販売比率!M21 -> 20.212738 | BK28: =$H$28*月別販売比率!R21 -> 16 | BL28: 60 | BM28: =$H$28*月別販売比率!W21 -> 15.233344 | BO28: =$H$28*月別販売比率!AB21 -> 24 | BP28: 35 | BQ28: =$H$28*月別販売比率!AG21 -> 20 | BS28: =$H$28*月別販売比率!AL21 -> 18 | BT28: 20 | BU28: =$H$28*月別販売比率!AQ21 -> 20 | BW28: =$H$28*月別販売比率!AV21 -> 12.178875 | BX28: 37 | BY28: =$H$28*月別販売比率!BA21 -> 11.124624 | CA28: =$H$28*月別販売比率!BF21 -> 16 | CC28: =H28*月別販売比率!$C$21 -> 14.17285 | CE28: =H28*月別販売比率!$H$21 -> 14 | CF28: 62 | CG28: =H28*月別販売比率!$M$21 -> 20.212738 | CI28: =H28*月別販売比率!$R$21 -> 16 | CK28: =H28*月別販売比率!$W$21 -> 15.233344 | CL28: 30 | CM28: =H28*月別販売比率!$AB$21 -> 24 | CO28: =H28*月別販売比率!$AG$21 -> 20 | CP28: 40 | CQ28: =H28*月別販売比率!$AL$21 -> 18 | CR28: 35 | CS28: =H28*月別販売比率!$AQ$21 -> 20 | CT28: 25 | CU28: =H28*月別販売比率!$AV$21 -> 12.178875 | CW28: =H28*月別販売比率!$BA$21 -> 11.124624 | CY28: =H28*月別販売比率!$BF$21 -> 16
E29: +1.50 | F29: 32 | G29: =F29*3630 -> 116160 | H29: 320 | I29: =H29*3630 -> 1161600 | J29: 24 | K29: =SUM(L29:N29) -> 21 | L29: 9 | M29: 12 | S29: 45693 | X29: 45869 | AD29: 46045 | AI29: =SUM(J29:K29)-CI29+CJ29 -> 19.4 | AJ29: =AI29-CK29+CL29 -> 55.026649 | AK29: =AJ29-CM29+CN29 -> 16.626649 | AL29: =AK29-CO29+CP29 -> 44.626649 | AM29: =AL29-CQ29+CR29 -> 45.826649 | AN29: =AM29-CS29+CT29 -> 58.826649 | AO29: =AN29-CU29+CV29 -> 39.340449 | AP29: =AO29-CW29+CX29 -> 21.541051 | AQ29: =AP29-CY29+CZ29 -> -4.0589493 | AS29: =$H$29*月別販売比率!AG5 -> 32 | AU29: =$H$29*月別販売比率!AL5 -> 28.8 | AW29: =$H$29*月別販売比率!AQ5 -> 32 | AX29: 30 | AY29: =$H$29*月別販売比率!AV5 -> 19.4862 | AZ29: 48 | BA29: =$H$29*月別販売比率!BA5 -> 17.799399 | BB29: 48 | BC29: =$H$29*月別販売比率!BF5 -> 25.6 | BE29: =$H$29*月別販売比率!C21 -> 22.67656 | BG29: =$H$29*月別販売比率!H21 -> 22.4 | BI29: =$H$29*月別販売比率!M21 -> 32.340381 | BK29: =$H$29*月別販売比率!R21 -> 25.6 | BL29: 60 | BM29: =$H$29*月別販売比率!W21 -> 24.373351 | BO29: =$H$29*月別販売比率!AB21 -> 38.4 | BP29: 40 | BQ29: =$H$29*月別販売比率!AG21 -> 32 | BS29: =$H$29*月別販売比率!AL21 -> 28.8 | BT29: 25 | BU29: =$H$29*月別販売比率!AQ21 -> 32 | BW29: =$H$29*月別販売比率!AV21 -> 19.4862 | BX29: 40 | BY29: =$H$29*月別販売比率!BA21 -> 17.799399 | CA29: =$H$29*月別販売比率!BF21 -> 25.6 | CC29: =H29*月別販売比率!$C$21 -> 22.67656 | CE29: =H29*月別販売比率!$H$21 -> 22.4 | CF29: 96 | CG29: =H29*月別販売比率!$M$21 -> 32.340381 | CI29: =H29*月別販売比率!$R$21 -> 25.6 | CK29: =H29*月別販売比率!$W$21 -> 24.373351 | CL29: 60 | CM29: =H29*月別販売比率!$AB$21 -> 38.4 | CO29: =H29*月別販売比率!$AG$21 -> 32 | CP29: 60 | CQ29: =H29*月別販売比率!$AL$21 -> 28.8 | CR29: 30 | CS29: =H29*月別販売比率!$AQ$21 -> 32 | CT29: 45 | CU29: =H29*月別販売比率!$AV$21 -> 19.4862 | CW29: =H29*月別販売比率!$BA$21 -> 17.799399 | CY29: =H29*月別販売比率!$BF$21 -> 25.6
E30: +2.00 | F30: 25 | G30: =F30*3630 -> 90750 | H30: 260 | I30: =H30*3630 -> 943800 | J30: 34 | K30: =SUM(L30:N30) -> 22 | L30: 10 | M30: 12 | S30: 45693 | X30: 45869 | AD30: 46045 | AI30: =SUM(J30:K30)-CI30+CJ30 -> 35.2 | AJ30: =AI30-CK30+CL30 -> 65.396653 | AK30: =AJ30-CM30+CN30 -> 34.196653 | AL30: =AK30-CO30+CP30 -> 48.196653 | AM30: =AL30-CQ30+CR30 -> 54.796653 | AN30: =AM30-CS30+CT30 -> 63.796653 | AO30: =AN30-CU30+CV30 -> 47.964115 | AP30: =AO30-CW30+CX30 -> 33.502104 | AQ30: =AP30-CY30+CZ30 -> 12.702104 | AS30: =$H$30*月別販売比率!AG5 -> 26 | AU30: =$H$30*月別販売比率!AL5 -> 23.4 | AW30: =$H$30*月別販売比率!AQ5 -> 26 | AX30: 30 | AY30: =$H$30*月別販売比率!AV5 -> 15.832538 | AZ30: 36 | BA30: =$H$30*月別販売比率!BA5 -> 14.462011 | BB30: 36 | BC30: =$H$30*月別販売比率!BF5 -> 20.8 | BE30: =$H$30*月別販売比率!C21 -> 18.424705 | BG30: =$H$30*月別販売比率!H21 -> 18.2 | BI30: =$H$30*月別販売比率!M21 -> 26.276559 | BK30: =$H$30*月別販売比率!R21 -> 20.8 | BL30: 35 | BM30: =$H$30*月別販売比率!W21 -> 19.803347 | BO30: =$H$30*月別販売比率!AB21 -> 31.2 | BP30: 35 | BQ30: =$H$30*月別販売比率!AG21 -> 26 | BS30: =$H$30*月別販売比率!AL21 -> 23.4 | BT30: 0 | BU30: =$H$30*月別販売比率!AQ21 -> 26 | BW30: =$H$30*月別販売比率!AV21 -> 15.832538 | BX30: 42 | BY30: =$H$30*月別販売比率!BA21 -> 14.462011 | CA30: =$H$30*月別販売比率!BF21 -> 20.8 | CC30: =H30*月別販売比率!$C$21 -> 18.424705 | CE30: =H30*月別販売比率!$H$21 -> 18.2 | CF30: 81 | CG30: =H30*月別販売比率!$M$21 -> 26.276559 | CI30: =H30*月別販売比率!$R$21 -> 20.8 | CK30: =H30*月別販売比率!$W$21 -> 19.803347 | CL30: 50 | CM30: =H30*月別販売比率!$AB$21 -> 31.2 | CO30: =H30*月別販売比率!$AG$21 -> 26 | CP30: 40 | CQ30: =H30*月別販売比率!$AL$21 -> 23.4 | CR30: 30 | CS30: =H30*月別販売比率!$AQ$21 -> 26 | CT30: 35 | CU30: =H30*月別販売比率!$AV$21 -> 15.832538 | CW30: =H30*月別販売比率!$BA$21 -> 14.462011 | CY30: =H30*月別販売比率!$BF$21 -> 20.8
E31: +2.50 | F31: 28 | G31: =F31*3630 -> 101640 | H31: =F31*($H$27/$F$27) -> 143.58499 | I31: =H31*3630 -> 521213.51 | J31: 7 | K31: =SUM(L31:N31) -> 27 | L31: 7 | M31: 20 | Q31: 45631 | AI31: =SUM(J31:K31)-CI31+CJ31 -> 22.513201 | AJ31: =AI31-CK31+CL31 -> 31.576803 | AK31: =AJ31-CM31+CN31 -> 14.346605 | AL31: =AK31-CO31+CP31 -> 19.988106 | AM31: =AL31-CQ31+CR31 -> 32.065457 | AN31: =AM31-CS31+CT31 -> 42.706958 | AO31: =AN31-CU31+CV31 -> 33.963439 | AP31: =AO31-CW31+CX31 -> 25.976794 | AQ31: =AP31-CY31+CZ31 -> 14.489995 | AS31: =$H$31*月別販売比率!AG5 -> 14.358499 | AU31: =$H$31*月別販売比率!AL5 -> 12.922649 | AW31: =$H$31*月別販売比率!AQ5 -> 14.358499 | AX31: 25 | AY31: =$H$31*月別販売比率!AV5 -> 8.7435182 | AZ31: 12 | BA31: =$H$31*月別販売比率!BA5 -> 7.9866452 | BB31: 12 | BC31: =$H$31*月別販売比率!BF5 -> 11.486799 | BE31: =$H$31*月別販売比率!C21 -> 10.175043 | BF31: 48 | BG31: =$H$31*月別販売比率!H21 -> 10.050949 | BI31: =$H$31*月別販売比率!M21 -> 14.511229 | BK31: =$H$31*月別販売比率!R21 -> 11.486799 | BL31: 25 | BM31: =$H$31*月別販売比率!W21 -> 10.936398 | BO31: =$H$31*月別販売比率!AB21 -> 17.230199 | BP31: 40 | BQ31: =$H$31*月別販売比率!AG21 -> 14.358499 | BS31: =$H$31*月別販売比率!AL21 -> 12.922649 | BT31: 0 | BU31: =$H$31*月別販売比率!AQ21 -> 14.358499 | BW31: =$H$31*月別販売比率!AV21 -> 8.7435182 | BX31: 35 | BY31: =$H$31*月別販売比率!BA21 -> 7.9866452 | CA31: =$H$31*月別販売比率!BF21 -> 11.486799 | CC31: =H31*月別販売比率!$C$21 -> 10.175043 | CE31: =H31*月別販売比率!$H$21 -> 10.050949 | CF31: 32 | CG31: =H31*月別販売比率!$M$21 -> 14.511229 | CI31: =H31*月別販売比率!$R$21 -> 11.486799 | CK31: =H31*月別販売比率!$W$21 -> 10.936398 | CL31: 20 | CM31: =H31*月別販売比率!$AB$21 -> 17.230199 | CO31: =H31*月別販売比率!$AG$21 -> 14.358499 | CP31: 20 | CQ31: =H31*月別販売比率!$AL$21 -> 12.922649 | CR31: 25 | CS31: =H31*月別販売比率!$AQ$21 -> 14.358499 | CT31: 25 | CU31: =H31*月別販売比率!$AV$21 -> 8.7435182 | CW31: =H31*月別販売比率!$BA$21 -> 7.9866452 | CY31: =H31*月別販売比率!$BF$21 -> 11.486799
E32: +3.00 | F32: 17 | G32: =F32*3630 -> 61710 | H32: =F32*($H$27/$F$27) -> 87.1766 | I32: =H32*3630 -> 316451.06 | J32: 4 | K32: =SUM(L32:N32) -> 21 | L32: 3 | M32: 18 | Q32: 45631 | R32: 45685 | AD32: 46045 | AI32: =SUM(J32:K32)-CI32+CJ32 -> 18.025872 | AJ32: =AI32-CK32+CL32 -> 31.385916 | AK32: =AJ32-CM32+CN32 -> 20.924724 | AL32: =AK32-CO32+CP32 -> 12.207064 | AM32: =AL32-CQ32+CR32 -> 14.36117 | AN32: =AM32-CS32+CT32 -> 15.64351 | AO32: =AN32-CU32+CV32 -> 10.334945 | AP32: =AO32-CW32+CX32 -> 5.4859108 | AQ32: =AP32-CY32+CZ32 -> -1.4882172 | AS32: =$H$32*月別販売比率!AG5 -> 8.71766 | AU32: =$H$32*月別販売比率!AL5 -> 7.845894 | AW32: =$H$32*月別販売比率!AQ5 -> 8.71766 | AX32: 15 | AY32: =$H$32*月別販売比率!AV5 -> 5.3085646 | AZ32: 12 | BA32: =$H$32*月別販売比率!BA5 -> 4.8490346 | BB32: 12 | BC32: =$H$32*月別販売比率!BF5 -> 6.974128 | BE32: =$H$32*月別販売比率!C21 -> 6.1777045 | BF32: 24 | BG32: =$H$32*月別販売比率!H21 -> 6.102362 | BI32: =$H$32*月別販売比率!M21 -> 8.8103888 | BK32: =$H$32*月別販売比率!R21 -> 6.974128 | BL32: 10 | BM32: =$H$32*月別販売比率!W21 -> 6.6399557 | BO32: =$H$32*月別販売比率!AB21 -> 10.461192 | BP32: 30 | BQ32: =$H$32*月別販売比率!AG21 -> 8.71766 | BS32: =$H$32*月別販売比率!AL21 -> 7.845894 | BT32: 0 | BU32: =$H$32*月別販売比率!AQ21 -> 8.71766 | BW32: =$H$32*月別販売比率!AV21 -> 5.3085646 | BX32: 12 | BY32: =$H$32*月別販売比率!BA21 -> 4.8490346 | CA32: =$H$32*月別販売比率!BF21 -> 6.974128 | CC32: =H32*月別販売比率!$C$21 -> 6.1777045 | CE32: =H32*月別販売比率!$H$21 -> 6.102362 | CF32: 22 | CG32: =H32*月別販売比率!$M$21 -> 8.8103888 | CI32: =H32*月別販売比率!$R$21 -> 6.974128 | CK32: =H32*月別販売比率!$W$21 -> 6.6399557 | CL32: 20 | CM32: =H32*月別販売比率!$AB$21 -> 10.461192 | CO32: =H32*月別販売比率!$AG$21 -> 8.71766 | CQ32: =H32*月別販売比率!$AL$21 -> 7.845894 | CR32: 10 | CS32: =H32*月別販売比率!$AQ$21 -> 8.71766 | CT32: 10 | CU32: =H32*月別販売比率!$AV$21 -> 5.3085646 | CW32: =H32*月別販売比率!$BA$21 -> 4.8490346 | CY32: =H32*月別販売比率!$BF$21 -> 6.974128
D33: 2 | E33: +1.00 | F33: 76 | G33: =F33*3630 -> 275880 | H33: =F33*($H$27/$F$27) -> 389.73068 | I33: =H33*3630 -> 1414722.4 | J33: 68 | K33: =SUM(L33:N33) -> 23 | L33: 1 | M33: 22 | T33: 45721 | X33: 45869 | AI33: =SUM(J33:K33)-CI33+CJ33 -> 59.821545 | AJ33: =AI33-CK33+CL33 -> 80.137037 | AK33: =AJ33-CM33+CN33 -> 33.369355 | AL33: =AK33-CO33+CP33 -> 34.396287 | AM33: =AL33-CQ33+CR33 -> 54.320525 | AN33: =AM33-CS33+CT33 -> 70.347457 | AO33: =AN33-CU33+CV33 -> 46.61505 | AP33: =AO33-CW33+CX33 -> 24.937013 | AQ33: =AP33-CY33+CZ33 -> -6.2414416 | AS33: =$H$33*月別販売比率!AG5 -> 38.973068 | AU33: =$H$33*月別販売比率!AL5 -> 35.075762 | AW33: =$H$33*月別販売比率!AQ5 -> 38.973068 | AX33: 45 | AY33: =$H$33*月別販売比率!AV5 -> 23.732407 | AZ33: 42 | BA33: =$H$33*月別販売比率!BA5 -> 21.678037 | BB33: 42 | BC33: =$H$33*月別販売比率!BF5 -> 31.178455 | BE33: =$H$33*月別販売比率!C21 -> 27.617973 | BF33: 45 | BG33: =$H$33*月別販売比率!H21 -> 27.281148 | BI33: =$H$33*月別販売比率!M21 -> 39.387621 | BJ33: 75 | BK33: =$H$33*月別販売比率!R21 -> 31.178455 | BL33: 110 | BM33: =$H$33*月別販売比率!W21 -> 29.684508 | BO33: =$H$33*月別販売比率!AB21 -> 46.767682 | BP33: 100 | BQ33: =$H$33*月別販売比率!AG21 -> 38.973068 | BS33: =$H$33*月別販売比率!AL21 -> 35.075762 | BT33: 60 | BU33: =$H$33*月別販売比率!AQ21 -> 38.973068 | BW33: =$H$33*月別販売比率!AV21 -> 23.732407 | BX33: 110 | BY33: =$H$33*月別販売比率!BA21 -> 21.678037 | CA33: =$H$33*月別販売比率!BF21 -> 31.178455 | CC33: =H33*月別販売比率!$C$21 -> 27.617973 | CE33: =H33*月別販売比率!$H$21 -> 27.281148 | CF33: 77 | CG33: =H33*月別販売比率!$M$21 -> 39.387621 | CI33: =H33*月別販売比率!$R$21 -> 31.178455 | CK33: =H33*月別販売比率!$W$21 -> 29.684508 | CL33: 50 | CM33: =H33*月別販売比率!$AB$21 -> 46.767682 | CO33: =H33*月別販売比率!$AG$21 -> 38.973068 | CP33: 40 | CQ33: =H33*月別販売比率!$AL$21 -> 35.075762 | CR33: 55 | CS33: =H33*月別販売比率!$AQ$21 -> 38.973068 | CT33: 55 | CU33: =H33*月別販売比率!$AV$21 -> 23.732407 | CW33: =H33*月別販売比率!$BA$21 -> 21.678037 | CY33: =H33*月別販売比率!$BF$21 -> 31.178455
E34: +1.50 | F34: 94 | G34: =F34*3630 -> 341220 | H34: =F34*($H$27/$F$27) -> 482.03532 | I34: =H34*3630 -> 1749788.2 | J34: 142 | K34: =SUM(L34:N34) -> 24 | L34: 6 | M34: 18 | R34: 45685 | X34: 45856 | AI34: =SUM(J34:K34)-CI34+CJ34 -> 127.43717 | AJ34: =AI34-CK34+CL34 -> 140.72212 | AK34: =AJ34-CM34+CN34 -> 82.877887 | AL34: =AK34-CO34+CP34 -> 74.674355 | AM34: =AL34-CQ34+CR34 -> 81.291176 | AN34: =AM34-CS34+CT34 -> 88.087644 | AO34: =AN34-CU34+CV34 -> 58.734404 | AP34: =AO34-CW34+CX34 -> 31.922095 | AQ34: =AP34-CY34+CZ34 -> -6.6407304 | AS34: =$H$34*月別販売比率!AG5 -> 48.203532 | AU34: =$H$34*月別販売比率!AL5 -> 43.383179 | AW34: =$H$34*月別販売比率!AQ5 -> 48.203532 | AX34: 45 | AY34: =$H$34*月別販売比率!AV5 -> 29.35324 | AZ34: 48 | BA34: =$H$34*月別販売比率!BA5 -> 26.812309 | BB34: 48 | BC34: =$H$34*月別販売比率!BF5 -> 38.562826 | BE34: =$H$34*月別販売比率!C21 -> 34.159072 | BF34: 60 | BG34: =$H$34*月別販売比率!H21 -> 33.742472 | BI34: =$H$34*月別販売比率!M21 -> 48.716268 | BJ34: 95 | BK34: =$H$34*月別販売比率!R21 -> 38.562826 | BL34: 130 | BM34: =$H$34*月別販売比率!W21 -> 36.715049 | BO34: =$H$34*月別販売比率!AB21 -> 57.844238 | BP34: 125 | BQ34: =$H$34*月別販売比率!AG21 -> 48.203532 | BS34: =$H$34*月別販売比率!AL21 -> 43.383179 | BT34: 55 | BU34: =$H$34*月別販売比率!AQ21 -> 48.203532 | BW34: =$H$34*月別販売比率!AV21 -> 29.35324 | BX34: 120 | BY34: =$H$34*月別販売比率!BA21 -> 26.812309 | CA34: =$H$34*月別販売比率!BF21 -> 38.562826 | CC34: =H34*月別販売比率!$C$21 -> 34.159072 | CE34: =H34*月別販売比率!$H$21 -> 33.742472 | CF34: 97 | CG34: =H34*月別販売比率!$M$21 -> 48.716268 | CI34: =H34*月別販売比率!$R$21 -> 38.562826 | CK34: =H34*月別販売比率!$W$21 -> 36.715049 | CL34: 50 | CM34: =H34*月別販売比率!$AB$21 -> 57.844238 | CO34: =H34*月別販売比率!$AG$21 -> 48.203532 | CP34: 40 | CQ34: =H34*月別販売比率!$AL$21 -> 43.383179 | CR34: 50 | CS34: =H34*月別販売比率!$AQ$21 -> 48.203532 | CT34: 55 | CU34: =H34*月別販売比率!$AV$21 -> 29.35324 | CW34: =H34*月別販売比率!$BA$21 -> 26.812309 | CY34: =H34*月別販売比率!$BF$21 -> 38.562826
E35: +2.00 | F35: 96 | G35: =F35*3630 -> 348480 | H35: =F35*($H$27/$F$27) -> 492.29139 | I35: =H35*3630 -> 1787017.7 | J35: 194 | K35: =SUM(L35:N35) -> 31 | L35: 10 | M35: 21 | Q35: 45631 | R35: 45685 | AB35: 45971 | AC35: 45971 | AI35: =SUM(J35:K35)-CI35+CJ35 -> 185.61669 | AJ35: =AI35-CK35+CL35 -> 188.12047 | AK35: =AJ35-CM35+CN35 -> 129.0455 | AL35: =AK35-CO35+CP35 -> 119.81636 | AM35: =AL35-CQ35+CR35 -> 105.51014 | AN35: =AM35-CS35+CT35 -> 111.281 | AO35: =AN35-CU35+CV35 -> 81.303221 | AP35: =AO35-CW35+CX35 -> 53.920438 | AQ35: =AP35-CY35+CZ35 -> 14.537126 | AS35: =$H$35*月別販売比率!AG5 -> 49.229139 | AU35: =$H$35*月別販売比率!AL5 -> 44.306225 | AW35: =$H$35*月別販売比率!AQ5 -> 49.229139 | AX35: 45 | AY35: =$H$35*月別販売比率!AV5 -> 29.977777 | AZ35: 36 | BA35: =$H$35*月別販売比率!BA5 -> 27.382783 | BB35: 36 | BC35: =$H$35*月別販売比率!BF5 -> 39.383311 | BE35: =$H$35*月別販売比率!C21 -> 34.885861 | BF35: 70 | BG35: =$H$35*月別販売比率!H21 -> 34.460397 | BI35: =$H$35*月別販売比率!M21 -> 49.752784 | BJ35: 90 | BK35: =$H$35*月別販売比率!R21 -> 39.383311 | BL35: 140 | BM35: =$H$35*月別販売比率!W21 -> 37.496221 | BO35: =$H$35*月別販売比率!AB21 -> 59.074967 | BP35: 115 | BQ35: =$H$35*月別販売比率!AG21 -> 49.229139 | BS35: =$H$35*月別販売比率!AL21 -> 44.306225 | BT35: 40 | BU35: =$H$35*月別販売比率!AQ21 -> 49.229139 | BW35: =$H$35*月別販売比率!AV21 -> 29.977777 | BX35: 120 | BY35: =$H$35*月別販売比率!BA21 -> 27.382783 | CA35: =$H$35*月別販売比率!BF21 -> 39.383311 | CC35: =H35*月別販売比率!$C$21 -> 34.885861 | CE35: =H35*月別販売比率!$H$21 -> 34.460397 | CF35: 47 | CG35: =H35*月別販売比率!$M$21 -> 49.752784 | CI35: =H35*月別販売比率!$R$21 -> 39.383311 | CK35: =H35*月別販売比率!$W$21 -> 37.496221 | CL35: 40 | CM35: =H35*月別販売比率!$AB$21 -> 59.074967 | CO35: =H35*月別販売比率!$AG$21 -> 49.229139 | CP35: 40 | CQ35: =H35*月別販売比率!$AL$21 -> 44.306225 | CR35: 30 | CS35: =H35*月別販売比率!$AQ$21 -> 49.229139 | CT35: 55 | CU35: =H35*月別販売比率!$AV$21 -> 29.977777 | CW35: =H35*月別販売比率!$BA$21 -> 27.382783 | CY35: =H35*月別販売比率!$BF$21 -> 39.383311
E36: +2.50 | F36: 31 | G36: =F36*3630 -> 112530 | H36: =F36*($H$27/$F$27) -> 158.96909 | I36: =H36*3630 -> 577057.81 | J36: 49 | K36: =SUM(L36:N36) -> 22 | L36: 8 | M36: 14 | Q36: 45631 | AI36: =SUM(J36:K36)-CI36+CJ36 -> 58.282472 | AJ36: =AI36-CK36+CL36 -> 46.174318 | AK36: =AJ36-CM36+CN36 -> 27.098026 | AL36: =AK36-CO36+CP36 -> 11.201117 | AM36: =AL36-CQ36+CR36 -> 21.893898 | AN36: =AM36-CS36+CT36 -> 30.996989 | AO36: =AN36-CU36+CV36 -> 21.316665 | AP36: =AO36-CW36+CX36 -> 12.474308 | AQ36: =AP36-CY36+CZ36 -> -0.24321961 | AS36: =$H$36*月別販売比率!AG5 -> 15.896909 | AU36: =$H$36*月別販売比率!AL5 -> 14.307219 | AW36: =$H$36*月別販売比率!AQ5 -> 15.896909 | AX36: 25 | AY36: =$H$36*月別販売比率!AV5 -> 9.6803238 | AZ36: 12 | BA36: =$H$36*月別販売比率!BA5 -> 8.8423572 | BB36: 12 | BC36: =$H$36*月別販売比率!BF5 -> 12.717528 | BE36: =$H$36*月別販売比率!C21 -> 11.265226 | BF36: 43 | BG36: =$H$36*月別販売比率!H21 -> 11.127837 | BI36: =$H$36*月別販売比率!M21 -> 16.066003 | BJ36: 10 | BK36: =$H$36*月別販売比率!R21 -> 12.717528 | BL36: 30 | BM36: =$H$36*月別販売比率!W21 -> 12.108155 | BO36: =$H$36*月別販売比率!AB21 -> 19.076291 | BP36: 45 | BQ36: =$H$36*月別販売比率!AG21 -> 15.896909 | BS36: =$H$36*月別販売比率!AL21 -> 14.307219 | BT36: 15 | BU36: =$H$36*月別販売比率!AQ21 -> 15.896909 | BW36: =$H$36*月別販売比率!AV21 -> 9.6803238 | BX36: 45 | BY36: =$H$36*月別販売比率!BA21 -> 8.8423572 | CA36: =$H$36*月別販売比率!BF21 -> 12.717528 | CC36: =H36*月別販売比率!$C$21 -> 11.265226 | CE36: =H36*月別販売比率!$H$21 -> 11.127837 | CF36: 42 | CG36: =H36*月別販売比率!$M$21 -> 16.066003 | CI36: =H36*月別販売比率!$R$21 -> 12.717528 | CK36: =H36*月別販売比率!$W$21 -> 12.108155 | CM36: =H36*月別販売比率!$AB$21 -> 19.076291 | CO36: =H36*月別販売比率!$AG$21 -> 15.896909 | CQ36: =H36*月別販売比率!$AL$21 -> 14.307219 | CR36: 25 | CS36: =H36*月別販売比率!$AQ$21 -> 15.896909 | CT36: 25 | CU36: =H36*月別販売比率!$AV$21 -> 9.6803238 | CW36: =H36*月別販売比率!$BA$21 -> 8.8423572 | CY36: =H36*月別販売比率!$BF$21 -> 12.717528
E37: +3.00 | F37: 23 | G37: =F37*3630 -> 83490 | H37: =F37*($H$27/$F$27) -> 117.94481 | I37: =H37*3630 -> 428139.67 | J37: 37 | K37: =SUM(L37:N37) -> 23 | L37: 4 | M37: 19 | AI37: =SUM(J37:K37)-CI37+CJ37 -> 50.564415 | AJ37: =AI37-CK37+CL37 -> 51.580945 | AK37: =AJ37-CM37+CN37 -> 37.427568 | AL37: =AK37-CO37+CP37 -> 25.633087 | AM37: =AL37-CQ37+CR37 -> 25.018054 | AN37: =AM37-CS37+CT37 -> 28.223572 | AO37: =AN37-CU37+CV37 -> 21.041397 | AP37: =AO37-CW37+CX37 -> 14.480938 | AQ37: =AP37-CY37+CZ37 -> 5.0453532 | AS37: =$H$37*月別販売比率!AG5 -> 11.794481 | AU37: =$H$37*月別販売比率!AL5 -> 10.615033 | AW37: =$H$37*月別販売比率!AQ5 -> 11.794481 | AX37: 20 | AY37: =$H$37*月別販売比率!AV5 -> 7.1821757 | AZ37: 12 | BA37: =$H$37*月別販売比率!BA5 -> 6.5604585 | BB37: 12 | BC37: =$H$37*月別販売比率!BF5 -> 9.435585 | BE37: =$H$37*月別販売比率!C21 -> 8.3580708 | BF37: 10 | BG37: =$H$37*月別販売比率!H21 -> 8.2561369 | BI37: =$H$37*月別販売比率!M21 -> 11.919938 | BJ37: 30 | BK37: =$H$37*月別販売比率!R21 -> 9.435585 | BM37: =$H$37*月別販売比率!W21 -> 8.9834695 | BO37: =$H$37*月別販売比率!AB21 -> 14.153377 | BP37: 35 | BQ37: =$H$37*月別販売比率!AG21 -> 11.794481 | BS37: =$H$37*月別販売比率!AL21 -> 10.615033 | BT37: 20 | BU37: =$H$37*月別販売比率!AQ21 -> 11.794481 | BW37: =$H$37*月別販売比率!AV21 -> 7.1821757 | BX37: 30 | BY37: =$H$37*月別販売比率!BA21 -> 6.5604585 | CA37: =$H$37*月別販売比率!BF21 -> 9.435585 | CC37: =H37*月別販売比率!$C$21 -> 8.3580708 | CE37: =H37*月別販売比率!$H$21 -> 8.2561369 | CF37: 12 | CG37: =H37*月別販売比率!$M$21 -> 11.919938 | CI37: =H37*月別販売比率!$R$21 -> 9.435585 | CK37: =H37*月別販売比率!$W$21 -> 8.9834695 | CL37: 10 | CM37: =H37*月別販売比率!$AB$21 -> 14.153377 | CO37: =H37*月別販売比率!$AG$21 -> 11.794481 | CQ37: =H37*月別販売比率!$AL$21 -> 10.615033 | CR37: 10 | CS37: =H37*月別販売比率!$AQ$21 -> 11.794481 | CT37: 15 | CU37: =H37*月別販売比率!$AV$21 -> 7.1821757 | CW37: =H37*月別販売比率!$BA$21 -> 6.5604585 | CY37: =H37*月別販売比率!$BF$21 -> 9.435585
B38: 3 | C38: flm-001 | F38: =SUM(F39:F48) -> 983 | G38: =SUM(G39:G48) -> 4108940 | H38: 2200 | I38: =SUM(I39:I48) -> 11182584 | J38: =SUM(J39:J48) -> 303 | K38: =SUM(K39:K48) -> 263 | L38: =SUM(L39:L48) -> 87 | M38: =SUM(M39:M48) -> 176 | N38: =SUM(N39:N48) -> 0 | AS38: =SUM(AS39:AS48) -> 267.52594 | AU38: =SUM(AU39:AU48) -> 240.77335 | AW38: =SUM(AW39:AW48) -> 267.52594 | AX38: =SUM(AX39:AX48) -> 610 | AY38: =SUM(AY39:AY48) -> 162.90825 | BA38: =SUM(BA39:BA48) -> 148.80628 | BC38: =SUM(BC39:BC48) -> 214.02075 | BE38: =SUM(BE39:BE48) -> 189.58025 | BF38: =SUM(BF39:BF48) -> 345 | BG38: =SUM(BG39:BG48) -> 187.26816 | BH38: =SUM(BH39:BH48) -> 403 | BI38: =SUM(BI39:BI48) -> 270.37159 | BJ38: =SUM(BJ39:BJ48) -> 630 | BK38: =SUM(BK39:BK48) -> 214.02075 | BL38: =SUM(BL39:BL48) -> 0 | ... CT38: =SUM(CT39:CT48) -> 740 | CU38: 162.90825 | CV38: =SUM(CV39:CV48) -> 0 | CW38: =SUM(CW39:CW48) -> 148.80628 | CX38: =SUM(CX39:CX48) -> 0 | CY38: =SUM(CY39:CY48) -> 214.02075 | CZ38: =SUM(CZ39:CZ48) -> 0
C39: 入荷：6月 570枚 7月 570枚 ●10月 330枚 （9月希望） 12月 330枚 12月② 300枚 | D39: 1 | E39: +1.00 | F39: 144 | G39: =F39*4180 -> 601920 | H39: =F39*($H$38/$F$38) -> 322.27874 | I39: =H39*4180 -> 1347125.1 | J39: 2 | K39: =SUM(L39:N39) -> 25 | L39: 7 | M39: 18 | V39: 45786 | AI39: =SUM(J39:K39)-CI39+CJ39 -> 71.217701 | AJ39: =AI39-CK39+CL39 -> 46.670786 | AK39: =AJ39-CM39+CN39 -> 7.9973377 | AL39: =AK39-CO39+CP39 -> 15.769464 | AM39: =AL39-CQ39+CR39 -> -13.235623 | AN39: =0-CS39+CT39 -> 57.772126 | AO39: =AN39-CU39+CV39 -> 38.147164 | AP39: =AO39-CW39+CX39 -> 20.221014 | AQ39: =AP39-CY39+CZ39 -> -5.5612846 | AS39: =$H$39*月別販売比率!AG5 -> 32.227874 | AU39: =$H$39*月別販売比率!AL5 -> 29.005086 | AW39: =$H$39*月別販売比率!AQ5 -> 32.227874 | AY39: =$H$39*月別販売比率!AV5 -> 19.624963 | BA39: =$H$39*月別販売比率!BA5 -> 17.926149 | BC39: =$H$39*月別販売比率!BF5 -> 25.782299 | BE39: =$H$39*月別販売比率!C21 -> 22.838041 | BF39: 50 | BG39: =$H$39*月別販売比率!H21 -> 22.559512 | BH39: 68 | BI39: =$H$39*月別販売比率!M21 -> 32.570678 | BJ39: 95 | BK39: =$H$39*月別販売比率!R21 -> 25.782299 | BM39: =$H$39*月別販売比率!W21 -> 24.546915 | BO39: =$H$39*月別販売比率!AB21 -> 38.673449 | BQ39: =$H$39*月別販売比率!AG21 -> 32.227874 | BR39: 70 | BS39: =$H$39*月別販売比率!AL21 -> 29.005086 | BT39: 70 | BU39: =$H$39*月別販売比率!AQ21 -> 32.227874 | BW39: =$H$39*月別販売比率!AV21 -> 19.624963 | BY39: =$H$39*月別販売比率!BA21 -> 17.926149 | CA39: =$H$39*月別販売比率!BF21 -> 25.782299 | CC39: =H39*月別販売比率!$C$21 -> 22.838041 | CE39: =H39*月別販売比率!$H$21 -> 22.559512 | CG39: =$H$39*月別販売比率!M21 -> 32.570678 | CH39: 17 | CI39: =H39*月別販売比率!$R$21 -> 25.782299 | CJ39: 70 | CK39: =H39*月別販売比率!$W$21 -> 24.546915 | CM39: =H39*月別販売比率!$AB$21 -> 38.673449 | CO39: =H39*月別販売比率!$AG$21 -> 32.227874 | CP39: 40 | CQ39: =H39*月別販売比率!$AL$21 -> 29.005086 | CS39: =H39*月別販売比率!$AQ$21 -> 32.227874 | CT39: 90 | CU39: =H39*月別販売比率!$AV$21 -> 19.624963 | CW39: =H39*月別販売比率!$BA$21 -> 17.926149 | CY39: =H39*月別販売比率!$BF$21 -> 25.782299
E40: +1.50 | F40: 226 | G40: =F40*4180 -> 944680 | H40: 550 | I40: =H40*4180 -> 2299000 | J40: 107 | K40: =SUM(L40:N40) -> 30 | L40: 10 | M40: 20 | V40: 45786 | AI40: =SUM(J40:K40)-CI40+CJ40 -> 193 | AJ40: =AI40-CK40+CL40 -> 151.1083 | AK40: =AJ40-CM40+CN40 -> 85.108304 | AL40: =AK40-CO40+CP40 -> 100.1083 | AM40: =AL40-CQ40+CR40 -> 50.608304 | AN40: =AM40-CS40+CT40 -> 145.6083 | AO40: =AN40-CU40+CV40 -> 112.1164 | AP40: =AO40-CW40+CX40 -> 81.523681 | AQ40: =AP40-CY40+CZ40 -> 37.523681 | AS40: =$H$40*月別販売比率!AG5 -> 55 | AU40: =$H$40*月別販売比率!AL5 -> 49.5 | AW40: =$H$40*月別販売比率!AQ5 -> 55 | AX40: 100 | AY40: =$H$40*月別販売比率!AV5 -> 33.491907 | BA40: =$H$40*月別販売比率!BA5 -> 30.592716 | BC40: =$H$40*月別販売比率!BF5 -> 44 | BE40: =$H$40*月別販売比率!C21 -> 38.975338 | BF40: 49 | BG40: =$H$40*月別販売比率!H21 -> 38.5 | BH40: 146 | BI40: =$H$40*月別販売比率!M21 -> 55.585029 | BJ40: 155 | BK40: =$H$40*月別販売比率!R21 -> 44 | BM40: =$H$40*月別販売比率!W21 -> 41.891696 | BO40: =$H$40*月別販売比率!AB21 -> 66 | BQ40: =$H$40*月別販売比率!AG21 -> 55 | BR40: 100 | BS40: =$H$40*月別販売比率!AL21 -> 49.5 | BT40: 95 | BU40: =$H$40*月別販売比率!AQ21 -> 55 | BW40: =$H$40*月別販売比率!AV21 -> 33.491907 | BY40: =$H$40*月別販売比率!BA21 -> 30.592716 | CA40: =$H$40*月別販売比率!BF21 -> 44 | CC40: =H40*月別販売比率!$C$21 -> 38.975338 | CE40: =H40*月別販売比率!$H$21 -> 38.5 | CG40: =$H$40*月別販売比率!M21 -> 55.585029 | CH40: 137 | CI40: =H40*月別販売比率!$R$21 -> 44 | CJ40: 100 | CK40: =H40*月別販売比率!$W$21 -> 41.891696 | CM40: =H40*月別販売比率!$AB$21 -> 66 | CO40: =H40*月別販売比率!$AG$21 -> 55 | CP40: 70 | CQ40: =H40*月別販売比率!$AL$21 -> 49.5 | CS40: =H40*月別販売比率!$AQ$21 -> 55 | CT40: 150 | CU40: =H40*月別販売比率!$AV$21 -> 33.491907 | CW40: =H40*月別販売比率!$BA$21 -> 30.592716 | CY40: =H40*月別販売比率!$BF$21 -> 44
E41: +2.00 | F41: 204 | G41: =F41*4180 -> 852720 | H41: =F41*($H$38/$F$38) -> 456.56155 | I41: =H41*4180 -> 1908427.3 | J41: 41 | K41: =SUM(L41:N41) -> 17 | L41: 5 | M41: 12 | V41: 45786 | AI41: =SUM(J41:K41)-CI41+CJ41 -> 101.47508 | AJ41: =AI41-CK41+CL41 -> 66.700281 | AK41: =AJ41-CM41+CN41 -> 11.912895 | AL41: =AK41-CO41+CP41 -> 51.256741 | AM41: =AL41-CQ41+CR41 -> 10.166201 | AN41: =AM41-CS41+CT41 -> 89.510047 | AO41: =AN41-CU41+CV41 -> 61.708016 | AP41: =AO41-CW41+CX41 -> 36.312638 | AQ41: =AP41-CY41+CZ41 -> -0.21228523 | AS41: =$H$41*月別販売比率!AG5 -> 45.656155 | AU41: =$H$41*月別販売比率!AL5 -> 41.090539 | AW41: =$H$41*月別販売比率!AQ5 -> 45.656155 | AX41: 100 | AY41: =$H$41*月別販売比率!AV5 -> 27.80203 | BA41: =$H$41*月別販売比率!BA5 -> 25.395378 | BC41: =$H$41*月別販売比率!BF5 -> 36.524924 | BE41: =$H$41*月別販売比率!C21 -> 32.353892 | BF41: 49 | BG41: =$H$41*月別販売比率!H21 -> 31.959308 | BH41: 131 | BI41: =$H$41*月別販売比率!M21 -> 46.141794 | BJ41: 135 | BK41: =$H$41*月別販売比率!R21 -> 36.524924 | BM41: =$H$41*月別販売比率!W21 -> 34.774796 | BO41: =$H$41*月別販売比率!AB21 -> 54.787386 | BQ41: =$H$41*月別販売比率!AG21 -> 45.656155 | BR41: 100 | BS41: =$H$41*月別販売比率!AL21 -> 41.090539 | BT41: 95 | BU41: =$H$41*月別販売比率!AQ21 -> 45.656155 | BW41: =$H$41*月別販売比率!AV21 -> 27.80203 | BY41: =$H$41*月別販売比率!BA21 -> 25.395378 | CA41: =$H$41*月別販売比率!BF21 -> 36.524924 | CC41: =H41*月別販売比率!$C$21 -> 32.353892 | CE41: =H41*月別販売比率!$H$21 -> 31.959308 | CG41: =$H$41*月別販売比率!M21 -> 46.141794 | CH41: 57 | CI41: =H41*月別販売比率!$R$21 -> 36.524924 | CJ41: 80 | CK41: =H41*月別販売比率!$W$21 -> 34.774796 | CM41: =H41*月別販売比率!$AB$21 -> 54.787386 | CO41: =H41*月別販売比率!$AG$21 -> 45.656155 | CP41: 85 | CQ41: =H41*月別販売比率!$AL$21 -> 41.090539 | CS41: =H41*月別販売比率!$AQ$21 -> 45.656155 | CT41: 125 | CU41: =H41*月別販売比率!$AV$21 -> 27.80203 | CW41: =H41*月別販売比率!$BA$21 -> 25.395378 | CY41: =H41*月別販売比率!$BF$21 -> 36.524924
E42: +2.50 | F42: 89 | G42: =F42*4180 -> 372020 | H42: =F42*($H$38/$F$38) -> 199.18616 | I42: =H42*4180 -> 832598.17 | J42: 21 | K42: =SUM(L42:N42) -> 31 | L42: 10 | M42: 21 | Q42: 45654 | AA42: 45950 | AI42: =SUM(J42:K42)-CI42+CJ42 -> 86.065107 | AJ42: =AI42-CK42+CL42 -> 70.89375 | AK42: =AJ42-CM42+CN42 -> 46.99141 | AL42: =AK42-CO42+CP42 -> 42.072794 | AM42: =AL42-CQ42+CR42 -> 24.146039 | AN42: =AM42-CS42+CT42 -> 59.227422 | AO42: =AN42-CU42+CV42 -> 47.098105 | AP42: =AO42-CW42+CX42 -> 36.018749 | AQ42: =AP42-CY42+CZ42 -> 20.083856 | AS42: =$H$42*月別販売比率!AG5 -> 19.918616 | AU42: =$H$42*月別販売比率!AL5 -> 17.926755 | AW42: =$H$42*月別販売比率!AQ5 -> 19.918616 | AX42: 100 | AY42: =$H$42*月別販売比率!AV5 -> 12.129317 | BA42: =$H$42*月別販売比率!BA5 -> 11.079356 | BC42: =$H$42*月別販売比率!BF5 -> 15.934893 | BE42: =$H$42*月別販売比率!C21 -> 14.115178 | BF42: 29 | BG42: =$H$42*月別販売比率!H21 -> 13.943032 | BH42: 31 | BI42: =$H$42*月別販売比率!M21 -> 20.130489 | BJ42: 60 | BK42: =$H$42*月別販売比率!R21 -> 15.934893 | BM42: =$H$42*月別販売比率!W21 -> 15.171357 | BO42: =$H$42*月別販売比率!AB21 -> 23.90234 | BQ42: =$H$42*月別販売比率!AG21 -> 19.918616 | BR42: 60 | BS42: =$H$42*月別販売比率!AL21 -> 17.926755 | BT42: 70 | BU42: =$H$42*月別販売比率!AQ21 -> 19.918616 | BW42: =$H$42*月別販売比率!AV21 -> 12.129317 | BY42: =$H$42*月別販売比率!BA21 -> 11.079356 | CA42: =$H$42*月別販売比率!BF21 -> 15.934893 | CC42: =H42*月別販売比率!$C$21 -> 14.115178 | CE42: =H42*月別販売比率!$H$21 -> 13.943032 | CG42: =$H$42*月別販売比率!M21 -> 20.130489 | CH42: 57 | CI42: =H42*月別販売比率!$R$21 -> 15.934893 | CJ42: 50 | CK42: =H42*月別販売比率!$W$21 -> 15.171357 | CM42: =H42*月別販売比率!$AB$21 -> 23.90234 | CO42: =H42*月別販売比率!$AG$21 -> 19.918616 | CP42: 15 | CQ42: =H42*月別販売比率!$AL$21 -> 17.926755 | CS42: =H42*月別販売比率!$AQ$21 -> 19.918616 | CT42: 55 | CU42: =H42*月別販売比率!$AV$21 -> 12.129317 | CW42: =H42*月別販売比率!$BA$21 -> 11.079356 | CY42: =H42*月別販売比率!$BF$21 -> 15.934893
E43: +3.00 | F43: 50 | G43: =F43*4180 -> 209000 | H43: =F43*($H$38/$F$38) -> 111.90234 | I43: =H43*4180 -> 467751.78 | J43: 0 | K43: =SUM(L43:N43) -> 22 | L43: 9 | M43: 13 | AA43: 45950 | AI43: =SUM(J43:K43)-CI43+CJ43 -> 43.047813 | AJ43: =AI43-CK43+CL43 -> 34.524579 | AK43: =AJ43-CM43+CN43 -> 21.096298 | AL43: =AK43-CO43+CP43 -> 19.906064 | AM43: =AL43-CQ43+CR43 -> 9.8348533 | AN43: =AM43-CS43+CT43 -> 38.644619 | AO43: =AN43-CU43+CV43 -> 31.830396 | AP43: =AO43-CW43+CX43 -> 25.606039 | AQ43: =AP43-CY43+CZ43 -> 16.653852 | AS43: =$H$43*月別販売比率!AG5 -> 11.190234 | AU43: =$H$43*月別販売比率!AL5 -> 10.071211 | AW43: =$H$43*月別販売比率!AQ5 -> 11.190234 | AY43: =$H$43*月別販売比率!AV5 -> 6.8142231 | BA43: =$H$43*月別販売比率!BA5 -> 6.2243574 | BC43: =$H$43*月別販売比率!BF5 -> 8.9521872 | BE43: =$H$43*月別販売比率!C21 -> 7.9298755 | BF43: 25 | BG43: =$H$43*月別販売比率!H21 -> 7.8331638 | BH43: 25 | BI43: =$H$43*月別販売比率!M21 -> 11.309263 | BJ43: 35 | BK43: =$H$43*月別販売比率!R21 -> 8.9521872 | BM43: =$H$43*月別販売比率!W21 -> 8.5232342 | BO43: =$H$43*月別販売比率!AB21 -> 13.428281 | BQ43: =$H$43*月別販売比率!AG21 -> 11.190234 | BR43: 30 | BS43: =$H$43*月別販売比率!AL21 -> 10.071211 | BT43: 30 | BU43: =$H$43*月別販売比率!AQ21 -> 11.190234 | BW43: =$H$43*月別販売比率!AV21 -> 6.8142231 | BY43: =$H$43*月別販売比率!BA21 -> 6.2243574 | CA43: =$H$43*月別販売比率!BF21 -> 8.9521872 | CC43: =H43*月別販売比率!$C$21 -> 7.9298755 | CE43: =H43*月別販売比率!$H$21 -> 7.8331638 | CG43: =$H$43*月別販売比率!M21 -> 11.309263 | CH43: 27 | CI43: =H43*月別販売比率!$R$21 -> 8.9521872 | CJ43: 30 | CK43: =H43*月別販売比率!$W$21 -> 8.5232342 | CM43: =H43*月別販売比率!$AB$21 -> 13.428281 | CO43: =H43*月別販売比率!$AG$21 -> 11.190234 | CP43: 10 | CQ43: =H43*月別販売比率!$AL$21 -> 10.071211 | CS43: =H43*月別販売比率!$AQ$21 -> 11.190234 | CT43: 40 | CU43: =H43*月別販売比率!$AV$21 -> 6.8142231 | CW43: =H43*月別販売比率!$BA$21 -> 6.2243574 | CY43: =H43*月別販売比率!$BF$21 -> 8.9521872
D44: 2 | E44: +1.00 | F44: 56 | G44: =F44*4180 -> 234080 | H44: =F44*($H$38/$F$38) -> 125.33062 | I44: =H44*4180 -> 523881.99 | J44: 12 | K44: =SUM(L44:N44) -> 34 | L44: 12 | M44: 22 | V44: 45786 | AI44: =SUM(J44:K44)-CI44+CJ44 -> 65.97355 | AJ44: =AI44-CK44+CL44 -> 56.427528 | AK44: =AJ44-CM44+CN44 -> 41.387854 | AL44: =AK44-CO44+CP44 -> 38.854792 | AM44: =AL44-CQ44+CR44 -> 27.575036 | AN44: =AM44-CS44+CT44 -> 35.041974 | AO44: =AN44-CU44+CV44 -> 27.410044 | AP44: =AO44-CW44+CX44 -> 20.438764 | AQ44: =AP44-CY44+CZ44 -> 10.412314 | AS44: =$H$44*月別販売比率!AG5 -> 12.533062 | AU44: =$H$44*月別販売比率!AL5 -> 11.279756 | AW44: =$H$44*月別販売比率!AQ5 -> 12.533062 | AX44: 50 | AY44: =$H$44*月別販売比率!AV5 -> 7.6319299 | BA44: =$H$44*月別販売比率!BA5 -> 6.9712802 | BC44: =$H$44*月別販売比率!BF5 -> 10.02645 | BE44: =$H$44*月別販売比率!C21 -> 8.8814606 | BF44: 44 | BG44: =$H$44*月別販売比率!H21 -> 8.7731434 | BH44: 1 | BI44: =$H$44*月別販売比率!M21 -> 12.666375 | BJ44: 40 | BK44: =$H$44*月別販売比率!R21 -> 10.02645 | BM44: =$H$44*月別販売比率!W21 -> 9.5460223 | BO44: =$H$44*月別販売比率!AB21 -> 15.039674 | BQ44: =$H$44*月別販売比率!AG21 -> 12.533062 | BR44: 30 | BS44: =$H$44*月別販売比率!AL21 -> 11.279756 | BT44: 60 | BU44: =$H$44*月別販売比率!AQ21 -> 12.533062 | BW44: =$H$44*月別販売比率!AV21 -> 7.6319299 | BY44: =$H$44*月別販売比率!BA21 -> 6.9712802 | CA44: =$H$44*月別販売比率!BF21 -> 10.02645 | CC44: =H44*月別販売比率!$C$21 -> 8.8814606 | CE44: =H44*月別販売比率!$H$21 -> 8.7731434 | CG44: =$H$44*月別販売比率!M21 -> 12.666375 | CH44: 37 | CI44: =H44*月別販売比率!$R$21 -> 10.02645 | CJ44: 30 | CK44: =H44*月別販売比率!$W$21 -> 9.5460223 | CM44: =H44*月別販売比率!$AB$21 -> 15.039674 | CO44: =H44*月別販売比率!$AG$21 -> 12.533062 | CP44: 10 | CQ44: =H44*月別販売比率!$AL$21 -> 11.279756 | CS44: =H44*月別販売比率!$AQ$21 -> 12.533062 | CT44: 20 | CU44: =H44*月別販売比率!$AV$21 -> 7.6319299 | CW44: =H44*月別販売比率!$BA$21 -> 6.9712802 | CY44: =H44*月別販売比率!$BF$21 -> 10.02645
E45: +1.50 | F45: 88 | G45: =F45*4180 -> 367840 | H45: 380 | I45: =H45*4180 -> 1588400 | J45: 67 | K45: =SUM(L45:N45) -> 25 | L45: 10 | M45: 15 | Q45: 45654 | AA45: 45950 | AI45: =SUM(J45:K45)-CI45+CJ45 -> 141.6 | AJ45: =AI45-CK45+CL45 -> 112.65665 | AK45: =AJ45-CM45+CN45 -> 67.056646 | AL45: =AK45-CO45+CP45 -> 74.056646 | AM45: =AL45-CQ45+CR45 -> 39.856646 | AN45: =AM45-CS45+CT45 -> 116.85665 | AO45: =AN45-CU45+CV45 -> 93.716784 | AP45: =AO45-CW45+CX45 -> 72.579998 | AQ45: =AP45-CY45+CZ45 -> 42.179998 | AS45: =$H$45*月別販売比率!AG5 -> 38 | AU45: =$H$45*月別販売比率!AL5 -> 34.2 | AW45: =$H$45*月別販売比率!AQ5 -> 38 | AX45: 100 | AY45: =$H$45*月別販売比率!AV5 -> 23.139863 | BA45: =$H$45*月別販売比率!BA5 -> 21.136786 | BC45: =$H$45*月別販売比率!BF5 -> 30.4 | BE45: =$H$45*月別販売比率!C21 -> 26.928415 | BF45: 55 | BG45: =$H$45*月別販売比率!H21 -> 26.6 | BI45: =$H$45*月別販売比率!M21 -> 38.404202 | BJ45: 60 | BK45: =$H$45*月別販売比率!R21 -> 30.4 | BM45: =$H$45*月別販売比率!W21 -> 28.943354 | BO45: =$H$45*月別販売比率!AB21 -> 45.6 | BP45: 80 | BQ45: =$H$45*月別販売比率!AG21 -> 38 | BS45: =$H$45*月別販売比率!AL21 -> 34.2 | BT45: 60 | BU45: =$H$45*月別販売比率!AQ21 -> 38 | BW45: =$H$45*月別販売比率!AV21 -> 23.139863 | BY45: =$H$45*月別販売比率!BA21 -> 21.136786 | CA45: =$H$45*月別販売比率!BF21 -> 30.4 | CC45: =H45*月別販売比率!$C$21 -> 26.928415 | CE45: =H45*月別販売比率!$H$21 -> 26.6 | CG45: =$H$45*月別販売比率!M21 -> 38.404202 | CH45: 97 | CI45: =H45*月別販売比率!$R$21 -> 30.4 | CJ45: 80 | CK45: =H45*月別販売比率!$W$21 -> 28.943354 | CM45: =H45*月別販売比率!$AB$21 -> 45.6 | CO45: =H45*月別販売比率!$AG$21 -> 38 | CP45: 45 | CQ45: =H45*月別販売比率!$AL$21 -> 34.2 | CS45: =H45*月別販売比率!$AQ$21 -> 38 | CT45: 115 | CU45: =H45*月別販売比率!$AV$21 -> 23.139863 | CW45: =H45*月別販売比率!$BA$21 -> 21.136786 | CY45: =H45*月別販売比率!$BF$21 -> 30.4
E46: +2.00 | F46: 66 | G46: =F46*4180 -> 275880 | H46: 300 | I46: =H46*4180 -> 1254000 | J46: 47 | K46: =SUM(L46:N46) -> 24 | L46: 9 | M46: 15 | Q46: 45654 | AI46: =SUM(J46:K46)-CI46+CJ46 -> 117 | AJ46: =AI46-CK46+CL46 -> 94.149984 | AK46: =AJ46-CM46+CN46 -> 58.149984 | AL46: =AK46-CO46+CP46 -> 58.149984 | AM46: =AL46-CQ46+CR46 -> 31.149984 | AN46: =AM46-CS46+CT46 -> 91.149984 | AO46: =AN46-CU46+CV46 -> 72.881671 | AP46: =AO46-CW46+CX46 -> 56.194735 | AQ46: =AP46-CY46+CZ46 -> 32.194735 | AS46: =$H$46*月別販売比率!AG5 -> 30 | AU46: =$H$46*月別販売比率!AL5 -> 27 | AW46: =$H$46*月別販売比率!AQ5 -> 30 | AX46: 90 | AY46: =$H$46*月別販売比率!AV5 -> 18.268313 | BA46: =$H$46*月別販売比率!BA5 -> 16.686936 | BC46: =$H$46*月別販売比率!BF5 -> 24 | BE46: =$H$46*月別販売比率!C21 -> 21.259275 | BF46: 20 | BG46: =$H$46*月別販売比率!H21 -> 21 | BI46: =$H$46*月別販売比率!M21 -> 30.319107 | BJ46: 40 | BK46: =$H$46*月別販売比率!R21 -> 24 | BM46: =$H$46*月別販売比率!W21 -> 22.850016 | BO46: =$H$46*月別販売比率!AB21 -> 36 | BP46: 70 | BQ46: =$H$46*月別販売比率!AG21 -> 30 | BS46: =$H$46*月別販売比率!AL21 -> 27 | BT46: 60 | BU46: =$H$46*月別販売比率!AQ21 -> 30 | BW46: =$H$46*月別販売比率!AV21 -> 18.268313 | BY46: =$H$46*月別販売比率!BA21 -> 16.686936 | CA46: =$H$46*月別販売比率!BF21 -> 24 | CC46: =H46*月別販売比率!$C$21 -> 21.259275 | CE46: =H46*月別販売比率!$H$21 -> 21 | CG46: =$H$46*月別販売比率!M21 -> 30.319107 | CH46: 77 | CI46: =H46*月別販売比率!$R$21 -> 24 | CJ46: 70 | CK46: =H46*月別販売比率!$W$21 -> 22.850016 | CM46: =H46*月別販売比率!$AB$21 -> 36 | CO46: =H46*月別販売比率!$AG$21 -> 30 | CP46: 30 | CQ46: =H46*月別販売比率!$AL$21 -> 27 | CS46: =H46*月別販売比率!$AQ$21 -> 30 | CT46: 90 | CU46: =H46*月別販売比率!$AV$21 -> 18.268313 | CW46: =H46*月別販売比率!$BA$21 -> 16.686936 | CY46: =H46*月別販売比率!$BF$21 -> 24
E47: +2.50 | F47: 37 | G47: =F47*4180 -> 154660 | H47: 130 | I47: =H47*4180 -> 543400 | J47: 6 | K47: =SUM(L47:N47) -> 29 | L47: 10 | M47: 19 | Q47: 45654 | AI47: =SUM(J47:K47)-CI47+CJ47 -> 54.6 | AJ47: =AI47-CK47+CL47 -> 44.698326 | AK47: =AJ47-CM47+CN47 -> 29.098326 | AL47: =AK47-CO47+CP47 -> 31.098326 | AM47: =AL47-CQ47+CR47 -> 19.398326 | AN47: =AM47-CS47+CT47 -> 41.398326 | AO47: =AN47-CU47+CV47 -> 33.482058 | AP47: =AO47-CW47+CX47 -> 26.251052 | AQ47: =AP47-CY47+CZ47 -> 15.851052 | AS47: =$H$47*月別販売比率!AG5 -> 13 | AU47: =$H$47*月別販売比率!AL5 -> 11.7 | AW47: =$H$47*月別販売比率!AQ5 -> 13 | AX47: 70 | AY47: =$H$47*月別販売比率!AV5 -> 7.9162688 | BA47: =$H$47*月別販売比率!BA5 -> 7.2310057 | BC47: =$H$47*月別販売比率!BF5 -> 10.4 | BE47: =$H$47*月別販売比率!C21 -> 9.2123526 | BF47: 0 | BG47: =$H$47*月別販売比率!H21 -> 9.1 | BI47: =$H$47*月別販売比率!M21 -> 13.13828 | BJ47: 0 | BK47: =$H$47*月別販売比率!R21 -> 10.4 | BM47: =$H$47*月別販売比率!W21 -> 9.9016736 | BO47: =$H$47*月別販売比率!AB21 -> 15.6 | BP47: 40 | BQ47: =$H$47*月別販売比率!AG21 -> 13 | BS47: =$H$47*月別販売比率!AL21 -> 11.7 | BT47: 30 | BU47: =$H$47*月別販売比率!AQ21 -> 13 | BW47: =$H$47*月別販売比率!AV21 -> 7.9162688 | BY47: =$H$47*月別販売比率!BA21 -> 7.2310057 | CA47: =$H$47*月別販売比率!BF21 -> 10.4 | CC47: =H47*月別販売比率!$C$21 -> 9.2123526 | CE47: =H47*月別販売比率!$H$21 -> 9.1 | CG47: =$H$47*月別販売比率!M21 -> 13.13828 | CH47: 37 | CI47: =H47*月別販売比率!$R$21 -> 10.4 | CJ47: 30 | CK47: =H47*月別販売比率!$W$21 -> 9.9016736 | CM47: =H47*月別販売比率!$AB$21 -> 15.6 | CO47: =H47*月別販売比率!$AG$21 -> 13 | CP47: 15 | CQ47: =H47*月別販売比率!$AL$21 -> 11.7 | CS47: =H47*月別販売比率!$AQ$21 -> 13 | CT47: 35 | CU47: =H47*月別販売比率!$AV$21 -> 7.9162688 | CW47: =H47*月別販売比率!$BA$21 -> 7.2310057 | CY47: =H47*月別販売比率!$BF$21 -> 10.4
E48: +3.00 | F48: 23 | G48: =F48*4180 -> 96140 | H48: 100 | I48: =H48*4180 -> 418000 | J48: 0 | K48: =SUM(L48:N48) -> 26 | L48: 5 | M48: 21 | V48: 45786 | AI48: =SUM(J48:K48)-CI48+CJ48 -> 48 | AJ48: =AI48-CK48+CL48 -> 40.383328 | AK48: =AJ48-CM48+CN48 -> 28.383328 | AL48: =AK48-CO48+CP48 -> 28.383328 | AM48: =AL48-CQ48+CR48 -> 19.383328 | AN48: =AM48-CS48+CT48 -> 29.383328 | AO48: =AN48-CU48+CV48 -> 23.29389 | AP48: =AO48-CW48+CX48 -> 17.731578 | AQ48: =AP48-CY48+CZ48 -> 9.7315783 | AS48: =$H$48*月別販売比率!AG5 -> 10 | AU48: =$H$48*月別販売比率!AL5 -> 9 | AW48: =$H$48*月別販売比率!AQ5 -> 10 | AY48: =$H$48*月別販売比率!AV5 -> 6.0894375 | BA48: =$H$48*月別販売比率!BA5 -> 5.5623121 | BC48: =$H$48*月別販売比率!BF5 -> 8 | BE48: =$H$48*月別販売比率!C21 -> 7.0864251 | BF48: 24 | BG48: =$H$48*月別販売比率!H21 -> 7 | BH48: 1 | BI48: =$H$48*月別販売比率!M21 -> 10.106369 | BJ48: 10 | BK48: =$H$48*月別販売比率!R21 -> 8 | BM48: =$H$48*月別販売比率!W21 -> 7.616672 | BO48: =$H$48*月別販売比率!AB21 -> 12 | BP48: 20 | BQ48: =$H$48*月別販売比率!AG21 -> 10 | BS48: =$H$48*月別販売比率!AL21 -> 9 | BT48: 30 | BU48: =$H$48*月別販売比率!AQ21 -> 10 | BW48: =$H$48*月別販売比率!AV21 -> 6.0894375 | BY48: =$H$48*月別販売比率!BA21 -> 5.5623121 | CA48: =$H$48*月別販売比率!BF21 -> 8 | CC48: =H48*月別販売比率!$C$21 -> 7.0864251 | CE48: =H48*月別販売比率!$H$21 -> 7 | CG48: =$H$48*月別販売比率!M21 -> 10.106369 | CH48: 27 | CI48: =H48*月別販売比率!$R$21 -> 8 | CJ48: 30 | CK48: =H48*月別販売比率!$W$21 -> 7.616672 | CM48: =H48*月別販売比率!$AB$21 -> 12 | CO48: =H48*月別販売比率!$AG$21 -> 10 | CP48: 10 | CQ48: =H48*月別販売比率!$AL$21 -> 9 | CS48: =H48*月別販売比率!$AQ$21 -> 10 | CT48: 20 | CU48: =H48*月別販売比率!$AV$21 -> 6.0894375 | CW48: =H48*月別販売比率!$BA$21 -> 5.5623121 | CY48: =H48*月別販売比率!$BF$21 -> 8
B49: 4 | C49: fll-3004 | F49: =SUM(F50:F64) -> 1702 | G49: =SUM(G50:G63) -> 5097400 | H49: 1700 | I49: =SUM(I50:I63) -> 8281164.5 | J49: =SUM(J50:J63) -> -2 | K49: =SUM(K50:K63) -> 449 | L49: =SUM(L50:L63) -> 121 | M49: =SUM(M50:M63) -> 198 | N49: =SUM(N50:N63) -> 130 | AS49: =SUM(AS50:AS63) -> 268.86898 | AT49: =SUM(AT50:AT63) -> 0 | AU49: =SUM(AU50:AU63) -> 268.86898 | AV49: =SUM(AV50:AV63) -> 341 | AW49: =SUM(AW50:AW63) -> 268.86898 | AX49: =SUM(AX50:AX63) -> 0 | AY49: =SUM(AY50:AY63) -> 163.72608 | AZ49: =SUM(AZ50:AZ64) -> 415 | BA49: =SUM(BA50:BA63) -> 149.55332 | BB49: =SUM(BB50:BB63) -> 0 | BC49: =SUM(BC50:BC63) -> 215.09518 | BD49: =SUM(BD50:BD63) -> 0 | BE49: =SUM(BE50:BE63) -> 190.53199 | BF49: =SUM(BF50:BF63) -> 260 | BG49: =SUM(BG50:BG63) -> 188.20828 | BH49: =SUM(BH50:BH63) -> 325 | ... BK49: =SUM(BK50:BK63) -> 215.09518 | BL49: =SUM(BL50:BL64) -> 340 | BM49: =SUM(BM50:BM63) -> 204.78868 | BN49: =SUM(BN50:BN64) -> 295 | BO49: =SUM(BO50:BO63) -> 322.64277 | BP49: =SUM(BP50:BP64) -> 0 | BQ49: =SUM(BQ50:BQ63) -> 268.86898 | BR49: =SUM(BR50:BR63) -> 430 | BS49: =SUM(BS50:BS63) -> 241.98208 | BT49: =SUM(BT50:BT64) -> 350 | BU49: =SUM(BU50:BU63) -> 268.86898 | BV49: =SUM(BV50:BV64) -> 240 | BW49: =SUM(BW50:BW63) -> 163.72608 | BX49: =SUM(BX50:BX63) -> 0 | BY49: =SUM(BY50:BY63) -> 149.55332 | BZ49: =SUM(BZ50:BZ63) -> 0 | CA49: =SUM(CA50:CA63) -> 215.09518 | CB49: =SUM(CB50:CB63) -> 0 | CC49: =SUM(CC50:CC63) -> 190.53199 | CD49: =SUM(CD50:CD63) -> 0 | CE49: =SUM(CE50:CE63) -> 188.20828 | CF49: =SUM(CF50:CF64) -> 597 | CG49: =SUM(CG50:CG63) -> 271.72891 | CH49: =SUM(CH50:CH63) -> 0 | CI49: =SUM(CI50:CI63) -> 215.09518 | CJ49: =SUM(CJ50:CJ64) -> 233 | CK49: =SUM(CK50:CK63) -> 204.78868 | CL49: =SUM(CL50:CL64) -> 315 | CM49: =SUM(CM50:CM63) -> 322.64277 | CN49: =SUM(CN50:CN63) -> 0 | CO49: =SUM(CO50:CO63) -> 268.86898 | CP49: =SUM(CP50:CP63) -> 355 | CQ49: =SUM(CQ50:CQ63) -> 241.98208 | CR49: =SUM(CR50:CR63) -> 495 | CS49: =SUM(CS50:CS63) -> 268.86898 | CT49: =SUM(CT50:CT63) -> 0 | CU49: 163.11714 | CV49: =SUM(CV50:CV63) -> 510 | CW49: =SUM(CW50:CW63) -> 149.55332 | CX49: =SUM(CX50:CX63) -> 0 | CY49: =SUM(CY50:CY63) -> 215.09518 | CZ49: =SUM(CZ50:CZ63) -> 0
C50: 入荷：7月 239枚 8月 315枚 10月 355枚（9月希望） | D50: 1 | E50: +0.50 | F50: 196 | G50: =F50*3080 -> 603680 | H50: 230 | I50: =H50*3080 -> 708400 | J50: 2 | K50: =SUM(L50:N50) -> 47 | L50: 12 | M50: 15 | N50: 20 | Q50: 45643 | AI50: =SUM(J50:K50)-CI50+CJ50 -> 45.6 | AJ50: =AI50-CK50+CL50 -> 48.081654 | AK50: =AJ50-CM50+CN50 -> 20.481654 | AL50: =AK50-CO50+CP50 -> 17.481654 | AM50: =AL50-CQ50+CR50 -> 46.781654 | AN50: =AM50-CS50+CT50 -> 23.781654 | AO50: =AN50-CU50+CV50 -> 59.775948 | AP50: =AO50-CW50+CX50 -> 46.98263 | AQ50: =AP50-CY50+CZ50 -> 28.58263 | AS50: =$H$50*月別販売比率!AG5 -> 23 | AU50: =$H$50*月別販売比率!AG5 -> 23 | AV50: 37 | AW50: =$H$50*月別販売比率!AQ5 -> 23 | AY50: =$H$50*月別販売比率!AV5 -> 14.005706 | AZ50: 30 | BA50: =$H$50*月別販売比率!BA5 -> 12.793318 | BC50: =$H$50*月別販売比率!BF5 -> 18.4 | BE50: =$H$50*月別販売比率!C5 -> 16.298778 | BF50: 60 | BG50: =$H$50*月別販売比率!H5 -> 16.1 | BH50: 28 | BI50: =$H$50*月別販売比率!M5 -> 23.244648 | BK50: =$H$50*月別販売比率!R5 -> 18.4 | BL50: 20 | BM50: =$H$50*月別販売比率!W5 -> 17.518346 | BN50: 30 | BO50: =$H$50*月別販売比率!AB5 -> 27.6 | BQ50: =$H$50*月別販売比率!AG5 -> 23 | BR50: 40 | BS50: =$H$50*月別販売比率!AL5 -> 20.7 | BT50: 20 | BU50: =$H$50*月別販売比率!AQ5 -> 23 | BV50: 15 | BW50: =$H$50*月別販売比率!AV5 -> 14.005706 | BY50: =$H$50*月別販売比率!BA5 -> 12.793318 | CA50: =$H$50*月別販売比率!BF5 -> 18.4 | CC50: =H50*月別販売比率!$C$21 -> 16.298778 | CE50: =H50*月別販売比率!$H$21 -> 16.1 | CF50: 40 | CG50: =H50*月別販売比率!$M$21 -> 23.244648 | CI50: =H50*月別販売比率!$R$21 -> 18.4 | CJ50: 15 | CK50: =H50*月別販売比率!$W$21 -> 17.518346 | CL50: 20 | CM50: =H50*月別販売比率!$AB$21 -> 27.6 | CO50: =H50*月別販売比率!$AG$21 -> 23 | CP50: 20 | CQ50: =H50*月別販売比率!$AL$21 -> 20.7 | CR50: 50 | CS50: =H50*月別販売比率!$AQ$21 -> 23 | CU50: =H50*月別販売比率!$AV$21 -> 14.005706 | CV50: 50 | CW50: =H50*月別販売比率!$BA$21 -> 12.793318 | CY50: =H50*月別販売比率!$BF$21 -> 18.4
E51: +1.00 | F51: 52 | G51: =F51*3080 -> 160160 | H51: 220 | I51: =H51*3080 -> 677600 | J51: 0 | K51: =SUM(L51:N51) -> 52 | L51: 14 | M51: 16 | N51: 22 | U51: 45757 | X51: 45848 | AA51: 45940 | AH51: 46157 | AI51: =SUM(J51:K51)-CI51+CJ51 -> 39.4 | AJ51: =AI51-CK51+CL51 -> 52.643322 | AK51: =AJ51-CM51+CN51 -> 26.243322 | AL51: =AK51-CO51+CP51 -> 29.243322 | AM51: =AL51-CQ51+CR51 -> 49.443322 | AN51: =AM51-CS51+CT51 -> 27.443322 | AO51: =AN51-CU51+CV51 -> 54.046559 | AP51: =AO51-CW51+CX51 -> 41.809472 | AQ51: =AP51-CY51+CZ51 -> 24.209472 | AS51: =$H$51*月別販売比率!AG5 -> 22 | AU51: =$H$51*月別販売比率!AG5 -> 22 | AW51: =$H$51*月別販売比率!AQ5 -> 22 | AY51: =$H$51*月別販売比率!AV5 -> 13.396763 | AZ51: 35 | BA51: =$H$51*月別販売比率!BA5 -> 12.237087 | BC51: =$H$51*月別販売比率!BF5 -> 17.6 | BE51: =$H$51*月別販売比率!C5 -> 15.590135 | BF51: 10 | BG51: =$H$51*月別販売比率!H5 -> 15.4 | BH51: 6 | BI51: =$H$51*月別販売比率!M5 -> 22.234012 | BK51: =$H$51*月別販売比率!R5 -> 17.6 | BL51: 10 | BM51: =$H$51*月別販売比率!W5 -> 16.756678 | BN51: 15 | BO51: =$H$51*月別販売比率!AB5 -> 26.4 | BQ51: =$H$51*月別販売比率!AG5 -> 22 | BR51: 20 | BS51: =$H$51*月別販売比率!AL5 -> 19.8 | BT51: 10 | BU51: =$H$51*月別販売比率!AQ5 -> 22 | BV51: 10 | BW51: =$H$51*月別販売比率!AV5 -> 13.396763 | BY51: =$H$51*月別販売比率!BA5 -> 12.237087 | CA51: =$H$51*月別販売比率!BF5 -> 17.6 | CC51: =H51*月別販売比率!$C$21 -> 15.590135 | CE51: =H51*月別販売比率!$H$21 -> 15.4 | CF51: 60 | CG51: =H51*月別販売比率!$M$21 -> 22.234012 | CI51: =H51*月別販売比率!$R$21 -> 17.6 | CJ51: 5 | CK51: =H51*月別販売比率!$W$21 -> 16.756678 | CL51: 30 | CM51: =H51*月別販売比率!$AB$21 -> 26.4 | CO51: =H51*月別販売比率!$AG$21 -> 22 | CP51: 25 | CQ51: =H51*月別販売比率!$AL$21 -> 19.8 | CR51: 40 | CS51: =H51*月別販売比率!$AQ$21 -> 22 | CU51: =H51*月別販売比率!$AV$21 -> 13.396763 | CV51: 40 | CW51: =H51*月別販売比率!$BA$21 -> 12.237087 | CY51: =H51*月別販売比率!$BF$21 -> 17.6
E52: +1.50 | F52: 52 | G52: =F52*3080 -> 160160 | H52: 220 | I52: =H52*3080 -> 677600 | J52: 0 | K52: =SUM(L52:N52) -> 43 | L52: 10 | M52: 15 | N52: 18 | AA52: 45940 | AI52: =SUM(J52:K52)-CI52+CJ52 -> 40.4 | AJ52: =AI52-CK52+CL52 -> 58.643322 | AK52: =AJ52-CM52+CN52 -> 32.243322 | AL52: =AK52-CO52+CP52 -> 40.243322 | AM52: =AL52-CQ52+CR52 -> 60.443322 | AN52: =AM52-CS52+CT52 -> 38.443322 | AO52: =AN52-CU52+CV52 -> 65.046559 | AP52: =AO52-CW52+CX52 -> 52.809472 | AQ52: =AP52-CY52+CZ52 -> 35.209472 | AS52: =$H$52*月別販売比率!AG5 -> 22 | AU52: =$H$52*月別販売比率!AG5 -> 22 | AW52: =$H$52*月別販売比率!AQ5 -> 22 | AY52: =$H$52*月別販売比率!AV5 -> 13.396763 | AZ52: 30 | BA52: =$H$52*月別販売比率!BA5 -> 12.237087 | BC52: =$H$52*月別販売比率!BF5 -> 17.6 | BE52: =$H$52*月別販売比率!C5 -> 15.590135 | BF52: 10 | BG52: =$H$52*月別販売比率!H5 -> 15.4 | BI52: =$H$52*月別販売比率!M5 -> 22.234012 | BK52: =$H$52*月別販売比率!R5 -> 17.6 | BM52: =$H$52*月別販売比率!W5 -> 16.756678 | BN52: 10 | BO52: =$H$52*月別販売比率!AB5 -> 26.4 | BQ52: =$H$52*月別販売比率!AG5 -> 22 | BR52: 40 | BS52: =$H$52*月別販売比率!AL5 -> 19.8 | BT52: 25 | BU52: =$H$52*月別販売比率!AQ5 -> 22 | BV52: 15 | BW52: =$H$52*月別販売比率!AV5 -> 13.396763 | BY52: =$H$52*月別販売比率!BA5 -> 12.237087 | CA52: =$H$52*月別販売比率!BF5 -> 17.6 | CC52: =H52*月別販売比率!$C$21 -> 15.590135 | CE52: =H52*月別販売比率!$H$21 -> 15.4 | CF52: 50 | CG52: =H52*月別販売比率!$M$21 -> 22.234012 | CI52: =H52*月別販売比率!$R$21 -> 17.6 | CJ52: 15 | CK52: =H52*月別販売比率!$W$21 -> 16.756678 | CL52: 35 | CM52: =H52*月別販売比率!$AB$21 -> 26.4 | CO52: =H52*月別販売比率!$AG$21 -> 22 | CP52: 30 | CQ52: =H52*月別販売比率!$AL$21 -> 19.8 | CR52: 40 | CS52: =H52*月別販売比率!$AQ$21 -> 22 | CU52: =H52*月別販売比率!$AV$21 -> 13.396763 | CV52: 40 | CW52: =H52*月別販売比率!$BA$21 -> 12.237087 | CY52: =H52*月別販売比率!$BF$21 -> 17.6
E53: +2.00 | F53: 52 | G53: =F53*3080 -> 160160 | H53: 85 | I53: =H53*3080 -> 261800 | J53: 0 | K53: =SUM(L53:N53) -> 14 | L53: 5 | M53: 9 | X53: 45848 | AI53: =SUM(J53:K53)-CI53+CJ53 -> 15.2 | AJ53: =AI53-CK53+CL53 -> 23.725829 | AK53: =AJ53-CM53+CN53 -> 13.525829 | AL53: =AK53-CO53+CP53 -> 15.025829 | AM53: =AL53-CQ53+CR53 -> 27.375829 | AN53: =AM53-CS53+CT53 -> 18.875829 | AO53: =AN53-CU53+CV53 -> 33.699807 | AP53: =AO53-CW53+CX53 -> 28.971842 | AQ53: =AP53-CY53+CZ53 -> 22.171842 | AS53: =$H$53*月別販売比率!AG5 -> 8.5 | AU53: =$H$53*月別販売比率!AG5 -> 8.5 | AW53: =$H$53*月別販売比率!AQ5 -> 8.5 | AY53: =$H$53*月別販売比率!AV5 -> 5.1760219 | AZ53: 25 | BA53: =$H$53*月別販売比率!BA5 -> 4.7279653 | BC53: =$H$53*月別販売比率!BF5 -> 6.8 | BE53: =$H$53*月別販売比率!C5 -> 6.0234613 | BF53: 10 | BG53: =$H$53*月別販売比率!H5 -> 5.95 | BH53: 5 | BI53: =$H$53*月別販売比率!M5 -> 8.5904136 | BK53: =$H$53*月別販売比率!R5 -> 6.8 | BL53: 20 | BM53: =$H$53*月別販売比率!W5 -> 6.4741712 | BN53: 10 | BO53: =$H$53*月別販売比率!AB5 -> 10.2 | BQ53: =$H$53*月別販売比率!AG5 -> 8.5 | BR53: 20 | BS53: =$H$53*月別販売比率!AL5 -> 7.65 | BT53: 10 | BU53: =$H$53*月別販売比率!AQ5 -> 8.5 | BV53: 10 | BW53: =$H$53*月別販売比率!AV5 -> 5.1760219 | BY53: =$H$53*月別販売比率!BA5 -> 4.7279653 | CA53: =$H$53*月別販売比率!BF5 -> 6.8 | CC53: =H53*月別販売比率!$C$21 -> 6.0234613 | CE53: =H53*月別販売比率!$H$21 -> 5.95 | CG53: =H53*月別販売比率!$M$21 -> 8.5904136 | CI53: =H53*月別販売比率!$R$21 -> 6.8 | CJ53: 8 | CK53: =H53*月別販売比率!$W$21 -> 6.4741712 | CL53: 15 | CM53: =H53*月別販売比率!$AB$21 -> 10.2 | CO53: =H53*月別販売比率!$AG$21 -> 8.5 | CP53: 10 | CQ53: =H53*月別販売比率!$AL$21 -> 7.65 | CR53: 20 | CS53: =H53*月別販売比率!$AQ$21 -> 8.5 | CU53: =H53*月別販売比率!$AV$21 -> 5.1760219 | CV53: 20 | CW53: =H53*月別販売比率!$BA$21 -> 4.7279653 | CY53: =H53*月別販売比率!$BF$21 -> 6.8
E54: +2.50 | F54: 10 | G54: =F54*3080 -> 30800 | H54: 60 | I54: =H54*3080 -> 184800 | J54: 0 | K54: =SUM(L54:N54) -> 48 | L54: 30 | M54: 18 | AI54: =SUM(J54:K54)-CI54+CJ54 -> 48.2 | AJ54: =AI54-CK54+CL54 -> 43.629997 | AK54: =AJ54-CM54+CN54 -> 36.429997 | AL54: =AK54-CO54+CP54 -> 30.429997 | AM54: =AL54-CQ54+CR54 -> 35.029997 | AN54: =AM54-CS54+CT54 -> 29.029997 | AO54: =AN54-CU54+CV54 -> 35.376334 | AP54: =AO54-CW54+CX54 -> 32.038947 | AQ54: =AP54-CY54+CZ54 -> 27.238947 | AS54: =$H$54*月別販売比率!AG5 -> 6 | AU54: =$H$54*月別販売比率!AG5 -> 6 | AW54: =$H$54*月別販売比率!AQ5 -> 6 | AY54: =$H$54*月別販売比率!AV5 -> 3.6536625 | AZ54: 25 | BA54: =$H$54*月別販売比率!BA5 -> 3.3373872 | BC54: =$H$54*月別販売比率!BF5 -> 4.8 | BE54: =$H$54*月別販売比率!C5 -> 4.2518551 | BG54: =$H$54*月別販売比率!H5 -> 4.2 | BI54: =$H$54*月別販売比率!M5 -> 6.0638213 | BK54: =$H$54*月別販売比率!R5 -> 4.8 | BM54: =$H$54*月別販売比率!W5 -> 4.5700032 | BO54: =$H$54*月別販売比率!AB5 -> 7.2 | BQ54: =$H$54*月別販売比率!AG5 -> 6 | BR54: 10 | BS54: =$H$54*月別販売比率!AL5 -> 5.4 | BT54: 10 | BU54: =$H$54*月別販売比率!AQ5 -> 6 | BW54: =$H$54*月別販売比率!AV5 -> 3.6536625 | BY54: =$H$54*月別販売比率!BA5 -> 3.3373872 | CA54: =$H$54*月別販売比率!BF5 -> 4.8 | CC54: =H54*月別販売比率!$C$21 -> 4.2518551 | CE54: =H54*月別販売比率!$H$21 -> 4.2 | CG54: =H54*月別販売比率!$M$21 -> 6.0638213 | CI54: =H54*月別販売比率!$R$21 -> 4.8 | CJ54: 5 | CK54: =H54*月別販売比率!$W$21 -> 4.5700032 | CM54: =H54*月別販売比率!$AB$21 -> 7.2 | CO54: =H54*月別販売比率!$AG$21 -> 6 | CQ54: =H54*月別販売比率!$AL$21 -> 5.4 | CR54: 10 | CS54: =H54*月別販売比率!$AQ$21 -> 6 | CU54: =H54*月別販売比率!$AV$21 -> 3.6536625 | CV54: 10 | CW54: =H54*月別販売比率!$BA$21 -> 3.3373872 | CY54: =H54*月別販売比率!$BF$21 -> 4.8
D55: 2 | E55: +0.50 | F55: 233 | G55: =F55*3080 -> 717640 | H55: 280 | I55: =H55*3080 -> 862400 | J55: 0 | K55: =SUM(L55:N55) -> 40 | L55: 10 | M55: 14 | N55: 16 | Q55: 45643 | U55: 45757 | AA55: 45940 | AI55: =SUM(J55:K55)-CI55+CJ55 -> 47.6 | AJ55: =AI55-CK55+CL55 -> 61.273318 | AK55: =AJ55-CM55+CN55 -> 27.673318 | AL55: =AK55-CO55+CP55 -> 29.673318 | AM55: =AL55-CQ55+CR55 -> 64.473318 | AN55: =AM55-CS55+CT55 -> 36.473318 | AO55: =AN55-CU55+CV55 -> 79.422893 | AP55: =AO55-CW55+CX55 -> 63.848419 | AQ55: =AP55-CY55+CZ55 -> 41.448419 | AS55: =$H$55*月別販売比率!AG5 -> 28 | AU55: =$H$55*月別販売比率!AG5 -> 28 | AV55: 42 | AW55: =$H$55*月別販売比率!AQ5 -> 28 | AY55: =$H$55*月別販売比率!AV5 -> 17.050425 | AZ55: 30 | BA55: =$H$55*月別販売比率!BA5 -> 15.574474 | BC55: =$H$55*月別販売比率!BF5 -> 22.4 | BE55: =$H$55*月別販売比率!C5 -> 19.84199 | BF55: 40 | BG55: =$H$55*月別販売比率!H5 -> 19.6 | BH55: 47 | BI55: =$H$55*月別販売比率!M5 -> 28.297833 | BK55: =$H$55*月別販売比率!R5 -> 22.4 | BL55: 50 | BM55: =$H$55*月別販売比率!W5 -> 21.326682 | BN55: 40 | BO55: =$H$55*月別販売比率!AB5 -> 33.6 | BQ55: =$H$55*月別販売比率!AG5 -> 28 | BR55: 60 | BS55: =$H$55*月別販売比率!AL5 -> 25.2 | BT55: 30 | BU55: =$H$55*月別販売比率!AQ5 -> 28 | BV55: 25 | BW55: =$H$55*月別販売比率!AV5 -> 17.050425 | BY55: =$H$55*月別販売比率!BA5 -> 15.574474 | CA55: =$H$55*月別販売比率!BF5 -> 22.4 | CC55: =H55*月別販売比率!$C$21 -> 19.84199 | CE55: =H55*月別販売比率!$H$21 -> 19.6 | CF55: 52 | CG55: =H55*月別販売比率!$M$21 -> 28.297833 | CI55: =H55*月別販売比率!$R$21 -> 22.4 | CJ55: 30 | CK55: =H55*月別販売比率!$W$21 -> 21.326682 | CL55: 35 | CM55: =H55*月別販売比率!$AB$21 -> 33.6 | CO55: =H55*月別販売比率!$AG$21 -> 28 | CP55: 30 | CQ55: =H55*月別販売比率!$AL$21 -> 25.2 | CR55: 60 | CS55: =H55*月別販売比率!$AQ$21 -> 28 | CU55: =H55*月別販売比率!$AV$21 -> 17.050425 | CV55: 60 | CW55: =H55*月別販売比率!$BA$21 -> 15.574474 | CY55: =H55*月別販売比率!$BF$21 -> 22.4
E56: +1.00 | F56: 103 | G56: =F56*3080 -> 317240 | H56: 180 | I56: =H56*3080 -> 554400 | J56: 0 | K56: =SUM(L56:N56) -> 8 | L56: 0 | M56: 8 | AH56: 46157 | AI56: =SUM(J56:K56)-CI56+CJ56 -> 28.6 | AJ56: =AI56-CK56+CL56 -> 39.88999 | AK56: =AJ56-CM56+CN56 -> 18.28999 | AL56: =AK56-CO56+CP56 -> 25.28999 | AM56: =AL56-CQ56+CR56 -> 49.08999 | AN56: =AM56-CS56+CT56 -> 31.08999 | AO56: =AN56-CU56+CV56 -> 50.129003 | AP56: =AO56-CW56+CX56 -> 40.116841 | AQ56: =AP56-CY56+CZ56 -> 25.716841 | AS56: =$H$56*月別販売比率!AG5 -> 18 | AU56: =$H$56*月別販売比率!AG5 -> 18 | AV56: 17 | AW56: =$H$56*月別販売比率!AQ5 -> 18 | AY56: =$H$56*月別販売比率!AV5 -> 10.960988 | AZ56: 35 | BA56: =$H$56*月別販売比率!BA5 -> 10.012162 | BC56: =$H$56*月別販売比率!BF5 -> 14.4 | BE56: =$H$56*月別販売比率!C5 -> 12.755565 | BG56: =$H$56*月別販売比率!H5 -> 12.6 | BH56: 30 | BI56: =$H$56*月別販売比率!M5 -> 18.191464 | BK56: =$H$56*月別販売比率!R5 -> 14.4 | BL56: 25 | BM56: =$H$56*月別販売比率!W5 -> 13.71001 | BN56: 20 | BO56: =$H$56*月別販売比率!AB5 -> 21.6 | BQ56: =$H$56*月別販売比率!AG5 -> 18 | BR56: 60 | BS56: =$H$56*月別販売比率!AL5 -> 16.2 | BT56: 30 | BU56: =$H$56*月別販売比率!AQ5 -> 18 | BV56: 30 | BW56: =$H$56*月別販売比率!AV5 -> 10.960988 | BY56: =$H$56*月別販売比率!BA5 -> 10.012162 | CA56: =$H$56*月別販売比率!BF5 -> 14.4 | CC56: =H56*月別販売比率!$C$21 -> 12.755565 | CE56: =H56*月別販売比率!$H$21 -> 12.6 | CF56: 15 | CG56: =H56*月別販売比率!$M$21 -> 18.191464 | CI56: =H56*月別販売比率!$R$21 -> 14.4 | CJ56: 35 | CK56: =H56*月別販売比率!$W$21 -> 13.71001 | CL56: 25 | CM56: =H56*月別販売比率!$AB$21 -> 21.6 | CO56: =H56*月別販売比率!$AG$21 -> 18 | CP56: 25 | CQ56: =H56*月別販売比率!$AL$21 -> 16.2 | CR56: 40 | CS56: =H56*月別販売比率!$AQ$21 -> 18 | CU56: =H56*月別販売比率!$AV$21 -> 10.960988 | CV56: 30 | CW56: =H56*月別販売比率!$BA$21 -> 10.012162 | CY56: =H56*月別販売比率!$BF$21 -> 14.4
E57: +1.50 | F57: 186 | G57: =F57*3080 -> 572880 | H57: =F57*($H$49/$F$49) -> 185.78143 | I57: =H57*3080 -> 572206.82 | J57: 0 | K57: =SUM(L57:N57) -> 30 | L57: 11 | M57: 15 | N57: 4 | U57: 45757 | X57: 45848 | AI57: =SUM(J57:K57)-CI57+CJ57 -> 30.137485 | AJ57: =AI57-CK57+CL57 -> 20.987123 | AK57: =AJ57-CM57+CN57 -> -1.3066492 | AL57: =0-CO57+CP57 -> 16.421857 | AM57: =AL57-CQ57+CR57 -> 39.701528 | AN57: =AM57-CS57+CT57 -> 21.123384 | AO57: =AN57-CU57+CV57 -> 39.81034 | AP57: =AO57-CW57+CX57 -> 29.476597 | AQ57: =AP57-CY57+CZ57 -> 14.614082 | AS57: =$H$57*月別販売比率!AG5 -> 18.578143 | AU57: =$H$57*月別販売比率!AG5 -> 18.578143 | AV57: 52 | AW57: =$H$57*月別販売比率!AQ5 -> 18.578143 | AY57: =$H$57*月別販売比率!AV5 -> 11.313044 | AZ57: 10 | BA57: =$H$57*月別販売比率!BA5 -> 10.333743 | BC57: =$H$57*月別販売比率!BF5 -> 14.862515 | BE57: =$H$57*月別販売比率!C5 -> 13.165262 | BF57: 60 | BG57: =$H$57*月別販売比率!H5 -> 13.0047 | BH57: 20 | BI57: =$H$57*月別販売比率!M5 -> 18.775757 | BK57: =$H$57*月別販売比率!R5 -> 14.862515 | BL57: 35 | BM57: =$H$57*月別販売比率!W5 -> 14.150362 | BN57: 25 | BO57: =$H$57*月別販売比率!AB5 -> 22.293772 | BQ57: =$H$57*月別販売比率!AG5 -> 18.578143 | BR57: 30 | BS57: =$H$57*月別販売比率!AL5 -> 16.720329 | BT57: 50 | BU57: =$H$57*月別販売比率!AQ5 -> 18.578143 | BV57: 25 | BW57: =$H$57*月別販売比率!AV5 -> 11.313044 | BY57: =$H$57*月別販売比率!BA5 -> 10.333743 | CA57: =$H$57*月別販売比率!BF5 -> 14.862515 | CC57: =H57*月別販売比率!$C$21 -> 13.165262 | CE57: =H57*月別販売比率!$H$21 -> 13.0047 | CF57: 45 | CG57: =H57*月別販売比率!$M$21 -> 18.775757 | CI57: =H57*月別販売比率!$R$21 -> 14.862515 | CJ57: 15 | CK57: =H57*月別販売比率!$W$21 -> 14.150362 | CL57: 5 | CM57: =H57*月別販売比率!$AB$21 -> 22.293772 | CO57: =H57*月別販売比率!$AG$21 -> 18.578143 | CP57: 35 | CQ57: =H57*月別販売比率!$AL$21 -> 16.720329 | CR57: 40 | CS57: =H57*月別販売比率!$AQ$21 -> 18.578143 | CU57: =H57*月別販売比率!$AV$21 -> 11.313044 | CV57: 30 | CW57: =H57*月別販売比率!$BA$21 -> 10.333743 | CY57: =H57*月別販売比率!$BF$21 -> 14.862515
E58: +2.00 | F58: 78 | G58: =F58*3080 -> 240240 | H58: =F58*($H$49/$F$49) -> 77.908343 | I58: =H58*3080 -> 239957.7 | J58: 0 | K58: =SUM(L58:N58) -> 17 | L58: 3 | M58: 14 | AI58: =SUM(J58:K58)-CI58+CJ58 -> 25.767333 | AJ58: =AI58-CK58+CL58 -> 19.83331 | AK58: =AJ58-CM58+CN58 -> 10.484308 | AL58: =AK58-CO58+CP58 -> 17.693474 | AM58: =AL58-CQ58+CR58 -> 20.681723 | AN58: =AM58-CS58+CT58 -> 12.890889 | AO58: =AN58-CU58+CV58 -> 18.146709 | AP58: =AO58-CW58+CX58 -> 13.813204 | AQ58: =AP58-CY58+CZ58 -> 7.5805364 | AS58: =$H$58*月別販売比率!AG5 -> 7.7908343 | AU58: =$H$58*月別販売比率!AG5 -> 7.7908343 | AV58: 27 | AW58: =$H$58*月別販売比率!AQ5 -> 7.7908343 | AY58: =$H$58*月別販売比率!AV5 -> 4.7441799 | AZ58: 25 | BA58: =$H$58*月別販売比率!BA5 -> 4.3335052 | BC58: =$H$58*月別販売比率!BF5 -> 6.2326675 | BE58: =$H$58*月別販売比率!C5 -> 5.5209164 | BG58: =$H$58*月別販売比率!H5 -> 5.453584 | BH58: 45 | BI58: =$H$58*月別販売比率!M5 -> 7.8737046 | BK58: =$H$58*月別販売比率!R5 -> 6.2326675 | BM58: =$H$58*月別販売比率!W5 -> 5.934023 | BN58: 15 | BO58: =$H$58*月別販売比率!AB5 -> 9.3490012 | BQ58: =$H$58*月別販売比率!AG5 -> 7.7908343 | BR58: 0 | BS58: =$H$58*月別販売比率!AL5 -> 7.0117509 | BT58: 10 | BU58: =$H$58*月別販売比率!AQ5 -> 7.7908343 | BV58: 20 | BW58: =$H$58*月別販売比率!AV5 -> 4.7441799 | BY58: =$H$58*月別販売比率!BA5 -> 4.3335052 | CA58: =$H$58*月別販売比率!BF5 -> 6.2326675 | CC58: =H58*月別販売比率!$C$21 -> 5.5209164 | CE58: =H58*月別販売比率!$H$21 -> 5.453584 | CF58: 20 | CG58: =H58*月別販売比率!$M$21 -> 7.8737046 | CI58: =H58*月別販売比率!$R$21 -> 6.2326675 | CJ58: 15 | CK58: =H58*月別販売比率!$W$21 -> 5.934023 | CM58: =H58*月別販売比率!$AB$21 -> 9.3490012 | CO58: =H58*月別販売比率!$AG$21 -> 7.7908343 | CP58: 15 | CQ58: =H58*月別販売比率!$AL$21 -> 7.0117509 | CR58: 10 | CS58: =H58*月別販売比率!$AQ$21 -> 7.7908343 | CU58: =H58*月別販売比率!$AV$21 -> 4.7441799 | CV58: 10 | CW58: =H58*月別販売比率!$BA$21 -> 4.3335052 | CY58: =H58*月別販売比率!$BF$21 -> 6.2326675
E59: +2.50 | F59: 31 | G59: =F59*3080 -> 95480 | H59: 150 | I59: =H59*3080 -> 462000 | J59: 1 | K59: =SUM(L59:N59) -> 46 | L59: 6 | M59: 15 | N59: 25 | X59: 45848 | AI59: =SUM(J59:K59)-CI59+CJ59 -> 45 | AJ59: =AI59-CK59+CL59 -> 58.574992 | AK59: =AJ59-CM59+CN59 -> 40.574992 | AL59: =AK59-CO59+CP59 -> 45.574992 | AM59: =AL59-CQ59+CR59 -> 42.074992 | AN59: =AM59-CS59+CT59 -> 27.074992 | AO59: =AN59-CU59+CV59 -> 37.940836 | AP59: =AO59-CW59+CX59 -> 29.597368 | AQ59: =AP59-CY59+CZ59 -> 17.597368 | AS59: =$H$59*月別販売比率!AG5 -> 15 | AU59: =$H$59*月別販売比率!AG5 -> 15 | AV59: 3 | AW59: =$H$59*月別販売比率!AQ5 -> 15 | AY59: =$H$59*月別販売比率!AV5 -> 9.1341563 | AZ59: 25 | BA59: =$H$59*月別販売比率!BA5 -> 8.3434681 | BC59: =$H$59*月別販売比率!BF5 -> 12 | BE59: =$H$59*月別販売比率!C5 -> 10.629638 | BG59: =$H$59*月別販売比率!H5 -> 10.5 | BH59: 7 | BI59: =$H$59*月別販売比率!M5 -> 15.159553 | BK59: =$H$59*月別販売比率!R5 -> 12 | BL59: 5 | BM59: =$H$59*月別販売比率!W5 -> 11.425008 | BN59: 10 | BO59: =$H$59*月別販売比率!AB5 -> 18 | BQ59: =$H$59*月別販売比率!AG5 -> 15 | BR59: 20 | BS59: =$H$59*月別販売比率!AL5 -> 13.5 | BT59: 10 | BU59: =$H$59*月別販売比率!AQ5 -> 15 | BV59: 10 | BW59: =$H$59*月別販売比率!AV5 -> 9.1341563 | BY59: =$H$59*月別販売比率!BA5 -> 8.3434681 | CA59: =$H$59*月別販売比率!BF5 -> 12 | CC59: =H59*月別販売比率!$C$21 -> 10.629638 | CE59: =H59*月別販売比率!$H$21 -> 10.5 | CF59: 40 | CG59: =H59*月別販売比率!$M$21 -> 15.159553 | CI59: =H59*月別販売比率!$R$21 -> 12 | CJ59: 10 | CK59: =H59*月別販売比率!$W$21 -> 11.425008 | CL59: 25 | CM59: =H59*月別販売比率!$AB$21 -> 18 | CO59: =H59*月別販売比率!$AG$21 -> 15 | CP59: 20 | CQ59: =H59*月別販売比率!$AL$21 -> 13.5 | CR59: 10 | CS59: =H59*月別販売比率!$AQ$21 -> 15 | CU59: =H59*月別販売比率!$AV$21 -> 9.1341563 | CV59: 20 | CW59: =H59*月別販売比率!$BA$21 -> 8.3434681 | CY59: =H59*月別販売比率!$BF$21 -> 12
D60: 3 | E60: +0.50 | F60: 222 | G60: =F60*3080 -> 683760 | H60: 290 | I60: =H60*3080 -> 893200 | J60: 0 | K60: =SUM(L60:N60) -> 38 | L60: 3 | M60: 16 | N60: 19 | Q60: 45643 | U60: 45757 | X60: 45848 | AA60: 45940 | AI60: =SUM(J60:K60)-CI60+CJ60 -> 24.8 | AJ60: =AI60-CK60+CL60 -> 37.711651 | AK60: =AJ60-CM60+CN60 -> 2.9116511 | AL60: =AK60-CO60+CP60 -> 8.9116511 | AM60: =AL60-CQ60+CR60 -> 42.811651 | AN60: =AM60-CS60+CT60 -> 13.811651 | AO60: =AN60-CU60+CV60 -> 56.152282 | AP60: =AO60-CW60+CX60 -> 40.021577 | AQ60: =AP60-CY60+CZ60 -> 16.821577 | AS60: =$H$60*月別販売比率!AG5 -> 29 | AU60: =$H$60*月別販売比率!AG5 -> 29 | AV60: 42 | AW60: =$H$60*月別販売比率!AQ5 -> 29 | AY60: =$H$60*月別販売比率!AV5 -> 17.659369 | AZ60: 30 | BA60: =$H$60*月別販売比率!BA5 -> 16.130705 | BC60: =$H$60*月別販売比率!BF5 -> 23.2 | BE60: =$H$60*月別販売比率!C5 -> 20.550633 | BF60: 40 | BG60: =$H$60*月別販売比率!H5 -> 20.3 | BH60: 65 | BI60: =$H$60*月別販売比率!M5 -> 29.30847 | BK60: =$H$60*月別販売比率!R5 -> 23.2 | BL60: 30 | BM60: =$H$60*月別販売比率!W5 -> 22.088349 | BN60: 40 | BO60: =$H$60*月別販売比率!AB5 -> 34.8 | BQ60: =$H$60*月別販売比率!AG5 -> 29 | BR60: 50 | BS60: =$H$60*月別販売比率!AL5 -> 26.1 | BT60: 30 | BU60: =$H$60*月別販売比率!AQ5 -> 29 | BV60: 25 | BW60: =$H$60*月別販売比率!AV5 -> 17.659369 | BY60: =$H$60*月別販売比率!BA5 -> 16.130705 | CA60: =$H$60*月別販売比率!BF5 -> 23.2 | CC60: =H60*月別販売比率!$C$21 -> 20.550633 | CE60: =H60*月別販売比率!$H$21 -> 20.3 | CF60: 75 | CG60: =H60*月別販売比率!$M$21 -> 29.30847 | CI60: =H60*月別販売比率!$R$21 -> 23.2 | CJ60: 10 | CK60: =H60*月別販売比率!$W$21 -> 22.088349 | CL60: 35 | CM60: =H60*月別販売比率!$AB$21 -> 34.8 | CO60: =H60*月別販売比率!$AG$21 -> 29 | CP60: 35 | CQ60: =H60*月別販売比率!$AL$21 -> 26.1 | CR60: 60 | CS60: =H60*月別販売比率!$AQ$21 -> 29 | CU60: =H60*月別販売比率!$AV$21 -> 17.659369 | CV60: 60 | CW60: =H60*月別販売比率!$BA$21 -> 16.130705 | CY60: =H60*月別販売比率!$BF$21 -> 23.2
E61: +1.00 | F61: 119 | G61: =F61*3080 -> 366520 | H61: 290 | I61: =H61*3080 -> 893200 | J61: 0 | K61: =SUM(L61:N61) -> 18 | L61: 4 | M61: 14 | U61: 45757 | X61: 45848 | AA61: 45940 | AI61: =SUM(J61:K61)-CI61+CJ61 -> 24.8 | AJ61: =AI61-CK61+CL61 -> 47.711651 | AK61: =AJ61-CM61+CN61 -> 12.911651 | AL61: =AK61-CO61+CP61 -> 28.911651 | AM61: =AL61-CQ61+CR61 -> 42.811651 | AN61: =AM61-CS61+CT61 -> 13.811651 | AO61: =AN61-CU61+CV61 -> 56.152282 | AP61: =AO61-CW61+CX61 -> 40.021577 | AQ61: =AP61-CY61+CZ61 -> 16.821577 | AS61: =$H$61*月別販売比率!AG5 -> 29 | AU61: =$H$61*月別販売比率!AG5 -> 29 | AV61: 22 | AW61: =$H$61*月別販売比率!AQ5 -> 29 | AY61: =$H$61*月別販売比率!AV5 -> 17.659369 | AZ61: 35 | BA61: =$H$61*月別販売比率!BA5 -> 16.130705 | BC61: =$H$61*月別販売比率!BF5 -> 23.2 | BE61: =$H$61*月別販売比率!C5 -> 20.550633 | BF61: 15 | BG61: =$H$61*月別販売比率!H5 -> 20.3 | BH61: 15 | BI61: =$H$61*月別販売比率!M5 -> 29.30847 | BK61: =$H$61*月別販売比率!R5 -> 23.2 | BL61: 45 | BM61: =$H$61*月別販売比率!W5 -> 22.088349 | BN61: 20 | BO61: =$H$61*月別販売比率!AB5 -> 34.8 | BQ61: =$H$61*月別販売比率!AG5 -> 29 | BR61: 40 | BS61: =$H$61*月別販売比率!AL5 -> 26.1 | BT61: 20 | BU61: =$H$61*月別販売比率!AQ5 -> 29 | BV61: 20 | BW61: =$H$61*月別販売比率!AV5 -> 17.659369 | BY61: =$H$61*月別販売比率!BA5 -> 16.130705 | CA61: =$H$61*月別販売比率!BF5 -> 23.2 | CC61: =H61*月別販売比率!$C$21 -> 20.550633 | CE61: =H61*月別販売比率!$H$21 -> 20.3 | CF61: 55 | CG61: =H61*月別販売比率!$M$21 -> 29.30847 | CI61: =H61*月別販売比率!$R$21 -> 23.2 | CJ61: 30 | CK61: =H61*月別販売比率!$W$21 -> 22.088349 | CL61: 45 | CM61: =H61*月別販売比率!$AB$21 -> 34.8 | CO61: =H61*月別販売比率!$AG$21 -> 29 | CP61: 45 | CQ61: =H61*月別販売比率!$AL$21 -> 26.1 | CR61: 40 | CS61: =H61*月別販売比率!$AQ$21 -> 29 | CU61: =H61*月別販売比率!$AV$21 -> 17.659369 | CV61: 60 | CW61: =H61*月別販売比率!$BA$21 -> 16.130705 | CY61: =H61*月別販売比率!$BF$21 -> 23.2
E62: +1.50 | F62: 176 | G62: =F62*3080 -> 542080 | H62: 230 | I62: =H62*3080 -> 708400 | J62: -5 | K62: =SUM(L62:N62) -> 31 | L62: 10 | M62: 15 | N62: 6 | X62: 45848 | AA62: 45940 | AI62: =SUM(J62:K62)-CI62+CJ62 -> 17.6 | AJ62: =AI62-CK62+CL62 -> 10.081654 | AK62: =AJ62-CM62+CN62 -> -17.518346 | AL62: =AK62-CO62+CP62 -> -10.518346 | AM62: =0-CQ62+CR62 -> 19.3 | AN62: =AM62-CS62+CT62 -> -3.7 | AO62: =0-CU62+CV62 -> 35.994294 | AP62: =AO62-CW62+CX62 -> 23.200976 | AQ62: =AP62-CY62+CZ62 -> 4.8009759 | AS62: =$H$62*月別販売比率!AG5 -> 23 | AU62: =$H$62*月別販売比率!AG5 -> 23 | AV62: 52 | AW62: =$H$62*月別販売比率!AQ5 -> 23 | AY62: =$H$62*月別販売比率!AV5 -> 14.005706 | AZ62: 30 | BA62: =$H$62*月別販売比率!BA5 -> 12.793318 | BC62: =$H$62*月別販売比率!BF5 -> 18.4 | BE62: =$H$62*月別販売比率!C5 -> 16.298778 | BF62: 10 | BG62: =$H$62*月別販売比率!H5 -> 16.1 | BH62: 30 | BI62: =$H$62*月別販売比率!M5 -> 23.244648 | BK62: =$H$62*月別販売比率!R5 -> 18.4 | BL62: 30 | BM62: =$H$62*月別販売比率!W5 -> 17.518346 | BN62: 30 | BO62: =$H$62*月別販売比率!AB5 -> 27.6 | BQ62: =$H$62*月別販売比率!AG5 -> 23 | BR62: 20 | BS62: =$H$62*月別販売比率!AL5 -> 20.7 | BT62: 45 | BU62: =$H$62*月別販売比率!AQ5 -> 23 | BV62: 15 | BW62: =$H$62*月別販売比率!AV5 -> 14.005706 | BY62: =$H$62*月別販売比率!BA5 -> 12.793318 | CA62: =$H$62*月別販売比率!BF5 -> 18.4 | CC62: =H62*月別販売比率!$C$21 -> 16.298778 | CE62: =H62*月別販売比率!$H$21 -> 16.1 | CF62: 65 | CG62: =H62*月別販売比率!$M$21 -> 23.244648 | CI62: =H62*月別販売比率!$R$21 -> 18.4 | CJ62: 10 | CK62: =H62*月別販売比率!$W$21 -> 17.518346 | CL62: 10 | CM62: =H62*月別販売比率!$AB$21 -> 27.6 | CO62: =H62*月別販売比率!$AG$21 -> 23 | CP62: 30 | CQ62: =H62*月別販売比率!$AL$21 -> 20.7 | CR62: 40 | CS62: =H62*月別販売比率!$AQ$21 -> 23 | CU62: =H62*月別販売比率!$AV$21 -> 14.005706 | CV62: 50 | CW62: =H62*月別販売比率!$BA$21 -> 12.793318 | CY62: =H62*月別販売比率!$BF$21 -> 18.4
E63: +2.00 | F63: 145 | G63: =F63*3080 -> 446600 | H63: 190 | I63: =H63*3080 -> 585200 | J63: 0 | K63: =SUM(L63:N63) -> 17 | L63: 3 | M63: 14 | AA63: 45940 | AI63: =SUM(J63:K63)-CI63+CJ63 -> 21.8 | AJ63: =AI63-CK63+CL63 -> 17.328323 | AK63: =AJ63-CM63+CN63 -> -5.4716769 | AL63: =0-CO63+CP63 -> 16 | AM63: =AL63-CQ63+CR63 -> 33.9 | AN63: =AM63-CS63+CT63 -> 14.9 | AO63: =AN63-CU63+CV63 -> 33.330069 | AP63: =AO63-CW63+CX63 -> 22.761676 | AQ63: =AP63-CY63+CZ63 -> 7.5616757 | AS63: =$H$63*月別販売比率!AG5 -> 19 | AU63: =$H$63*月別販売比率!AG5 -> 19 | AV63: 47 | AW63: =$H$63*月別販売比率!AQ5 -> 19 | AY63: =$H$63*月別販売比率!AV5 -> 11.569931 | AZ63: 25 | BA63: =$H$63*月別販売比率!BA5 -> 10.568393 | BC63: =$H$63*月別販売比率!BF5 -> 15.2 | BE63: =$H$63*月別販売比率!C5 -> 13.464208 | BF63: 5 | BG63: =$H$63*月別販売比率!H5 -> 13.3 | BH63: 27 | BI63: =$H$63*月別販売比率!M5 -> 19.202101 | BK63: =$H$63*月別販売比率!R5 -> 15.2 | BL63: 50 | BM63: =$H$63*月別販売比率!W5 -> 14.471677 | BN63: 25 | BO63: =$H$63*月別販売比率!AB5 -> 22.8 | BQ63: =$H$63*月別販売比率!AG5 -> 19 | BR63: 20 | BS63: =$H$63*月別販売比率!AL5 -> 17.1 | BT63: 40 | BU63: =$H$63*月別販売比率!AQ5 -> 19 | BV63: 10 | BW63: =$H$63*月別販売比率!AV5 -> 11.569931 | BY63: =$H$63*月別販売比率!BA5 -> 10.568393 | CA63: =$H$63*月別販売比率!BF5 -> 15.2 | CC63: =H63*月別販売比率!$C$21 -> 13.464208 | CE63: =H63*月別販売比率!$H$21 -> 13.3 | CF63: 40 | CG63: =H63*月別販売比率!$M$21 -> 19.202101 | CI63: =H63*月別販売比率!$R$21 -> 15.2 | CJ63: 20 | CK63: =H63*月別販売比率!$W$21 -> 14.471677 | CL63: 10 | CM63: =H63*月別販売比率!$AB$21 -> 22.8 | CO63: =H63*月別販売比率!$AG$21 -> 19 | CP63: 35 | CQ63: =H63*月別販売比率!$AL$21 -> 17.1 | CR63: 35 | CS63: =H63*月別販売比率!$AQ$21 -> 19 | CU63: =H63*月別販売比率!$AV$21 -> 11.569931 | CV63: 30 | CW63: =H63*月別販売比率!$BA$21 -> 10.568393 | CY63: =H63*月別販売比率!$BF$21 -> 15.2
E64: +2.50 | F64: 47 | G64: =F64*3080 -> 144760 | H64: 150 | I64: =H64*3080 -> 462000 | J64: 1 | K64: =SUM(L64:N64) -> 31 | L64: 2 | M64: 14 | N64: 15 | X64: 45848 | AA64: 45940 | AH64: 46157 | AI64: =SUM(J64:K64)-CI64+CJ64 -> 30 | AJ64: =AI64-CK64+CL64 -> 43.574992 | AK64: =AJ64-CM64+CN64 -> 25.574992 | AL64: =AK64-CO64+CP64 -> 25.574992 | AM64: =AL64-CQ64+CR64 -> 27.074992 | AN64: =AM64-CS64+CT64 -> 12.074992 | AO64: =AN64-CU64+CV64 -> 32.940836 | AP64: =AO64-CW64+CX64 -> 24.597368 | AQ64: =AP64-CY64+CZ64 -> 12.597368 | AS64: =$H$64*月別販売比率!AG5 -> 15 | AU64: =$H$64*月別販売比率!AG5 -> 15 | AV64: 7 | AW64: =$H$64*月別販売比率!AQ5 -> 15 | AY64: =$H$64*月別販売比率!AV5 -> 9.1341563 | AZ64: 25 | BA64: =$H$64*月別販売比率!BA5 -> 8.3434681 | BC64: =$H$64*月別販売比率!BF5 -> 12 | BE64: =$H$64*月別販売比率!C5 -> 10.629638 | BG64: =$H$64*月別販売比率!H5 -> 10.5 | BH64: 10 | BI64: =$H$64*月別販売比率!M5 -> 15.159553 | BK64: =$H$64*月別販売比率!R5 -> 12 | BL64: 20 | BM64: =$H$64*月別販売比率!W5 -> 11.425008 | BN64: 5 | BO64: =$H$64*月別販売比率!AB5 -> 18 | BQ64: =$H$64*月別販売比率!AG5 -> 15 | BR64: 20 | BS64: =$H$64*月別販売比率!AL5 -> 13.5 | BT64: 10 | BU64: =$H$64*月別販売比率!AQ5 -> 15 | BV64: 10 | BW64: =$H$64*月別販売比率!AV5 -> 9.1341563 | BY64: =$H$64*月別販売比率!BA5 -> 8.3434681 | CA64: =$H$64*月別販売比率!BF5 -> 12 | CC64: =H64*月別販売比率!$C$21 -> 10.629638 | CE64: =H64*月別販売比率!$H$21 -> 10.5 | CF64: 40 | CG64: =H64*月別販売比率!$M$21 -> 15.159553 | CI64: =H64*月別販売比率!$R$21 -> 12 | CJ64: 10 | CK64: =H64*月別販売比率!$W$21 -> 11.425008 | CL64: 25 | CM64: =H64*月別販売比率!$AB$21 -> 18 | CO64: =H64*月別販売比率!$AG$21 -> 15 | CP64: 15 | CQ64: =H64*月別販売比率!$AL$21 -> 13.5 | CR64: 15 | CS64: =H64*月別販売比率!$AQ$21 -> 15 | CU64: =H64*月別販売比率!$AV$21 -> 9.1341563 | CV64: 30 | CW64: =H64*月別販売比率!$BA$21 -> 8.3434681 | CY64: =H64*月別販売比率!$BF$21 -> 12
B65: 5 | C65: fll-006 | F65: =SUM(F66:F75) -> 691 | G65: =SUM(G66:G75) -> 2508330 | H65: 1970 | I65: =SUM(I66:I75) -> 7613544.1 | J65: =SUM(J66:J75) -> 178 | K65: =SUM(K66:K75) -> 508 | L65: =SUM(L66:L75) -> 50 | M65: =SUM(M66:M75) -> 114 | N65: =SUM(N66:N75) -> 344 | AS65: =SUM(AS66:AS75) -> 209.73951 | AT65: =SUM(AT66:AT75) -> 416 | AU65: =SUM(AU66:AU75) -> 188.76556 | AV65: =SUM(AV66:AV75) -> 0 | AW65: =SUM(AW66:AW75) -> 209.73951 | AX65: =SUM(AX66:AX75) -> 0 | AY65: =SUM(AY66:AY75) -> 127.71956 | AZ65: =SUM(AZ66:AZ75) -> 311 | ... CT65: =SUM(CT66:CT75) -> 0 | CU65: 127.71956 | CV65: =SUM(CV66:CV75) -> 0 | CW65: =SUM(CW66:CW75) -> 116.66366 | CX65: =SUM(CX66:CX75) -> 0 | CY65: =SUM(CY66:CY75) -> 167.79161 | CZ65: =SUM(CZ66:CZ75) -> 0
C66: 入荷：7月 289枚 11月 610枚 | D66: 1 | E66: +1.00 | F66: 60 | G66: =F66*3630 -> 217800 | H66: 250 | I66: =H66*3630 -> 907500 | J66: 0 | K66: =SUM(L66:N66) -> 13 | L66: 0 | M66: 13 | O66: 45594 | R66: 45687 | AI66: =SUM(J66:K66)-CI66+CJ66 -> 0 | AJ66: =AI66-CK66+CL66 -> -19.04168 | AK66: =AJ66-CM66+CN66 -> -49.04168 | AL66: =AK66-CO66+CP66 -> -74.04168 | AM66: =0-CQ66+CR66 -> 77.5 | AN66: =AM66-CS66+CT66 -> 52.5 | AO66: =AN66-CU66+CV66 -> 37.276406 | AP66: =AO66-CW66+CX66 -> 23.370626 | AQ66: =AP66-CY66+CZ66 -> 3.3706259 | AS66: =$H$66*月別販売比率!AG5 -> 25 | AT66: 30 | AU66: =$H$66*月別販売比率!AL5 -> 22.5 | AW66: =$H$66*月別販売比率!AQ5 -> 25 | AY66: =$H$66*月別販売比率!AV5 -> 15.223594 | AZ66: 40 | BA66: =$H$66*月別販売比率!BA5 -> 13.90578 | BC66: =$H$66*月別販売比率!BF5 -> 20 | BD66: 3 | BE66: =$H$66*月別販売比率!C21 -> 17.716063 | BG66: =$H$66*月別販売比率!H21 -> 17.5 | BH66: 50 | BI66: =$H$66*月別販売比率!M21 -> 25.265922 | BK66: =$H$66*月別販売比率!R21 -> 20 | BL66: 40 | BM66: =$H$66*月別販売比率!W21 -> 19.04168 | BN66: 28 | BO66: =$H$66*月別販売比率!AB21 -> 30 | BQ66: =$H$66*月別販売比率!AG21 -> 25 | BS66: =$H$66*月別販売比率!AL21 -> 22.5 | BU66: =$H$66*月別販売比率!AQ21 -> 25 | BV66: 69 | BW66: =$H$66*月別販売比率!AV21 -> 15.223594 | BY66: =$H$66*月別販売比率!BA21 -> 13.90578 | CA66: =$H$66*月別販売比率!BF21 -> 20 | CC66: =H66*月別販売比率!$C$21 -> 17.716063 | CD66: 10 | CE66: =H66*月別販売比率!$H$21 -> 17.5 | CG66: =H66*月別販売比率!$M$21 -> 25.265922 | CI66: =H66*月別販売比率!$R$21 -> 20 | CJ66: 7 | CK66: =H66*月別販売比率!$W$21 -> 19.04168 | CM66: =H66*月別販売比率!$AB$21 -> 30 | CO66: =H66*月別販売比率!$AG$21 -> 25 | CQ66: =H66*月別販売比率!$AL$21 -> 22.5 | CR66: 100 | CS66: =H66*月別販売比率!$AQ$21 -> 25 | CU66: =H66*月別販売比率!$AV$21 -> 15.223594 | CW66: =H66*月別販売比率!$BA$21 -> 13.90578 | CY66: =H66*月別販売比率!$BF$21 -> 20
E67: +1.50 | F67: 88 | G67: =F67*3630 -> 319440 | H67: =F67*($H$65/$F$65) -> 250.88278 | I67: =H67*3630 -> 910704.49 | J67: 19 | K67: =SUM(L67:N67) -> 93 | L67: 8 | M67: 15 | N67: 70 | O67: 45594 | R67: 45687 | U67: 45765 | AI67: =SUM(J67:K67)-CI67+CJ67 -> 148.92938 | AJ67: =AI67-CK67+CL67 -> 129.82046 | AK67: =AJ67-CM67+CN67 -> 99.714526 | AL67: =AK67-CO67+CP67 -> 74.626248 | AM67: =AL67-CQ67+CR67 -> 92.046798 | AN67: =AM67-CS67+CT67 -> 66.95852 | AO67: =AN67-CU67+CV67 -> 51.68117 | AP67: =AO67-CW67+CX67 -> 37.726287 | AQ67: =AP67-CY67+CZ67 -> 17.655665 | AS67: =$H$67*月別販売比率!AG5 -> 25.088278 | AT67: 50 | AU67: =$H$67*月別販売比率!AL5 -> 22.57945 | AW67: =$H$67*月別販売比率!AQ5 -> 25.088278 | AY67: =$H$67*月別販売比率!AV5 -> 15.27735 | AZ67: 50 | BA67: =$H$67*月別販売比率!BA5 -> 13.954883 | BC67: =$H$67*月別販売比率!BF5 -> 20.070622 | BD67: 40 | BE67: =$H$67*月別販売比率!C21 -> 17.77862 | BG67: =$H$67*月別販売比率!H21 -> 17.561795 | BH67: 55 | BI67: =$H$67*月別販売比率!M21 -> 25.355139 | BK67: =$H$67*月別販売比率!R21 -> 20.070622 | BL67: 60 | BM67: =$H$67*月別販売比率!W21 -> 19.108918 | BN67: 42 | BO67: =$H$67*月別販売比率!AB21 -> 30.105933 | BQ67: =$H$67*月別販売比率!AG21 -> 25.088278 | BS67: =$H$67*月別販売比率!AL21 -> 22.57945 | BU67: =$H$67*月別販売比率!AQ21 -> 25.088278 | BV67: 59 | BW67: =$H$67*月別販売比率!AV21 -> 15.27735 | BY67: =$H$67*月別販売比率!BA21 -> 13.954883 | CA67: =$H$67*月別販売比率!BF21 -> 20.070622 | CC67: =H67*月別販売比率!$C$21 -> 17.77862 | CD67: 20 | CE67: =H67*月別販売比率!$H$21 -> 17.561795 | CG67: =H67*月別販売比率!$M$21 -> 25.355139 | CI67: =H67*月別販売比率!$R$21 -> 20.070622 | CJ67: 57 | CK67: =H67*月別販売比率!$W$21 -> 19.108918 | CM67: =H67*月別販売比率!$AB$21 -> 30.105933 | CO67: =H67*月別販売比率!$AG$21 -> 25.088278 | CQ67: =H67*月別販売比率!$AL$21 -> 22.57945 | CR67: 40 | CS67: =H67*月別販売比率!$AQ$21 -> 25.088278 | CU67: =H67*月別販売比率!$AV$21 -> 15.27735 | CW67: =H67*月別販売比率!$BA$21 -> 13.954883 | CY67: =H67*月別販売比率!$BF$21 -> 20.070622
E68: +2.00 | F68: 66 | G68: =F68*3630 -> 239580 | H68: =F68*($H$65/$F$65) -> 188.16208 | I68: =H68*3630 -> 683028.36 | J68: 1 | K68: =SUM(L68:N68) -> 71 | L68: 8 | M68: 13 | N68: 50 | O68: 45594 | R68: 45687 | AI68: =SUM(J68:K68)-CI68+CJ68 -> 123.94703 | AJ68: =AI68-CK68+CL68 -> 109.61534 | AK68: =AJ68-CM68+CN68 -> 87.035894 | AL68: =AK68-CO68+CP68 -> 68.219686 | AM68: =AL68-CQ68+CR68 -> 61.285098 | AN68: =AM68-CS68+CT68 -> 42.46889 | AO68: =AN68-CU68+CV68 -> 31.010877 | AP68: =AO68-CW68+CX68 -> 20.544715 | AQ68: =AP68-CY68+CZ68 -> 5.4917484 | AS68: =$H$68*月別販売比率!AG5 -> 18.816208 | AT68: 30 | AU68: =$H$68*月別販売比率!AL5 -> 16.934588 | AW68: =$H$68*月別販売比率!AQ5 -> 18.816208 | AY68: =$H$68*月別販売比率!AV5 -> 11.458013 | AZ68: 43 | BA68: =$H$68*月別販売比率!BA5 -> 10.466162 | BC68: =$H$68*月別販売比率!BF5 -> 15.052967 | BD68: 20 | BE68: =$H$68*月別販売比率!C21 -> 13.333965 | BG68: =$H$68*月別販売比率!H21 -> 13.171346 | BH68: 45 | BI68: =$H$68*月別販売比率!M21 -> 19.016354 | BK68: =$H$68*月別販売比率!R21 -> 15.052967 | BL68: 45 | BM68: =$H$68*月別販売比率!W21 -> 14.331689 | BN68: 31 | BO68: =$H$68*月別販売比率!AB21 -> 22.57945 | BQ68: =$H$68*月別販売比率!AG21 -> 18.816208 | BS68: =$H$68*月別販売比率!AL21 -> 16.934588 | BU68: =$H$68*月別販売比率!AQ21 -> 18.816208 | BV68: 37 | BW68: =$H$68*月別販売比率!AV21 -> 11.458013 | BY68: =$H$68*月別販売比率!BA21 -> 10.466162 | CA68: =$H$68*月別販売比率!BF21 -> 15.052967 | CC68: =H68*月別販売比率!$C$21 -> 13.333965 | CE68: =H68*月別販売比率!$H$21 -> 13.171346 | CG68: =H68*月別販売比率!$M$21 -> 19.016354 | CI68: =H68*月別販売比率!$R$21 -> 15.052967 | CJ68: 67 | CK68: =H68*月別販売比率!$W$21 -> 14.331689 | CM68: =H68*月別販売比率!$AB$21 -> 22.57945 | CO68: =H68*月別販売比率!$AG$21 -> 18.816208 | CQ68: =H68*月別販売比率!$AL$21 -> 16.934588 | CR68: 10 | CS68: =H68*月別販売比率!$AQ$21 -> 18.816208 | CU68: =H68*月別販売比率!$AV$21 -> 11.458013 | CW68: =H68*月別販売比率!$BA$21 -> 10.466162 | CY68: =H68*月別販売比率!$BF$21 -> 15.052967
E69: +2.50 | F69: 70 | G69: =F69*3630 -> 254100 | H69: 160 | I69: =H69*3630 -> 580800 | J69: 83 | K69: =SUM(L69:N69) -> 51 | L69: 10 | M69: 13 | N69: 28 | O69: 45594 | R69: 45687 | AI69: =SUM(J69:K69)-CI69+CJ69 -> 121.2 | AJ69: =AI69-CK69+CL69 -> 109.01332 | AK69: =AJ69-CM69+CN69 -> 89.813325 | AL69: =AK69-CO69+CP69 -> 73.813325 | AM69: =AL69-CQ69+CR69 -> 79.413325 | AN69: =AM69-CS69+CT69 -> 63.413325 | AO69: =AN69-CU69+CV69 -> 53.670225 | AP69: =AO69-CW69+CX69 -> 44.770525 | AQ69: =AP69-CY69+CZ69 -> 31.970525 | AS69: =$H$69*月別販売比率!AG5 -> 16 | AT69: 50 | AU69: =$H$69*月別販売比率!AL5 -> 14.4 | AW69: =$H$69*月別販売比率!AQ5 -> 16 | AY69: =$H$69*月別販売比率!AV5 -> 9.7431001 | AZ69: 20 | BA69: =$H$69*月別販売比率!BA5 -> 8.8996993 | BC69: =$H$69*月別販売比率!BF5 -> 12.8 | BD69: 27 | BE69: =$H$69*月別販売比率!C21 -> 11.33828 | BG69: =$H$69*月別販売比率!H21 -> 11.2 | BH69: 60 | BI69: =$H$69*月別販売比率!M21 -> 16.17019 | BK69: =$H$69*月別販売比率!R21 -> 12.8 | BL69: 40 | BM69: =$H$69*月別販売比率!W21 -> 12.186675 | BN69: 35 | BO69: =$H$69*月別販売比率!AB21 -> 19.2 | BQ69: =$H$69*月別販売比率!AG21 -> 16 | BS69: =$H$69*月別販売比率!AL21 -> 14.4 | BU69: =$H$69*月別販売比率!AQ21 -> 16 | BV69: 12 | BW69: =$H$69*月別販売比率!AV21 -> 9.7431001 | BY69: =$H$69*月別販売比率!BA21 -> 8.8996993 | CA69: =$H$69*月別販売比率!BF21 -> 12.8 | CC69: =H69*月別販売比率!$C$21 -> 11.33828 | CE69: =H69*月別販売比率!$H$21 -> 11.2 | CG69: =H69*月別販売比率!$M$21 -> 16.17019 | CI69: =H69*月別販売比率!$R$21 -> 12.8 | CK69: =H69*月別販売比率!$W$21 -> 12.186675 | CM69: =H69*月別販売比率!$AB$21 -> 19.2 | CO69: =H69*月別販売比率!$AG$21 -> 16 | CQ69: =H69*月別販売比率!$AL$21 -> 14.4 | CR69: 20 | CS69: =H69*月別販売比率!$AQ$21 -> 16 | CU69: =H69*月別販売比率!$AV$21 -> 9.7431001 | CW69: =H69*月別販売比率!$BA$21 -> 8.8996993 | CY69: =H69*月別販売比率!$BF$21 -> 12.8
E70: +3.00 | F70: 44 | G70: =F70*3630 -> 159720 | H70: =F70*($H$65/$F$65) -> 125.44139 | I70: =H70*3630 -> 455352.24 | J70: 30 | K70: =SUM(L70:N70) -> 42 | L70: 3 | M70: 9 | N70: 30 | O70: 45594 | R70: 45687 | AI70: =SUM(J70:K70)-CI70+CJ70 -> 61.964689 | AJ70: =AI70-CK70+CL70 -> 52.41023 | AK70: =AJ70-CM70+CN70 -> 37.357263 | AL70: =AK70-CO70+CP70 -> 24.813124 | AM70: =AL70-CQ70+CR70 -> 48.523399 | AN70: =AM70-CS70+CT70 -> 35.97926 | AO70: =AN70-CU70+CV70 -> 28.340585 | AP70: =AO70-CW70+CX70 -> 21.363143 | AQ70: =AP70-CY70+CZ70 -> 11.327832 | AS70: =$H$70*月別販売比率!AG5 -> 12.544139 | AT70: 30 | AU70: =$H$70*月別販売比率!AL5 -> 11.289725 | AW70: =$H$70*月別販売比率!AQ5 -> 12.544139 | AY70: =$H$70*月別販売比率!AV5 -> 7.6386751 | BA70: =$H$70*月別販売比率!BA5 -> 6.9774415 | BC70: =$H$70*月別販売比率!BF5 -> 10.035311 | BD70: 11 | BE70: =$H$70*月別販売比率!C21 -> 8.8893101 | BG70: =$H$70*月別販売比率!H21 -> 8.7808973 | BH70: 40 | BI70: =$H$70*月別販売比率!M21 -> 12.67757 | BK70: =$H$70*月別販売比率!R21 -> 10.035311 | BL70: 30 | BM70: =$H$70*月別販売比率!W21 -> 9.5544592 | BN70: 23 | BO70: =$H$70*月別販売比率!AB21 -> 15.052967 | BQ70: =$H$70*月別販売比率!AG21 -> 12.544139 | BS70: =$H$70*月別販売比率!AL21 -> 11.289725 | BU70: =$H$70*月別販売比率!AQ21 -> 12.544139 | BW70: =$H$70*月別販売比率!AV21 -> 7.6386751 | BY70: =$H$70*月別販売比率!BA21 -> 6.9774415 | CA70: =$H$70*月別販売比率!BF21 -> 10.035311 | CC70: =H70*月別販売比率!$C$21 -> 8.8893101 | CE70: =H70*月別販売比率!$H$21 -> 8.7808973 | CG70: =H70*月別販売比率!$M$21 -> 12.67757 | CI70: =H70*月別販売比率!$R$21 -> 10.035311 | CK70: =H70*月別販売比率!$W$21 -> 9.5544592 | CM70: =H70*月別販売比率!$AB$21 -> 15.052967 | CO70: =H70*月別販売比率!$AG$21 -> 12.544139 | CQ70: =H70*月別販売比率!$AL$21 -> 11.289725 | CR70: 35 | CS70: =H70*月別販売比率!$AQ$21 -> 12.544139 | CU70: =H70*月別販売比率!$AV$21 -> 7.6386751 | CW70: =H70*月別販売比率!$BA$21 -> 6.9774415 | CY70: =H70*月別販売比率!$BF$21 -> 10.035311
D71: 2 | E71: +1.00 | F71: 97 | G71: =F71*3630 -> 352110 | H71: =F71*($H$65/$F$65) -> 276.54124 | I71: =H71*3630 -> 1003844.7 | J71: 7 | K71: =SUM(L71:N71) -> 70 | L71: 2 | M71: 13 | N71: 55 | O71: 45594 | R71: 45687 | AI71: =SUM(J71:K71)-CI71+CJ71 -> 54.8767 | AJ71: =AI71-CK71+CL71 -> 33.813461 | AK71: =AJ71-CM71+CN71 -> 0.62851145 | AL71: =AK71-CO71+CP71 -> -27.025613 | AM71: =0-CQ71+CR71 -> 85.111288 | AN71: =AM71-CS71+CT71 -> 57.457164 | AO71: =AN71-CU71+CV71 -> 40.617357 | AP71: =AO71-CW71+CX71 -> 25.23527 | AQ71: =AP71-CY71+CZ71 -> 3.1119706 | AS71: =$H$71*月別販売比率!AG5 -> 27.654124 | AT71: 36 | AU71: =$H$71*月別販売比率!AL5 -> 24.888712 | AW71: =$H$71*月別販売比率!AQ5 -> 27.654124 | AY71: =$H$71*月別販売比率!AV5 -> 16.839806 | AZ71: 55 | BA71: =$H$71*月別販売比率!BA5 -> 15.382087 | BC71: =$H$71*月別販売比率!BF5 -> 22.1233 | BD71: 38 | BE71: =$H$71*月別販売比率!C21 -> 19.596888 | BG71: =$H$71*月別販売比率!H21 -> 19.357887 | BH71: 75 | BI71: =$H$71*月別販売比率!M21 -> 27.948278 | BK71: =$H$71*月別販売比率!R21 -> 22.1233 | BL71: 60 | BM71: =$H$71*月別販売比率!W21 -> 21.06324 | BN71: 50 | BO71: =$H$71*月別販売比率!AB21 -> 33.184949 | BQ71: =$H$71*月別販売比率!AG21 -> 27.654124 | BS71: =$H$71*月別販売比率!AL21 -> 24.888712 | BU71: =$H$71*月別販売比率!AQ21 -> 27.654124 | BV71: 112 | BW71: =$H$71*月別販売比率!AV21 -> 16.839806 | BY71: =$H$71*月別販売比率!BA21 -> 15.382087 | CA71: =$H$71*月別販売比率!BF21 -> 22.1233 | CC71: =H71*月別販売比率!$C$21 -> 19.596888 | CE71: =H71*月別販売比率!$H$21 -> 19.357887 | CG71: =H71*月別販売比率!$M$21 -> 27.948278 | CI71: =H71*月別販売比率!$R$21 -> 22.1233 | CK71: =H71*月別販売比率!$W$21 -> 21.06324 | CM71: =H71*月別販売比率!$AB$21 -> 33.184949 | CO71: =H71*月別販売比率!$AG$21 -> 27.654124 | CQ71: =H71*月別販売比率!$AL$21 -> 24.888712 | CR71: 110 | CS71: =H71*月別販売比率!$AQ$21 -> 27.654124 | CU71: =H71*月別販売比率!$AV$21 -> 16.839806 | CW71: =H71*月別販売比率!$BA$21 -> 15.382087 | CY71: =H71*月別販売比率!$BF$21 -> 22.1233
E72: +1.50 | F72: 78 | G72: =F72*3630 -> 283140 | H72: 260 | I72: =H72*3630 -> 943800 | J72: 13 | K72: =SUM(L72:N72) -> 62 | L72: 4 | M72: 13 | N72: 45 | O72: 45594 | R72: 45687 | U72: 45765 | AI72: =SUM(J72:K72)-CI72+CJ72 -> 141.2 | AJ72: =AI72-CK72+CL72 -> 121.39665 | AK72: =AJ72-CM72+CN72 -> 90.196653 | AL72: =AK72-CO72+CP72 -> 64.196653 | AM72: =AL72-CQ72+CR72 -> 100.79665 | AN72: =AM72-CS72+CT72 -> 74.796653 | AO72: =AN72-CU72+CV72 -> 58.964115 | AP72: =AO72-CW72+CX72 -> 44.502104 | AQ72: =AP72-CY72+CZ72 -> 23.702104 | AS72: =$H$72*月別販売比率!AG5 -> 26 | AT72: 50 | AU72: =$H$72*月別販売比率!AL5 -> 23.4 | AW72: =$H$72*月別販売比率!AQ5 -> 26 | AY72: =$H$72*月別販売比率!AV5 -> 15.832538 | AZ72: 35 | BA72: =$H$72*月別販売比率!BA5 -> 14.462011 | BC72: =$H$72*月別販売比率!BF5 -> 20.8 | BD72: 45 | BE72: =$H$72*月別販売比率!C21 -> 18.424705 | BG72: =$H$72*月別販売比率!H21 -> 18.2 | BH72: 50 | BI72: =$H$72*月別販売比率!M21 -> 26.276559 | BK72: =$H$72*月別販売比率!R21 -> 20.8 | BL72: 55 | BM72: =$H$72*月別販売比率!W21 -> 19.803347 | BN72: 39 | BO72: =$H$72*月別販売比率!AB21 -> 31.2 | BQ72: =$H$72*月別販売比率!AG21 -> 26 | BS72: =$H$72*月別販売比率!AL21 -> 23.4 | BU72: =$H$72*月別販売比率!AQ21 -> 26 | BV72: 29 | BW72: =$H$72*月別販売比率!AV21 -> 15.832538 | BY72: =$H$72*月別販売比率!BA21 -> 14.462011 | CA72: =$H$72*月別販売比率!BF21 -> 20.8 | CC72: =H72*月別販売比率!$C$21 -> 18.424705 | CD72: 40 | CE72: =H72*月別販売比率!$H$21 -> 18.2 | CG72: =H72*月別販売比率!$M$21 -> 26.276559 | CI72: =H72*月別販売比率!$R$21 -> 20.8 | CJ72: 87 | CK72: =H72*月別販売比率!$W$21 -> 19.803347 | CM72: =H72*月別販売比率!$AB$21 -> 31.2 | CO72: =H72*月別販売比率!$AG$21 -> 26 | CQ72: =H72*月別販売比率!$AL$21 -> 23.4 | CR72: 60 | CS72: =H72*月別販売比率!$AQ$21 -> 26 | CU72: =H72*月別販売比率!$AV$21 -> 15.832538 | CW72: =H72*月別販売比率!$BA$21 -> 14.462011 | CY72: =H72*月別販売比率!$BF$21 -> 20.8
E73: +2.00 | F73: 63 | G73: =F73*3630 -> 228690 | H73: 230 | I73: =H73*3630 -> 834900 | J73: 9 | K73: =SUM(L73:N73) -> 42 | L73: 6 | M73: 10 | N73: 26 | O73: 45594 | R73: 45687 | U73: 45765 | AI73: =SUM(J73:K73)-CI73+CJ73 -> 89.6 | AJ73: =AI73-CK73+CL73 -> 72.081654 | AK73: =AJ73-CM73+CN73 -> 44.481654 | AL73: =AK73-CO73+CP73 -> 21.481654 | AM73: =AL73-CQ73+CR73 -> 90.781654 | AN73: =AM73-CS73+CT73 -> 67.781654 | AO73: =AN73-CU73+CV73 -> 53.775948 | AP73: =AO73-CW73+CX73 -> 40.98263 | AQ73: =AP73-CY73+CZ73 -> 22.58263 | AS73: =$H$73*月別販売比率!AG5 -> 23 | AT73: 40 | AU73: =$H$73*月別販売比率!AL5 -> 20.7 | AW73: =$H$73*月別販売比率!AQ5 -> 23 | AY73: =$H$73*月別販売比率!AV5 -> 14.005706 | AZ73: 28 | BA73: =$H$73*月別販売比率!BA5 -> 12.793318 | BC73: =$H$73*月別販売比率!BF5 -> 18.4 | BD73: 4 | BE73: =$H$73*月別販売比率!C21 -> 16.298778 | BG73: =$H$73*月別販売比率!H21 -> 16.1 | BH73: 48 | BI73: =$H$73*月別販売比率!M21 -> 23.244648 | BK73: =$H$73*月別販売比率!R21 -> 18.4 | BL73: 50 | BM73: =$H$73*月別販売比率!W21 -> 17.518346 | BN73: 33 | BO73: =$H$73*月別販売比率!AB21 -> 27.6 | BQ73: =$H$73*月別販売比率!AG21 -> 23 | BS73: =$H$73*月別販売比率!AL21 -> 20.7 | BU73: =$H$73*月別販売比率!AQ21 -> 23 | BV73: 67 | BW73: =$H$73*月別販売比率!AV21 -> 14.005706 | BY73: =$H$73*月別販売比率!BA21 -> 12.793318 | CA73: =$H$73*月別販売比率!BF21 -> 18.4 | CC73: =H73*月別販売比率!$C$21 -> 16.298778 | CD73: 20 | CE73: =H73*月別販売比率!$H$21 -> 16.1 | CG73: =H73*月別販売比率!$M$21 -> 23.244648 | CI73: =H73*月別販売比率!$R$21 -> 18.4 | CJ73: 57 | CK73: =H73*月別販売比率!$W$21 -> 17.518346 | CM73: =H73*月別販売比率!$AB$21 -> 27.6 | CO73: =H73*月別販売比率!$AG$21 -> 23 | CQ73: =H73*月別販売比率!$AL$21 -> 20.7 | CR73: 90 | CS73: =H73*月別販売比率!$AQ$21 -> 23 | CU73: =H73*月別販売比率!$AV$21 -> 14.005706 | CW73: =H73*月別販売比率!$BA$21 -> 12.793318 | CY73: =H73*月別販売比率!$BF$21 -> 18.4
E74: +2.50 | F74: 69 | G74: =F74*3630 -> 250470 | H74: =F74*($H$65/$F$65) -> 196.71491 | I74: =H74*3630 -> 714075.11 | J74: 11 | K74: =SUM(L74:N74) -> 38 | L74: 5 | M74: 9 | N74: 24 | O74: 45594 | R74: 45687 | U74: 45765 | AI74: =SUM(J74:K74)-CI74+CJ74 -> 40.262808 | AJ74: =AI74-CK74+CL74 -> 25.279678 | AK74: =AJ74-CM74+CN74 -> 1.6738896 | AL74: =AK74-CO74+CP74 -> -17.997601 | AM74: =0-CQ74+CR74 -> 62.295658 | AN74: =AM74-CS74+CT74 -> 42.624168 | AO74: =AN74-CU74+CV74 -> 30.645337 | AP74: =AO74-CW74+CX74 -> 19.70344 | AQ74: =AP74-CY74+CZ74 -> 3.9662471 | AS74: =$H$74*月別販売比率!AG5 -> 19.671491 | AT74: 50 | AU74: =$H$74*月別販売比率!AL5 -> 17.704342 | AW74: =$H$74*月別販売比率!AQ5 -> 19.671491 | AY74: =$H$74*月別販売比率!AV5 -> 11.978831 | AZ74: 30 | BA74: =$H$74*月別販売比率!BA5 -> 10.941897 | BC74: =$H$74*月別販売比率!BF5 -> 15.737192 | BD74: 16 | BE74: =$H$74*月別販売比率!C21 -> 13.940054 | BG74: =$H$74*月別販売比率!H21 -> 13.770043 | BH74: 60 | BI74: =$H$74*月別販売比率!M21 -> 19.880734 | BK74: =$H$74*月別販売比率!R21 -> 15.737192 | BL74: 50 | BM74: =$H$74*月別販売比率!W21 -> 14.983129 | BN74: 36 | BO74: =$H$74*月別販売比率!AB21 -> 23.605789 | BQ74: =$H$74*月別販売比率!AG21 -> 19.671491 | BS74: =$H$74*月別販売比率!AL21 -> 17.704342 | BU74: =$H$74*月別販売比率!AQ21 -> 19.671491 | BV74: 32 | BW74: =$H$74*月別販売比率!AV21 -> 11.978831 | BY74: =$H$74*月別販売比率!BA21 -> 10.941897 | CA74: =$H$74*月別販売比率!BF21 -> 15.737192 | CC74: =H74*月別販売比率!$C$21 -> 13.940054 | CD74: 10 | CE74: =H74*月別販売比率!$H$21 -> 13.770043 | CG74: =H74*月別販売比率!$M$21 -> 19.880734 | CI74: =H74*月別販売比率!$R$21 -> 15.737192 | CJ74: 7 | CK74: =H74*月別販売比率!$W$21 -> 14.983129 | CM74: =H74*月別販売比率!$AB$21 -> 23.605789 | CO74: =H74*月別販売比率!$AG$21 -> 19.671491 | CQ74: =H74*月別販売比率!$AL$21 -> 17.704342 | CR74: 80 | CS74: =H74*月別販売比率!$AQ$21 -> 19.671491 | CU74: =H74*月別販売比率!$AV$21 -> 11.978831 | CW74: =H74*月別販売比率!$BA$21 -> 10.941897 | CY74: =H74*月別販売比率!$BF$21 -> 15.737192
E75: +3.00 | F75: 56 | G75: =F75*3630 -> 203280 | H75: =F75*($H$65/$F$65) -> 159.65268 | I75: =H75*3630 -> 579539.22 | J75: 5 | K75: =SUM(L75:N75) -> 26 | L75: 4 | M75: 6 | N75: 16 | O75: 45594 | R75: 45687 | U75: 45765 | AI75: =SUM(J75:K75)-CI75+CJ75 -> 25.227786 | AJ75: =AI75-CK75+CL75 -> 13.067565 | AK75: =AJ75-CM75+CN75 -> -6.0907563 | AL75: =AK75-CO75+CP75 -> -22.056024 | AM75: =0-CQ75+CR75 -> 50.631259 | AN75: =AM75-CS75+CT75 -> 34.665991 | AO75: =AN75-CU75+CV75 -> 24.944041 | AP75: =AO75-CW75+CX75 -> 16.063661 | AQ75: =AP75-CY75+CZ75 -> 3.2914469 | AS75: =$H$75*月別販売比率!AG5 -> 15.965268 | AT75: 50 | AU75: =$H$75*月別販売比率!AL5 -> 14.368741 | AW75: =$H$75*月別販売比率!AQ5 -> 15.965268 | AY75: =$H$75*月別販売比率!AV5 -> 9.7219501 | AZ75: 10 | BA75: =$H$75*月別販売比率!BA5 -> 8.8803801 | BC75: =$H$75*月別販売比率!BF5 -> 12.772214 | BD75: 20 | BE75: =$H$75*月別販売比率!C21 -> 11.313667 | BG75: =$H$75*月別販売比率!H21 -> 11.175687 | BH75: 55 | BI75: =$H$75*月別販売比率!M21 -> 16.135089 | BK75: =$H$75*月別販売比率!R21 -> 12.772214 | BL75: 35 | BM75: =$H$75*月別販売比率!W21 -> 12.160221 | BN75: 29 | BO75: =$H$75*月別販売比率!AB21 -> 19.158321 | BQ75: =$H$75*月別販売比率!AG21 -> 15.965268 | BS75: =$H$75*月別販売比率!AL21 -> 14.368741 | BU75: =$H$75*月別販売比率!AQ21 -> 15.965268 | BW75: =$H$75*月別販売比率!AV21 -> 9.7219501 | BY75: =$H$75*月別販売比率!BA21 -> 8.8803801 | CA75: =$H$75*月別販売比率!BF21 -> 12.772214 | CC75: =H75*月別販売比率!$C$21 -> 11.313667 | CD75: 10 | CE75: =H75*月別販売比率!$H$21 -> 11.175687 | CG75: =H75*月別販売比率!$M$21 -> 16.135089 | CI75: =H75*月別販売比率!$R$21 -> 12.772214 | CJ75: 7 | CK75: =H75*月別販売比率!$W$21 -> 12.160221 | CM75: =H75*月別販売比率!$AB$21 -> 19.158321 | CO75: =H75*月別販売比率!$AG$21 -> 15.965268 | CQ75: =H75*月別販売比率!$AL$21 -> 14.368741 | CR75: 65 | CS75: =H75*月別販売比率!$AQ$21 -> 15.965268 | CU75: =H75*月別販売比率!$AV$21 -> 9.7219501 | CW75: =H75*月別販売比率!$BA$21 -> 8.8803801 | CY75: =H75*月別販売比率!$BF$21 -> 12.772214
B76: 6 | C76: si-13 | F76: =SUM(F77:F88) -> 272 | G76: =SUM(G77:G88) -> 1795200 | H76: 1250 | I76: =SUM(I77:I88) -> 8250000 | J76: =SUM(J77:J88) -> 137 | K76: =SUM(K77:K88) -> 515 | L76: =SUM(L77:L88) -> 113 | M76: =SUM(M77:M88) -> 96 | N76: =SUM(N77:N88) -> 306 | AS76: =SUM(AS77:AS88) -> 125 | AT76: =SUM(AT77:AT88) -> 0 | AU76: =SUM(AU77:AU88) -> 112.5 | AV76: =SUM(AV77:AV88) -> 0 | AW76: =SUM(AW77:AW88) -> 125 | AX76: =SUM(AX77:AX88) -> 0 | AY76: =SUM(AY77:AY88) -> 76.117969 | AZ76: =SUM(AZ77:AZ88) -> 0 | ... CT76: =SUM(CT77:CT88) -> 0 | CU76: 76.117969 | CV76: =SUM(CV77:CV88) -> 0 | CW76: =SUM(CW77:CW88) -> 69.528901 | CX76: =SUM(CX77:CX88) -> 0 | CY76: =SUM(CY77:CY88) -> 100 | CZ76: =SUM(CZ77:CZ88) -> 0
C77: 入荷：8月 170枚 10月 185枚 | D77: 1 | E77: +1.50 | F77: 31 | G77: =F77*6600 -> 204600 | H77: =F77*($H$76/$F$76) -> 142.46324 | I77: =H77*6600 -> 940257.35 | J77: 3 | K77: =SUM(L77:N77) -> 57 | L77: 9 | M77: 3 | N77: 45 | S77: 45716 | V77: 45786 | Y77: 45879 | AH77: 46172 | AI77: =SUM(J77:K77)-CI77+CJ77 -> 58.602941 | AJ77: =AI77-CK77+CL77 -> 77.751984 | AK77: =AJ77-CM77+CN77 -> 60.656396 | AL77: =AK77-CO77+CP77 -> 66.410072 | AM77: =AL77-CQ77+CR77 -> 53.588381 | AN77: =AM77-CS77+CT77 -> 39.342057 | AO77: =AN77-CU77+CV77 -> 30.666848 | AP77: =AO77-CW77+CX77 -> 22.742598 | AQ77: =AP77-CY77+CZ77 -> 11.345539 | AS77: =$H$77*月別販売比率!AG5 -> 14.246324 | AU77: =$H$77*月別販売比率!AL5 -> 12.821691 | AW77: =$H$77*月別販売比率!AQ5 -> 14.246324 | AY77: =$H$77*月別販売比率!AV5 -> 8.6752097 | BA77: =$H$77*月別販売比率!BA5 -> 7.9242497 | BB77: 20 | BC77: =$H$77*月別販売比率!BF5 -> 11.397059 | BE77: =$H$77*月別販売比率!C21 -> 10.09555 | BG77: =$H$77*月別販売比率!H21 -> 9.9724265 | BH77: 10 | BI77: =$H$77*月別販売比率!M21 -> 14.39786 | BK77: =$H$77*月別販売比率!R21 -> 11.397059 | BM77: =$H$77*月別販売比率!W21 -> 10.850957 | BN77: 37 | BO77: =$H$77*月別販売比率!AB21 -> 17.095588 | BQ77: =$H$77*月別販売比率!AG21 -> 14.246324 | BS77: =$H$77*月別販売比率!AL21 -> 12.821691 | BU77: =$H$77*月別販売比率!AQ21 -> 14.246324 | BV77: 10 | BW77: =$H$77*月別販売比率!AV21 -> 8.6752097 | BY77: =$H$77*月別販売比率!BA21 -> 7.9242497 | BZ77: 35 | CA77: =$H$77*月別販売比率!BF21 -> 11.397059 | CC77: =H77*月別販売比率!$C$21 -> 10.09555 | CE77: =H77*月別販売比率!$H$21 -> 9.9724265 | CF77: 40 | CG77: =H77*月別販売比率!$M$21 -> 14.39786 | CH77: 40 | CI77: =H77*月別販売比率!$R$21 -> 11.397059 | CJ77: 10 | CK77: =H77*月別販売比率!$W$21 -> 10.850957 | CL77: 30 | CM77: =H77*月別販売比率!$AB$21 -> 17.095588 | CO77: =H77*月別販売比率!$AG$21 -> 14.246324 | CP77: 20 | CQ77: =H77*月別販売比率!$AL$21 -> 12.821691 | CS77: =H77*月別販売比率!$AQ$21 -> 14.246324 | CU77: =H77*月別販売比率!$AV$21 -> 8.6752097 | CW77: =H77*月別販売比率!$BA$21 -> 7.9242497 | CY77: =H77*月別販売比率!$BF$21 -> 11.397059
E78: +2.00 | F78: 33 | G78: =F78*6600 -> 217800 | H78: =F78*($H$76/$F$76) -> 151.65441 | I78: =H78*6600 -> 1000919.1 | J78: 0 | K78: =SUM(L78:N78) -> 46 | L78: 8 | M78: 3 | N78: 35 | S78: 45716 | V78: 45786 | Y78: 45879 | AC78: 46011 | AH78: 46172 | AI78: =SUM(J78:K78)-CI78+CJ78 -> 38.867647 | AJ78: =AI78-CK78+CL78 -> 57.316628 | AK78: =AJ78-CM78+CN78 -> 39.118098 | AL78: =AK78-CO78+CP78 -> 43.952657 | AM78: =AL78-CQ78+CR78 -> 30.30376 | AN78: =AM78-CS78+CT78 -> 15.138319 | AO78: =AN78-CU78+CV78 -> 5.9034184 | AP78: =AO78-CW78+CX78 -> -2.5320733 | AQ78: =AP78-CY78+CZ78 -> -14.664426 | AS78: =$H$78*月別販売比率!AG5 -> 15.165441 | AU78: =$H$78*月別販売比率!AL5 -> 13.648897 | AW78: =$H$78*月別販売比率!AQ5 -> 15.165441 | AY78: =$H$78*月別販売比率!AV5 -> 9.2349007 | BA78: =$H$78*月別販売比率!BA5 -> 8.4354917 | BB78: 18 | BC78: =$H$78*月別販売比率!BF5 -> 12.132353 | BE78: =$H$78*月別販売比率!C21 -> 10.746876 | BG78: =$H$78*月別販売比率!H21 -> 10.615809 | BH78: 20 | BI78: =$H$78*月別販売比率!M21 -> 15.326754 | BK78: =$H$78*月別販売比率!R21 -> 12.132353 | BM78: =$H$78*月別販売比率!W21 -> 11.551019 | BN78: 35 | BO78: =$H$78*月別販売比率!AB21 -> 18.198529 | BQ78: =$H$78*月別販売比率!AG21 -> 15.165441 | BS78: =$H$78*月別販売比率!AL21 -> 13.648897 | BU78: =$H$78*月別販売比率!AQ21 -> 15.165441 | BV78: 25 | BW78: =$H$78*月別販売比率!AV21 -> 9.2349007 | BY78: =$H$78*月別販売比率!BA21 -> 8.4354917 | BZ78: 33 | CA78: =$H$78*月別販売比率!BF21 -> 12.132353 | CC78: =H78*月別販売比率!$C$21 -> 10.746876 | CE78: =H78*月別販売比率!$H$21 -> 10.615809 | CF78: 45 | CG78: =H78*月別販売比率!$M$21 -> 15.326754 | CH78: 40 | CI78: =H78*月別販売比率!$R$21 -> 12.132353 | CJ78: 5 | CK78: =H78*月別販売比率!$W$21 -> 11.551019 | CL78: 30 | CM78: =H78*月別販売比率!$AB$21 -> 18.198529 | CO78: =H78*月別販売比率!$AG$21 -> 15.165441 | CP78: 20 | CQ78: =H78*月別販売比率!$AL$21 -> 13.648897 | CS78: =H78*月別販売比率!$AQ$21 -> 15.165441 | CU78: =H78*月別販売比率!$AV$21 -> 9.2349007 | CW78: =H78*月別販売比率!$BA$21 -> 8.4354917 | CY78: =H78*月別販売比率!$BF$21 -> 12.132353
E79: +2.50 | F79: 22 | G79: =F79*6600 -> 145200 | H79: =F79*($H$76/$F$76) -> 101.10294 | I79: =H79*6600 -> 667279.41 | J79: 16 | K79: =SUM(L79:N79) -> 53 | L79: 10 | M79: 18 | N79: 25 | S79: 45716 | V79: 45786 | X79: 45855 | AH79: 46172 | AI79: =SUM(J79:K79)-CI79+CJ79 -> 65.911765 | AJ79: =AI79-CK79+CL79 -> 78.211085 | AK79: =AJ79-CM79+CN79 -> 66.078732 | AL79: =AK79-CO79+CP79 -> 70.968438 | AM79: =AL79-CQ79+CR79 -> 61.869173 | AN79: =AM79-CS79+CT79 -> 51.758879 | AO79: =AN79-CU79+CV79 -> 45.602279 | AP79: =AO79-CW79+CX79 -> 39.978618 | AQ79: =AP79-CY79+CZ79 -> 31.890383 | AS79: =$H$79*月別販売比率!AG5 -> 10.110294 | AU79: =$H$79*月別販売比率!AL5 -> 9.0992647 | AW79: =$H$79*月別販売比率!AQ5 -> 10.110294 | AY79: =$H$79*月別販売比率!AV5 -> 6.1566005 | BA79: =$H$79*月別販売比率!BA5 -> 5.6236611 | BB79: 17 | BC79: =$H$79*月別販売比率!BF5 -> 8.0882353 | BE79: =$H$79*月別販売比率!C21 -> 7.1645842 | BG79: =$H$79*月別販売比率!H21 -> 7.0772059 | BH79: 10 | BI79: =$H$79*月別販売比率!M21 -> 10.217836 | BK79: =$H$79*月別販売比率!R21 -> 8.0882353 | BM79: =$H$79*月別販売比率!W21 -> 7.7006794 | BN79: 25 | BO79: =$H$79*月別販売比率!AB21 -> 12.132353 | BQ79: =$H$79*月別販売比率!AG21 -> 10.110294 | BS79: =$H$79*月別販売比率!AL21 -> 9.0992647 | BU79: =$H$79*月別販売比率!AQ21 -> 10.110294 | BV79: 10 | BW79: =$H$79*月別販売比率!AV21 -> 6.1566005 | BY79: =$H$79*月別販売比率!BA21 -> 5.6236611 | BZ79: 23 | CA79: =$H$79*月別販売比率!BF21 -> 8.0882353 | CC79: =H79*月別販売比率!$C$21 -> 7.1645842 | CE79: =H79*月別販売比率!$H$21 -> 7.0772059 | CF79: 35 | CG79: =H79*月別販売比率!$M$21 -> 10.217836 | CH79: 20 | CI79: =H79*月別販売比率!$R$21 -> 8.0882353 | CJ79: 5 | CK79: =H79*月別販売比率!$W$21 -> 7.7006794 | CL79: 20 | CM79: =H79*月別販売比率!$AB$21 -> 12.132353 | CO79: =H79*月別販売比率!$AG$21 -> 10.110294 | CP79: 15 | CQ79: =H79*月別販売比率!$AL$21 -> 9.0992647 | CS79: =H79*月別販売比率!$AQ$21 -> 10.110294 | CU79: =H79*月別販売比率!$AV$21 -> 6.1566005 | CW79: =H79*月別販売比率!$BA$21 -> 5.6236611 | CY79: =H79*月別販売比率!$BF$21 -> 8.0882353
E80: +3.00 | F80: 18 | G80: =F80*6600 -> 118800 | H80: =F80*($H$76/$F$76) -> 82.720588 | I80: =H80*6600 -> 545955.88 | J80: 7 | K80: =SUM(L80:N80) -> 39 | L80: 10 | M80: 17 | N80: 12 | S80: 45716 | AC80: 46011 | AI80: =SUM(J80:K80)-CI80+CJ80 -> 39.382353 | AJ80: =AI80-CK80+CL80 -> 48.081797 | AK80: =AJ80-CM80+CN80 -> 38.155326 | AL80: =AK80-CO80+CP80 -> 39.883268 | AM80: =AL80-CQ80+CR80 -> 32.438415 | AN80: =AM80-CS80+CT80 -> 24.166356 | AO80: =AN80-CU80+CV80 -> 19.129137 | AP80: =AO80-CW80+CX80 -> 14.52796 | AQ80: =AP80-CY80+CZ80 -> 7.910313 | AS80: =$H$80*月別販売比率!AG5 -> 8.2720588 | AU80: =$H$80*月別販売比率!AL5 -> 7.4448529 | AW80: =$H$80*月別販売比率!AQ5 -> 8.2720588 | AY80: =$H$80*月別販売比率!AV5 -> 5.0372186 | BA80: =$H$80*月別販売比率!BA5 -> 4.6011773 | BB80: 15 | BC80: =$H$80*月別販売比率!BF5 -> 6.6176471 | BE80: =$H$80*月別販売比率!C21 -> 5.8619325 | BG80: =$H$80*月別販売比率!H21 -> 5.7904412 | BI80: =$H$80*月別販売比率!M21 -> 8.3600478 | BK80: =$H$80*月別販売比率!R21 -> 6.6176471 | BM80: =$H$80*月別販売比率!W21 -> 6.3005559 | BN80: 25 | BO80: =$H$80*月別販売比率!AB21 -> 9.9264706 | BQ80: =$H$80*月別販売比率!AG21 -> 8.2720588 | BS80: =$H$80*月別販売比率!AL21 -> 7.4448529 | BU80: =$H$80*月別販売比率!AQ21 -> 8.2720588 | BV80: 15 | BW80: =$H$80*月別販売比率!AV21 -> 5.0372186 | BY80: =$H$80*月別販売比率!BA21 -> 4.6011773 | BZ80: 5 | CA80: =$H$80*月別販売比率!BF21 -> 6.6176471 | CC80: =H80*月別販売比率!$C$21 -> 5.8619325 | CE80: =H80*月別販売比率!$H$21 -> 5.7904412 | CF80: 20 | CG80: =H80*月別販売比率!$M$21 -> 8.3600478 | CH80: 15 | CI80: =H80*月別販売比率!$R$21 -> 6.6176471 | CK80: =H80*月別販売比率!$W$21 -> 6.3005559 | CL80: 15 | CM80: =H80*月別販売比率!$AB$21 -> 9.9264706 | CO80: =H80*月別販売比率!$AG$21 -> 8.2720588 | CP80: 10 | CQ80: =H80*月別販売比率!$AL$21 -> 7.4448529 | CS80: =H80*月別販売比率!$AQ$21 -> 8.2720588 | CU80: =H80*月別販売比率!$AV$21 -> 5.0372186 | CW80: =H80*月別販売比率!$BA$21 -> 4.6011773 | CY80: =H80*月別販売比率!$BF$21 -> 6.6176471
D81: 2 | E81: +1.50 | F81: 30 | G81: =F81*6600 -> 198000 | H81: =F81*($H$76/$F$76) -> 137.86765 | I81: =H81*6600 -> 909926.47 | J81: 2 | K81: =SUM(L81:N81) -> 59 | L81: 10 | M81: 3 | N81: 46 | S81: 45716 | V81: 45786 | Y81: 45879 | AH81: 46172 | AI81: =SUM(J81:K81)-CI81+CJ81 -> 69.970588 | AJ81: =AI81-CK81+CL81 -> 79.469662 | AK81: =AJ81-CM81+CN81 -> 62.925544 | AL81: =AK81-CO81+CP81 -> 69.138779 | AM81: =AL81-CQ81+CR81 -> 56.730691 | AN81: =AM81-CS81+CT81 -> 42.943926 | AO81: =AN81-CU81+CV81 -> 34.548562 | AP81: =AO81-CW81+CX81 -> 26.879933 | AQ81: =AP81-CY81+CZ81 -> 15.850522 | AS81: =$H$81*月別販売比率!AG5 -> 13.786765 | AU81: =$H$81*月別販売比率!AL5 -> 12.408088 | AW81: =$H$81*月別販売比率!AQ5 -> 13.786765 | AY81: =$H$81*月別販売比率!AV5 -> 8.3953643 | BA81: =$H$81*月別販売比率!BA5 -> 7.6686288 | BB81: 25 | BC81: =$H$81*月別販売比率!BF5 -> 11.029412 | BE81: =$H$81*月別販売比率!C21 -> 9.7698876 | BG81: =$H$81*月別販売比率!H21 -> 9.6507353 | BH81: 20 | BI81: =$H$81*月別販売比率!M21 -> 13.933413 | BK81: =$H$81*月別販売比率!R21 -> 11.029412 | BM81: =$H$81*月別販売比率!W21 -> 10.500927 | BN81: 19 | BO81: =$H$81*月別販売比率!AB21 -> 16.544118 | BQ81: =$H$81*月別販売比率!AG21 -> 13.786765 | BS81: =$H$81*月別販売比率!AL21 -> 12.408088 | BU81: =$H$81*月別販売比率!AQ21 -> 13.786765 | BV81: 11 | BW81: =$H$81*月別販売比率!AV21 -> 8.3953643 | BY81: =$H$81*月別販売比率!BA21 -> 7.6686288 | BZ81: 30 | CA81: =$H$81*月別販売比率!BF21 -> 11.029412 | CC81: =H81*月別販売比率!$C$21 -> 9.7698876 | CE81: =H81*月別販売比率!$H$21 -> 9.6507353 | CF81: 45 | CG81: =H81*月別販売比率!$M$21 -> 13.933413 | CH81: 30 | CI81: =H81*月別販売比率!$R$21 -> 11.029412 | CJ81: 20 | CK81: =H81*月別販売比率!$W$21 -> 10.500927 | CL81: 20 | CM81: =H81*月別販売比率!$AB$21 -> 16.544118 | CO81: =H81*月別販売比率!$AG$21 -> 13.786765 | CP81: 20 | CQ81: =H81*月別販売比率!$AL$21 -> 12.408088 | CS81: =H81*月別販売比率!$AQ$21 -> 13.786765 | CU81: =H81*月別販売比率!$AV$21 -> 8.3953643 | CW81: =H81*月別販売比率!$BA$21 -> 7.6686288 | CY81: =H81*月別販売比率!$BF$21 -> 11.029412
E82: +2.00 | F82: 23 | G82: =F82*6600 -> 151800 | H82: =F82*($H$76/$F$76) -> 105.69853 | I82: =H82*6600 -> 697610.29 | J82: 3 | K82: =SUM(L82:N82) -> 50 | L82: 7 | M82: 5 | N82: 38 | S82: 45716 | V82: 45786 | X82: 45855 | AI82: =SUM(J82:K82)-CI82+CJ82 -> 54.544118 | AJ82: =AI82-CK82+CL82 -> 66.493407 | AK82: =AJ82-CM82+CN82 -> 53.809584 | AL82: =AK82-CO82+CP82 -> 63.239731 | AM82: =AL82-CQ82+CR82 -> 53.726863 | AN82: =AM82-CS82+CT82 -> 43.15701 | AO82: =AN82-CU82+CV82 -> 36.720564 | AP82: =AO82-CW82+CX82 -> 30.841282 | AQ82: =AP82-CY82+CZ82 -> 22.3854 | AS82: =$H$82*月別販売比率!AG5 -> 10.569853 | AU82: =$H$82*月別販売比率!AL5 -> 9.5128676 | AW82: =$H$82*月別販売比率!AQ5 -> 10.569853 | AY82: =$H$82*月別販売比率!AV5 -> 6.4364459 | BA82: =$H$82*月別販売比率!BA5 -> 5.8792821 | BB82: 22 | BC82: =$H$82*月別販売比率!BF5 -> 8.4558824 | BE82: =$H$82*月別販売比率!C21 -> 7.4902471 | BG82: =$H$82*月別販売比率!H21 -> 7.3988971 | BH82: 10 | BI82: =$H$82*月別販売比率!M21 -> 10.682283 | BK82: =$H$82*月別販売比率!R21 -> 8.4558824 | BM82: =$H$82*月別販売比率!W21 -> 8.0507103 | BN82: 30 | BO82: =$H$82*月別販売比率!AB21 -> 12.683824 | BQ82: =$H$82*月別販売比率!AG21 -> 10.569853 | BS82: =$H$82*月別販売比率!AL21 -> 9.5128676 | BU82: =$H$82*月別販売比率!AQ21 -> 10.569853 | BW82: =$H$82*月別販売比率!AV21 -> 6.4364459 | BY82: =$H$82*月別販売比率!BA21 -> 5.8792821 | BZ82: 40 | CA82: =$H$82*月別販売比率!BF21 -> 8.4558824 | CC82: =H82*月別販売比率!$C$21 -> 7.4902471 | CE82: =H82*月別販売比率!$H$21 -> 7.3988971 | CF82: 20 | CG82: =H82*月別販売比率!$M$21 -> 10.682283 | CH82: 40 | CI82: =H82*月別販売比率!$R$21 -> 8.4558824 | CJ82: 10 | CK82: =H82*月別販売比率!$W$21 -> 8.0507103 | CL82: 20 | CM82: =H82*月別販売比率!$AB$21 -> 12.683824 | CO82: =H82*月別販売比率!$AG$21 -> 10.569853 | CP82: 20 | CQ82: =H82*月別販売比率!$AL$21 -> 9.5128676 | CS82: =H82*月別販売比率!$AQ$21 -> 10.569853 | CU82: =H82*月別販売比率!$AV$21 -> 6.4364459 | CW82: =H82*月別販売比率!$BA$21 -> 5.8792821 | CY82: =H82*月別販売比率!$BF$21 -> 8.4558824
E83: +2.50 | F83: 29 | G83: =F83*6600 -> 191400 | H83: =F83*($H$76/$F$76) -> 133.27206 | I83: =H83*6600 -> 879595.59 | J83: 18 | K83: =SUM(L83:N83) -> 58 | L83: 10 | M83: 10 | N83: 38 | S83: 45716 | V83: 45786 | X83: 45855 | AC83: 46011 | AH83: 46172 | AI83: =SUM(J83:K83)-CI83+CJ83 -> 75.338235 | AJ83: =AI83-CK83+CL83 -> 85.18734 | AK83: =AJ83-CM83+CN83 -> 69.194693 | AL83: =AK83-CO83+CP83 -> 75.867487 | AM83: =AL83-CQ83+CR83 -> 63.873001 | AN83: =AM83-CS83+CT83 -> 50.545796 | AO83: =AN83-CU83+CV83 -> 42.430277 | AP83: =AO83-CW83+CX83 -> 35.017269 | AQ83: =AP83-CY83+CZ83 -> 24.355504 | AS83: =$H$83*月別販売比率!AG5 -> 13.327206 | AU83: =$H$83*月別販売比率!AL5 -> 11.994485 | AW83: =$H$83*月別販売比率!AQ5 -> 13.327206 | AY83: =$H$83*月別販売比率!AV5 -> 8.1155188 | BA83: =$H$83*月別販売比率!BA5 -> 7.4130078 | BB83: 25 | BC83: =$H$83*月別販売比率!BF5 -> 10.661765 | BE83: =$H$83*月別販売比率!C21 -> 9.4442246 | BG83: =$H$83*月別販売比率!H21 -> 9.3290441 | BH83: 20 | BI83: =$H$83*月別販売比率!M21 -> 13.468966 | BK83: =$H$83*月別販売比率!R21 -> 10.661765 | BM83: =$H$83*月別販売比率!W21 -> 10.150896 | BN83: 27 | BO83: =$H$83*月別販売比率!AB21 -> 15.992647 | BQ83: =$H$83*月別販売比率!AG21 -> 13.327206 | BS83: =$H$83*月別販売比率!AL21 -> 11.994485 | BU83: =$H$83*月別販売比率!AQ21 -> 13.327206 | BV83: 13 | BW83: =$H$83*月別販売比率!AV21 -> 8.1155188 | BY83: =$H$83*月別販売比率!BA21 -> 7.4130078 | BZ83: 30 | CA83: =$H$83*月別販売比率!BF21 -> 10.661765 | CC83: =H83*月別販売比率!$C$21 -> 9.4442246 | CE83: =H83*月別販売比率!$H$21 -> 9.3290441 | CF83: 40 | CG83: =H83*月別販売比率!$M$21 -> 13.468966 | CH83: 30 | CI83: =H83*月別販売比率!$R$21 -> 10.661765 | CJ83: 10 | CK83: =H83*月別販売比率!$W$21 -> 10.150896 | CL83: 20 | CM83: =H83*月別販売比率!$AB$21 -> 15.992647 | CO83: =H83*月別販売比率!$AG$21 -> 13.327206 | CP83: 20 | CQ83: =H83*月別販売比率!$AL$21 -> 11.994485 | CS83: =H83*月別販売比率!$AQ$21 -> 13.327206 | CU83: =H83*月別販売比率!$AV$21 -> 8.1155188 | CW83: =H83*月別販売比率!$BA$21 -> 7.4130078 | CY83: =H83*月別販売比率!$BF$21 -> 10.661765
E84: +3.00 | F84: 9 | G84: =F84*6600 -> 59400 | H84: =F84*($H$76/$F$76) -> 41.360294 | I84: =H84*6600 -> 272977.94 | J84: 0 | K84: =SUM(L84:N84) -> 20 | L84: 10 | M84: 2 | N84: 8 | O84: 45587 | S84: 45716 | Y84: 45879 | AC84: 46011 | AH84: 46172 | AI84: =SUM(J84:K84)-CI84+CJ84 -> 16.691176 | AJ84: =AI84-CK84+CL84 -> 28.540899 | AK84: =AJ84-CM84+CN84 -> 23.577663 | AL84: =AK84-CO84+CP84 -> 19.441634 | AM84: =AL84-CQ84+CR84 -> 15.719207 | AN84: =AM84-CS84+CT84 -> 11.583178 | AO84: =AN84-CU84+CV84 -> 9.0645686 | AP84: =AO84-CW84+CX84 -> 6.76398 | AQ84: =AP84-CY84+CZ84 -> 3.4551565 | AS84: =$H$84*月別販売比率!AG5 -> 4.1360294 | AU84: =$H$84*月別販売比率!AL5 -> 3.7224265 | AW84: =$H$84*月別販売比率!AQ5 -> 4.1360294 | AY84: =$H$84*月別販売比率!AV5 -> 2.5186093 | BA84: =$H$84*月別販売比率!BA5 -> 2.3005886 | BB84: 10 | BC84: =$H$84*月別販売比率!BF5 -> 3.3088235 | BE84: =$H$84*月別販売比率!C21 -> 2.9309663 | BG84: =$H$84*月別販売比率!H21 -> 2.8952206 | BH84: 5 | BI84: =$H$84*月別販売比率!M21 -> 4.1800239 | BK84: =$H$84*月別販売比率!R21 -> 3.3088235 | BM84: =$H$84*月別販売比率!W21 -> 3.150278 | BN84: 5 | BO84: =$H$84*月別販売比率!AB21 -> 4.9632353 | BQ84: =$H$84*月別販売比率!AG21 -> 4.1360294 | BS84: =$H$84*月別販売比率!AL21 -> 3.7224265 | BU84: =$H$84*月別販売比率!AQ21 -> 4.1360294 | BV84: 10 | BW84: =$H$84*月別販売比率!AV21 -> 2.5186093 | BY84: =$H$84*月別販売比率!BA21 -> 2.3005886 | BZ84: 5 | CA84: =$H$84*月別販売比率!BF21 -> 3.3088235 | CC84: =H84*月別販売比率!$C$21 -> 2.9309663 | CE84: =H84*月別販売比率!$H$21 -> 2.8952206 | CF84: 10 | CG84: =H84*月別販売比率!$M$21 -> 4.1800239 | CH84: 15 | CI84: =H84*月別販売比率!$R$21 -> 3.3088235 | CK84: =H84*月別販売比率!$W$21 -> 3.150278 | CL84: 15 | CM84: =H84*月別販売比率!$AB$21 -> 4.9632353 | CO84: =H84*月別販売比率!$AG$21 -> 4.1360294 | CQ84: =H84*月別販売比率!$AL$21 -> 3.7224265 | CS84: =H84*月別販売比率!$AQ$21 -> 4.1360294 | CU84: =H84*月別販売比率!$AV$21 -> 2.5186093 | CW84: =H84*月別販売比率!$BA$21 -> 2.3005886 | CY84: =H84*月別販売比率!$BF$21 -> 3.3088235
D85: 3 | E85: +1.50 | F85: 22 | G85: =F85*6600 -> 145200 | H85: =F85*($H$76/$F$76) -> 101.10294 | I85: =H85*6600 -> 667279.41 | J85: 0 | K85: =SUM(L85:N85) -> 36 | L85: 9 | M85: 5 | N85: 22 | S85: 45716 | V85: 45786 | Y85: 45879 | AC85: 46011 | AH85: 46172 | AI85: =SUM(J85:K85)-CI85+CJ85 -> 27.911765 | AJ85: =AI85-CK85+CL85 -> 40.211085 | AK85: =AJ85-CM85+CN85 -> 28.078732 | AL85: =AK85-CO85+CP85 -> 32.968438 | AM85: =AL85-CQ85+CR85 -> 23.869173 | AN85: =AM85-CS85+CT85 -> 13.758879 | AO85: =AN85-CU85+CV85 -> 7.6022789 | AP85: =AO85-CW85+CX85 -> 1.9786178 | AQ85: =AP85-CY85+CZ85 -> -6.1096175 | AS85: =$H$85*月別販売比率!AG5 -> 10.110294 | AU85: =$H$85*月別販売比率!AL5 -> 9.0992647 | AW85: =$H$85*月別販売比率!AQ5 -> 10.110294 | AY85: =$H$85*月別販売比率!AV5 -> 6.1566005 | BA85: =$H$85*月別販売比率!BA5 -> 5.6236611 | BB85: 20 | BC85: =$H$85*月別販売比率!BF5 -> 8.0882353 | BE85: =$H$85*月別販売比率!C21 -> 7.1645842 | BG85: =$H$85*月別販売比率!H21 -> 7.0772059 | BH85: 15 | BI85: =$H$85*月別販売比率!M21 -> 10.217836 | BK85: =$H$85*月別販売比率!R21 -> 8.0882353 | BM85: =$H$85*月別販売比率!W21 -> 7.7006794 | BN85: 23 | BO85: =$H$85*月別販売比率!AB21 -> 12.132353 | BQ85: =$H$85*月別販売比率!AG21 -> 10.110294 | BS85: =$H$85*月別販売比率!AL21 -> 9.0992647 | BU85: =$H$85*月別販売比率!AQ21 -> 10.110294 | BV85: 10 | BW85: =$H$85*月別販売比率!AV21 -> 6.1566005 | BY85: =$H$85*月別販売比率!BA21 -> 5.6236611 | BZ85: 30 | CA85: =$H$85*月別販売比率!BF21 -> 8.0882353 | CC85: =H85*月別販売比率!$C$21 -> 7.1645842 | CE85: =H85*月別販売比率!$H$21 -> 7.0772059 | CF85: 30 | CG85: =H85*月別販売比率!$M$21 -> 10.217836 | CH85: 25 | CI85: =H85*月別販売比率!$R$21 -> 8.0882353 | CK85: =H85*月別販売比率!$W$21 -> 7.7006794 | CL85: 20 | CM85: =H85*月別販売比率!$AB$21 -> 12.132353 | CO85: =H85*月別販売比率!$AG$21 -> 10.110294 | CP85: 15 | CQ85: =H85*月別販売比率!$AL$21 -> 9.0992647 | CS85: =H85*月別販売比率!$AQ$21 -> 10.110294 | CU85: =H85*月別販売比率!$AV$21 -> 6.1566005 | CW85: =H85*月別販売比率!$BA$21 -> 5.6236611 | CY85: =H85*月別販売比率!$BF$21 -> 8.0882353
E86: +2.00 | F86: 25 | G86: =F86*6600 -> 165000 | H86: =F86*($H$76/$F$76) -> 114.88971 | I86: =H86*6600 -> 758272.06 | J86: 61 | K86: =SUM(L86:N86) -> 22 | L86: 10 | M86: 11 | N86: 1 | S86: 45716 | V86: 45786 | Y86: 45879 | AC86: 46011 | AH86: 46172 | AI86: =SUM(J86:K86)-CI86+CJ86 -> 73.808824 | AJ86: =AI86-CK86+CL86 -> 85.058051 | AK86: =AJ86-CM86+CN86 -> 71.271287 | AL86: =AK86-CO86+CP86 -> 79.782316 | AM86: =AL86-CQ86+CR86 -> 69.442243 | AN86: =AM86-CS86+CT86 -> 57.953272 | AO86: =AN86-CU86+CV86 -> 50.957135 | AP86: =AO86-CW86+CX86 -> 44.566611 | AQ86: =AP86-CY86+CZ86 -> 35.375435 | AS86: =$H$86*月別販売比率!AG5 -> 11.488971 | AU86: =$H$86*月別販売比率!AL5 -> 10.340074 | AW86: =$H$86*月別販売比率!AQ5 -> 11.488971 | AY86: =$H$86*月別販売比率!AV5 -> 6.9961369 | BA86: =$H$86*月別販売比率!BA5 -> 6.390524 | BB86: 17 | BC86: =$H$86*月別販売比率!BF5 -> 9.1911765 | BE86: =$H$86*月別販売比率!C21 -> 8.141573 | BG86: =$H$86*月別販売比率!H21 -> 8.0422794 | BH86: 25 | BI86: =$H$86*月別販売比率!M21 -> 11.611178 | BK86: =$H$86*月別販売比率!R21 -> 9.1911765 | BM86: =$H$86*月別販売比率!W21 -> 8.7507721 | BN86: 20 | BO86: =$H$86*月別販売比率!AB21 -> 13.786765 | BQ86: =$H$86*月別販売比率!AG21 -> 11.488971 | BS86: =$H$86*月別販売比率!AL21 -> 10.340074 | BU86: =$H$86*月別販売比率!AQ21 -> 11.488971 | BV86: 19 | BW86: =$H$86*月別販売比率!AV21 -> 6.9961369 | BY86: =$H$86*月別販売比率!BA21 -> 6.390524 | BZ86: 25 | CA86: =$H$86*月別販売比率!BF21 -> 9.1911765 | CC86: =H86*月別販売比率!$C$21 -> 8.141573 | CE86: =H86*月別販売比率!$H$21 -> 8.0422794 | CF86: 40 | CG86: =H86*月別販売比率!$M$21 -> 11.611178 | CH86: 25 | CI86: =H86*月別販売比率!$R$21 -> 9.1911765 | CK86: =H86*月別販売比率!$W$21 -> 8.7507721 | CL86: 20 | CM86: =H86*月別販売比率!$AB$21 -> 13.786765 | CO86: =H86*月別販売比率!$AG$21 -> 11.488971 | CP86: 20 | CQ86: =H86*月別販売比率!$AL$21 -> 10.340074 | CS86: =H86*月別販売比率!$AQ$21 -> 11.488971 | CU86: =H86*月別販売比率!$AV$21 -> 6.9961369 | CW86: =H86*月別販売比率!$BA$21 -> 6.390524 | CY86: =H86*月別販売比率!$BF$21 -> 9.1911765
E87: +2.50 | F87: 12 | G87: =F87*6600 -> 79200 | H87: =F87*($H$76/$F$76) -> 55.147059 | I87: =H87*6600 -> 363970.59 | J87: 7 | K87: =SUM(L87:N87) -> 38 | L87: 10 | M87: 10 | N87: 18 | S87: 45716 | V87: 45786 | Y87: 45879 | AC87: 46011 | AI87: =SUM(J87:K87)-CI87+CJ87 -> 40.588235 | AJ87: =AI87-CK87+CL87 -> 56.387865 | AK87: =AJ87-CM87+CN87 -> 49.770218 | AL87: =AK87-CO87+CP87 -> 59.255512 | AM87: =AL87-CQ87+CR87 -> 54.292276 | AN87: =AM87-CS87+CT87 -> 48.777571 | AO87: =AN87-CU87+CV87 -> 45.419425 | AP87: =AO87-CW87+CX87 -> 42.351973 | AQ87: =AP87-CY87+CZ87 -> 37.940209 | AS87: =$H$87*月別販売比率!AG5 -> 5.5147059 | AU87: =$H$87*月別販売比率!AL5 -> 4.9632353 | AW87: =$H$87*月別販売比率!AQ5 -> 5.5147059 | AY87: =$H$87*月別販売比率!AV5 -> 3.3581457 | BA87: =$H$87*月別販売比率!BA5 -> 3.0674515 | BB87: 4 | BC87: =$H$87*月別販売比率!BF5 -> 4.4117647 | BE87: =$H$87*月別販売比率!C21 -> 3.907955 | BG87: =$H$87*月別販売比率!H21 -> 3.8602941 | BH87: 10 | BI87: =$H$87*月別販売比率!M21 -> 5.5733652 | BK87: =$H$87*月別販売比率!R21 -> 4.4117647 | BM87: =$H$87*月別販売比率!W21 -> 4.2003706 | BN87: 13 | BO87: =$H$87*月別販売比率!AB21 -> 6.6176471 | BQ87: =$H$87*月別販売比率!AG21 -> 5.5147059 | BS87: =$H$87*月別販売比率!AL21 -> 4.9632353 | BU87: =$H$87*月別販売比率!AQ21 -> 5.5147059 | BV87: 15 | BW87: =$H$87*月別販売比率!AV21 -> 3.3581457 | BY87: =$H$87*月別販売比率!BA21 -> 3.0674515 | BZ87: 25 | CA87: =$H$87*月別販売比率!BF21 -> 4.4117647 | CC87: =H87*月別販売比率!$C$21 -> 3.907955 | CE87: =H87*月別販売比率!$H$21 -> 3.8602941 | CF87: 25 | CG87: =H87*月別販売比率!$M$21 -> 5.5733652 | CH87: 20 | CI87: =H87*月別販売比率!$R$21 -> 4.4117647 | CK87: =H87*月別販売比率!$W$21 -> 4.2003706 | CL87: 20 | CM87: =H87*月別販売比率!$AB$21 -> 6.6176471 | CO87: =H87*月別販売比率!$AG$21 -> 5.5147059 | CP87: 15 | CQ87: =H87*月別販売比率!$AL$21 -> 4.9632353 | CS87: =H87*月別販売比率!$AQ$21 -> 5.5147059 | CU87: =H87*月別販売比率!$AV$21 -> 3.3581457 | CW87: =H87*月別販売比率!$BA$21 -> 3.0674515 | CY87: =H87*月別販売比率!$BF$21 -> 4.4117647
E88: +3.00 | F88: 18 | G88: =F88*6600 -> 118800 | H88: =F88*($H$76/$F$76) -> 82.720588 | I88: =H88*6600 -> 545955.88 | J88: 20 | K88: =SUM(L88:N88) -> 37 | L88: 10 | M88: 9 | N88: 18 | O88: 45594 | V88: 45786 | Y88: 45879 | AC88: 46011 | AH88: 46172 | AI88: =SUM(J88:K88)-CI88+CJ88 -> 50.382353 | AJ88: =AI88-CK88+CL88 -> 59.081797 | AK88: =AJ88-CM88+CN88 -> 49.155326 | AL88: =AK88-CO88+CP88 -> 50.883268 | AM88: =AL88-CQ88+CR88 -> 43.438415 | AN88: =AM88-CS88+CT88 -> 35.166356 | AO88: =AN88-CU88+CV88 -> 30.129137 | AP88: =AO88-CW88+CX88 -> 25.52796 | AQ88: =AP88-CY88+CZ88 -> 18.910313 | AS88: =$H$88*月別販売比率!AG5 -> 8.2720588 | AU88: =$H$88*月別販売比率!AL5 -> 7.4448529 | AW88: =$H$88*月別販売比率!AQ5 -> 8.2720588 | AY88: =$H$88*月別販売比率!AV5 -> 5.0372186 | BA88: =$H$88*月別販売比率!BA5 -> 4.6011773 | BC88: =$H$88*月別販売比率!BF5 -> 6.6176471 | BE88: =$H$88*月別販売比率!C21 -> 5.8619325 | BG88: =$H$88*月別販売比率!H21 -> 5.7904412 | BH88: 10 | BI88: =$H$88*月別販売比率!M21 -> 8.3600478 | BK88: =$H$88*月別販売比率!R21 -> 6.6176471 | BM88: =$H$88*月別販売比率!W21 -> 6.3005559 | BN88: 5 | BO88: =$H$88*月別販売比率!AB21 -> 9.9264706 | BQ88: =$H$88*月別販売比率!AG21 -> 8.2720588 | BS88: =$H$88*月別販売比率!AL21 -> 7.4448529 | BU88: =$H$88*月別販売比率!AQ21 -> 8.2720588 | BV88: 35 | BW88: =$H$88*月別販売比率!AV21 -> 5.0372186 | BY88: =$H$88*月別販売比率!BA21 -> 4.6011773 | BZ88: 5 | CA88: =$H$88*月別販売比率!BF21 -> 6.6176471 | CC88: =H88*月別販売比率!$C$21 -> 5.8619325 | CE88: =H88*月別販売比率!$H$21 -> 5.7904412 | CF88: 35 | CG88: =H88*月別販売比率!$M$21 -> 8.3600478 | CH88: 20 | CI88: =H88*月別販売比率!$R$21 -> 6.6176471 | CK88: =H88*月別販売比率!$W$21 -> 6.3005559 | CL88: 15 | CM88: =H88*月別販売比率!$AB$21 -> 9.9264706 | CO88: =H88*月別販売比率!$AG$21 -> 8.2720588 | CP88: 10 | CQ88: =H88*月別販売比率!$AL$21 -> 7.4448529 | CS88: =H88*月別販売比率!$AQ$21 -> 8.2720588 | CU88: =H88*月別販売比率!$AV$21 -> 5.0372186 | CW88: =H88*月別販売比率!$BA$21 -> 4.6011773 | CY88: =H88*月別販売比率!$BF$21 -> 6.6176471
B89: 7 | C89: si-13PH（EC専売） | F89: =SUM(F90:F98) -> 293 | G89: =SUM(G90:G98) -> 2256100 | H89: 850 | I89: =SUM(I90:I98) -> 6968105.8 | J89: =SUM(J90:J98) -> 211 | K89: =SUM(K90:K98) -> 184 | L89: =SUM(L90:L98) -> 97 | M89: =SUM(M90:M98) -> 106 | N89: =SUM(N90:N98) -> 0 | AS89: =SUM(AS90:AS98) -> 72.395904 | AT89: =SUM(AT90:AT98) -> 0 | AU89: =SUM(AU90:AU98) -> 45.607017 | AV89: =SUM(AV90:AV98) -> 0 | AW89: =SUM(AW90:AW98) -> 50.816471 | AX89: =SUM(AX90:AX98) -> 0 | AY89: =SUM(AY90:AY98) -> 36.197952 | AZ89: =SUM(AZ90:AZ98) -> 0 | ... CT89: =SUM(CT90:CT98) -> 0 | CU89: 36.197952 | CV89: =SUM(CV90:CV98) -> 0 | CW89: =SUM(CW90:CW98) -> 27.148464 | CX89: =SUM(CX90:CX98) -> 0 | CY89: =SUM(CY90:CY98) -> 45.159524 | CZ89: =SUM(CZ90:CZ98) -> 0
C90: SI-13と合わせて 発注検討 入荷：8月 300枚 | D90: 1 | E90: +1.00 | F90: 23 | G90: =F90*7700 -> 177100 | H90: =F90*($H$89/$F$89) -> 66.723549 | I90: =H90*7700 -> 513771.33 | J90: 10 | K90: =SUM(L90:N90) -> 23 | L90: 10 | M90: 13 | Y90: 45879 | AH90: 46172 | AI90: =SUM(J90:K90)-CI90+CJ90 -> 20.989761 | AJ90: =AI90-CK90+CL90 -> 34.317406 | AK90: =AJ90-CM90+CN90 -> 26.31058 | AL90: =AK90-CO90+CP90 -> 20.972696 | AM90: =AL90-CQ90+CR90 -> 17.610007 | AN90: =AM90-CS90+CT90 -> 13.863214 | AO90: =AN90-CU90+CV90 -> 11.194272 | AP90: =AO90-CW90+CX90 -> 9.1925657 | AQ90: =AP90-CY90+CZ90 -> 5.8628704 | AS90: =$H$90*月別販売比率!AG25 -> 5.337884 | AU90: =$H$90*月別販売比率!AL25 -> 3.3626897 | AW90: =$H$90*月別販売比率!AQ25 -> 3.7467924 | AY90: =$H$90*月別販売比率!AV25 -> 2.668942 | BA90: =$H$90*月別販売比率!BA25 -> 2.0017065 | BC90: =$H$90*月別販売比率!BF25 -> 3.3296952 | BE90: =$H$90*月別販売比率!C25 -> 4.6706485 | BG90: =$H$90*月別販売比率!H25 -> 5.337884 | BH90: 12 | BI90: =$H$90*月別販売比率!M25 -> 9.3412969 | BK90: =$H$90*月別販売比率!R25 -> 12.010239 | BM90: =$H$90*月別販売比率!W25 -> 6.6723549 | BN90: 30 | BO90: =$H$90*月別販売比率!AB25 -> 8.0068259 | BQ90: =$H$90*月別販売比率!AG25 -> 5.337884 | BS90: =$H$90*月別販売比率!AL25 -> 3.3626897 | BU90: =$H$90*月別販売比率!AQ25 -> 3.7467924 | BW90: =$H$90*月別販売比率!AV25 -> 2.668942 | BY90: =$H$90*月別販売比率!BA25 -> 2.0017065 | CA90: =$H$90*月別販売比率!BF25 -> 3.3296952 | CC90: =H90*月別販売比率!$C$25 -> 4.6706485 | CD90: 15 | CE90: =H90*月別販売比率!$H$25 -> 5.337884 | CG90: =H90*月別販売比率!$M$25 -> 9.3412969 | CH90: 29 | CI90: =H90*月別販売比率!$R$25 -> 12.010239 | CK90: =H90*月別販売比率!$W$25 -> 6.6723549 | CL90: 20 | CM90: =H90*月別販売比率!$AB$25 -> 8.0068259 | CO90: =H90*月別販売比率!$AG$25 -> 5.337884 | CQ90: =H90*月別販売比率!$AL$25 -> 3.3626897 | CS90: =H90*月別販売比率!$AQ$25 -> 3.7467924 | CU90: =H90*月別販売比率!$AV$25 -> 2.668942 | CW90: =H90*月別販売比率!$BA$25 -> 2.0017065 | CY90: =H90*月別販売比率!$BF$25 -> 3.3296952
E91: +1.50 | F91: 50 | G91: =F91*7700 -> 385000 | H91: 200 | I91: =H91*7700 -> 1540000 | J91: 61 | K91: =SUM(L91:N91) -> 23 | L91: 10 | M91: 13 | AH91: 46172 | AI91: =SUM(J91:K91)-CI91+CJ91 -> 48 | AJ91: =AI91-CK91+CL91 -> 113 | AK91: =AJ91-CM91+CN91 -> 89 | AL91: =AK91-CO91+CP91 -> 73 | AM91: =AL91-CQ91+CR91 -> 62.920531 | AN91: =AM91-CS91+CT91 -> 51.689736 | AO91: =AN91-CU91+CV91 -> 43.689736 | AP91: =AO91-CW91+CX91 -> 37.689736 | AQ91: =AP91-CY91+CZ91 -> 27.709167 | AS91: =$H$91*月別販売比率!AG25 -> 16 | AU91: =$H$91*月別販売比率!AL25 -> 10.079469 | AW91: =$H$91*月別販売比率!AQ25 -> 11.230795 | AY91: =$H$91*月別販売比率!AV25 -> 8 | BA91: =$H$91*月別販売比率!BA25 -> 6 | BC91: =$H$91*月別販売比率!BF25 -> 9.9805698 | BE91: =$H$91*月別販売比率!C25 -> 14 | BG91: =$H$91*月別販売比率!H25 -> 16 | BH91: 37 | BI91: =$H$91*月別販売比率!M25 -> 28 | BK91: =$H$91*月別販売比率!R25 -> 36 | BM91: =$H$91*月別販売比率!W25 -> 20 | BN91: 30 | BO91: =$H$91*月別販売比率!AB25 -> 24 | BQ91: =$H$91*月別販売比率!AG25 -> 16 | BS91: =$H$91*月別販売比率!AL25 -> 10.079469 | BU91: =$H$91*月別販売比率!AQ25 -> 11.230795 | BW91: =$H$91*月別販売比率!AV25 -> 8 | BY91: =$H$91*月別販売比率!BA25 -> 6 | CA91: =$H$91*月別販売比率!BF25 -> 9.9805698 | CC91: =H91*月別販売比率!$C$25 -> 14 | CD91: 15 | CE91: =H91*月別販売比率!$H$25 -> 16 | CG91: =H91*月別販売比率!$M$25 -> 28 | CH91: 88 | CI91: =H91*月別販売比率!$R$25 -> 36 | CK91: =H91*月別販売比率!$W$25 -> 20 | CL91: 85 | CM91: =H91*月別販売比率!$AB$25 -> 24 | CO91: =H91*月別販売比率!$AG$25 -> 16 | CQ91: =H91*月別販売比率!$AL$25 -> 10.079469 | CS91: =H91*月別販売比率!$AQ$25 -> 11.230795 | CU91: =H91*月別販売比率!$AV$25 -> 8 | CW91: =H91*月別販売比率!$BA$25 -> 6 | CY91: =H91*月別販売比率!$BF$25 -> 9.9805698
E92: +2.00 | F92: 38 | G92: =F92*7700 -> 292600 | H92: =F92*($H$89/$F$89) -> 110.23891 | I92: =H92*7700 -> 848839.59 | J92: 25 | K92: =SUM(L92:N92) -> 20 | L92: 7 | M92: 13 | AI92: =SUM(J92:K92)-CI92+CJ92 -> 25.156997 | AJ92: =AI92-CK92+CL92 -> 54.133106 | AK92: =AJ92-CM92+CN92 -> 40.904437 | AL92: =AK92-CO92+CP92 -> 32.085324 | AM92: =AL92-CQ92+CR92 -> 26.529576 | AN92: =AM92-CS92+CT92 -> 20.339223 | AO92: =AN92-CU92+CV92 -> 15.929667 | AP92: =AO92-CW92+CX92 -> 12.6225 | AQ92: =AP92-CY92+CZ92 -> 7.1212642 | AS92: =$H$92*月別販売比率!AG25 -> 8.8191126 | AU92: =$H$92*月別販売比率!AL25 -> 5.5557482 | AW92: =$H$92*月別販売比率!AQ25 -> 6.1903526 | AY92: =$H$92*月別販売比率!AV25 -> 4.4095563 | BA92: =$H$92*月別販売比率!BA25 -> 3.3071672 | BC92: =$H$92*月別販売比率!BF25 -> 5.5012356 | BE92: =$H$92*月別販売比率!C25 -> 7.7167235 | BG92: =$H$92*月別販売比率!H25 -> 8.8191126 | BH92: 26 | BI92: =$H$92*月別販売比率!M25 -> 15.433447 | BK92: =$H$92*月別販売比率!R25 -> 19.843003 | BM92: =$H$92*月別販売比率!W25 -> 11.023891 | BN92: 30 | BO92: =$H$92*月別販売比率!AB25 -> 13.228669 | BQ92: =$H$92*月別販売比率!AG25 -> 8.8191126 | BS92: =$H$92*月別販売比率!AL25 -> 5.5557482 | BU92: =$H$92*月別販売比率!AQ25 -> 6.1903526 | BW92: =$H$92*月別販売比率!AV25 -> 4.4095563 | BY92: =$H$92*月別販売比率!BA25 -> 3.3071672 | CA92: =$H$92*月別販売比率!BF25 -> 5.5012356 | CC92: =H92*月別販売比率!$C$25 -> 7.7167235 | CD92: 15 | CE92: =H92*月別販売比率!$H$25 -> 8.8191126 | CG92: =H92*月別販売比率!$M$25 -> 15.433447 | CH92: 50 | CI92: =H92*月別販売比率!$R$25 -> 19.843003 | CK92: =H92*月別販売比率!$W$25 -> 11.023891 | CL92: 40 | CM92: =H92*月別販売比率!$AB$25 -> 13.228669 | CO92: =H92*月別販売比率!$AG$25 -> 8.8191126 | CQ92: =H92*月別販売比率!$AL$25 -> 5.5557482 | CS92: =H92*月別販売比率!$AQ$25 -> 6.1903526 | CU92: =H92*月別販売比率!$AV$25 -> 4.4095563 | CW92: =H92*月別販売比率!$BA$25 -> 3.3071672 | CY92: =H92*月別販売比率!$BF$25 -> 5.5012356
D93: 2 | E93: +1.00 | F93: 21 | G93: =F93*7700 -> 161700 | H93: =F93*($H$89/$F$89) -> 60.921502 | I93: =H93*7700 -> 469095.56 | J93: 11 | K93: =SUM(L93:N93) -> 25 | L93: 11 | M93: 14 | Y93: 45879 | AH93: 46172 | AI93: =SUM(J93:K93)-CI93+CJ93 -> 25.03413 | AJ93: =AI93-CK93+CL93 -> 28.94198 | AK93: =AJ93-CM93+CN93 -> 21.631399 | AL93: =AK93-CO93+CP93 -> 16.757679 | AM93: =AL93-CQ93+CR93 -> 13.687397 | AN93: =AM93-CS93+CT93 -> 10.266413 | AO93: =AN93-CU93+CV93 -> 7.8295528 | AP93: =AO93-CW93+CX93 -> 6.0019078 | AQ93: =AP93-CY93+CZ93 -> 2.9617513 | AS93: =$H$93*月別販売比率!AG25 -> 4.8737201 | AU93: =$H$93*月別販売比率!AL25 -> 3.0702819 | AW93: =$H$93*月別販売比率!AQ25 -> 3.4209844 | AY93: =$H$93*月別販売比率!AV25 -> 2.4368601 | BA93: =$H$93*月別販売比率!BA25 -> 1.8276451 | BC93: =$H$93*月別販売比率!BF25 -> 3.0401565 | BE93: =$H$93*月別販売比率!C25 -> 4.2645051 | BG93: =$H$93*月別販売比率!H25 -> 4.8737201 | BH93: 10 | BI93: =$H$93*月別販売比率!M25 -> 8.5290102 | BK93: =$H$93*月別販売比率!R25 -> 10.96587 | BM93: =$H$93*月別販売比率!W25 -> 6.0921502 | BN93: 15 | BO93: =$H$93*月別販売比率!AB25 -> 7.3105802 | BQ93: =$H$93*月別販売比率!AG25 -> 4.8737201 | BS93: =$H$93*月別販売比率!AL25 -> 3.0702819 | BU93: =$H$93*月別販売比率!AQ25 -> 3.4209844 | BW93: =$H$93*月別販売比率!AV25 -> 2.4368601 | BY93: =$H$93*月別販売比率!BA25 -> 1.8276451 | CA93: =$H$93*月別販売比率!BF25 -> 3.0401565 | CC93: =H93*月別販売比率!$C$25 -> 4.2645051 | CD93: 20 | CE93: =H93*月別販売比率!$H$25 -> 4.8737201 | CG93: =H93*月別販売比率!$M$25 -> 8.5290102 | CH93: 26 | CI93: =H93*月別販売比率!$R$25 -> 10.96587 | CK93: =H93*月別販売比率!$W$25 -> 6.0921502 | CL93: 10 | CM93: =H93*月別販売比率!$AB$25 -> 7.3105802 | CO93: =H93*月別販売比率!$AG$25 -> 4.8737201 | CQ93: =H93*月別販売比率!$AL$25 -> 3.0702819 | CS93: =H93*月別販売比率!$AQ$25 -> 3.4209844 | CU93: =H93*月別販売比率!$AV$25 -> 2.4368601 | CW93: =H93*月別販売比率!$BA$25 -> 1.8276451 | CY93: =H93*月別販売比率!$BF$25 -> 3.0401565
E94: +1.50 | F94: 47 | G94: =F94*7700 -> 361900 | H94: =F94*($H$89/$F$89) -> 136.34812 | I94: =H94*7700 -> 1049880.5 | J94: 43 | K94: =SUM(L94:N94) -> 23 | L94: 10 | M94: 13 | Y94: 45879 | AI94: =SUM(J94:K94)-CI94+CJ94 -> 41.457338 | AJ94: =AI94-CK94+CL94 -> 82.822526 | AK94: =AJ94-CM94+CN94 -> 66.460751 | AL94: =AK94-CO94+CP94 -> 55.552901 | AM94: =AL94-CQ94+CR94 -> 48.681318 | AN94: =AM94-CS94+CT94 -> 41.024829 | AO94: =AN94-CU94+CV94 -> 35.570904 | AP94: =AO94-CW94+CX94 -> 31.48046 | AQ94: =AP94-CY94+CZ94 -> 24.6763 | AS94: =$H$94*月別販売比率!AG25 -> 10.90785 | AU94: =$H$94*月別販売比率!AL25 -> 6.8715833 | AW94: =$H$94*月別販売比率!AQ25 -> 7.6564888 | AY94: =$H$94*月別販売比率!AV25 -> 5.4539249 | BA94: =$H$94*月別販売比率!BA25 -> 4.0904437 | BC94: =$H$94*月別販売比率!BF25 -> 6.8041598 | BE94: =$H$94*月別販売比率!C25 -> 9.5443686 | BG94: =$H$94*月別販売比率!H25 -> 10.90785 | BH94: 40 | BI94: =$H$94*月別販売比率!M25 -> 19.088737 | BK94: =$H$94*月別販売比率!R25 -> 24.542662 | BM94: =$H$94*月別販売比率!W25 -> 13.634812 | BN94: 30 | BO94: =$H$94*月別販売比率!AB25 -> 16.361775 | BQ94: =$H$94*月別販売比率!AG25 -> 10.90785 | BS94: =$H$94*月別販売比率!AL25 -> 6.8715833 | BU94: =$H$94*月別販売比率!AQ25 -> 7.6564888 | BW94: =$H$94*月別販売比率!AV25 -> 5.4539249 | BY94: =$H$94*月別販売比率!BA25 -> 4.0904437 | CA94: =$H$94*月別販売比率!BF25 -> 6.8041598 | CC94: =H94*月別販売比率!$C$25 -> 9.5443686 | CD94: 15 | CE94: =H94*月別販売比率!$H$25 -> 10.90785 | CG94: =H94*月別販売比率!$M$25 -> 19.088737 | CH94: 65 | CI94: =H94*月別販売比率!$R$25 -> 24.542662 | CK94: =H94*月別販売比率!$W$25 -> 13.634812 | CL94: 55 | CM94: =H94*月別販売比率!$AB$25 -> 16.361775 | CO94: =H94*月別販売比率!$AG$25 -> 10.90785 | CQ94: =H94*月別販売比率!$AL$25 -> 6.8715833 | CS94: =H94*月別販売比率!$AQ$25 -> 7.6564888 | CU94: =H94*月別販売比率!$AV$25 -> 5.4539249 | CW94: =H94*月別販売比率!$BA$25 -> 4.0904437 | CY94: =H94*月別販売比率!$BF$25 -> 6.8041598
E95: +2.00 | F95: 35 | G95: =F95*7700 -> 269500 | H95: =F95*($H$89/$F$89) -> 101.53584 | I95: =H95*7700 -> 781825.94 | J95: 16 | K95: =SUM(L95:N95) -> 24 | L95: 10 | M95: 14 | Y95: 45879 | AH95: 46172 | AI95: =SUM(J95:K95)-CI95+CJ95 -> 21.723549 | AJ95: =AI95-CK95+CL95 -> 51.569966 | AK95: =AJ95-CM95+CN95 -> 39.385666 | AL95: =AK95-CO95+CP95 -> 31.262799 | AM95: =AL95-CQ95+CR95 -> 26.145662 | AN95: =AM95-CS95+CT95 -> 20.444022 | AO95: =AN95-CU95+CV95 -> 16.382588 | AP95: =AO95-CW95+CX95 -> 13.336513 | AQ95: =AP95-CY95+CZ95 -> 8.2695855 | AS95: =$H$95*月別販売比率!AG25 -> 8.1228669 | AU95: =$H$95*月別販売比率!AL25 -> 5.1171365 | AW95: =$H$95*月別販売比率!AQ25 -> 5.7016406 | AY95: =$H$95*月別販売比率!AV25 -> 4.0614334 | BA95: =$H$95*月別販売比率!BA25 -> 3.0460751 | BC95: =$H$95*月別販売比率!BF25 -> 5.0669275 | BE95: =$H$95*月別販売比率!C25 -> 7.1075085 | BG95: =$H$95*月別販売比率!H25 -> 8.1228669 | BH95: 25 | BI95: =$H$95*月別販売比率!M25 -> 14.215017 | BK95: =$H$95*月別販売比率!R25 -> 18.276451 | BM95: =$H$95*月別販売比率!W25 -> 10.153584 | BN95: 25 | BO95: =$H$95*月別販売比率!AB25 -> 12.1843 | BQ95: =$H$95*月別販売比率!AG25 -> 8.1228669 | BS95: =$H$95*月別販売比率!AL25 -> 5.1171365 | BU95: =$H$95*月別販売比率!AQ25 -> 5.7016406 | BW95: =$H$95*月別販売比率!AV25 -> 4.0614334 | BY95: =$H$95*月別販売比率!BA25 -> 3.0460751 | CA95: =$H$95*月別販売比率!BF25 -> 5.0669275 | CC95: =H95*月別販売比率!$C$25 -> 7.1075085 | CD95: 15 | CE95: =H95*月別販売比率!$H$25 -> 8.1228669 | CG95: =H95*月別販売比率!$M$25 -> 14.215017 | CH95: 41 | CI95: =H95*月別販売比率!$R$25 -> 18.276451 | CK95: =H95*月別販売比率!$W$25 -> 10.153584 | CL95: 40 | CM95: =H95*月別販売比率!$AB$25 -> 12.1843 | CO95: =H95*月別販売比率!$AG$25 -> 8.1228669 | CQ95: =H95*月別販売比率!$AL$25 -> 5.1171365 | CS95: =H95*月別販売比率!$AQ$25 -> 5.7016406 | CU95: =H95*月別販売比率!$AV$25 -> 4.0614334 | CW95: =H95*月別販売比率!$BA$25 -> 3.0460751 | CY95: =H95*月別販売比率!$BF$25 -> 5.0669275
D96: 3 | E96: +1.00 | F96: 18 | G96: =F96*7700 -> 138600 | H96: =F96*($H$89/$F$89) -> 52.21843 | I96: =H96*7700 -> 402081.91 | J96: 0 | K96: =SUM(L96:N96) -> 19 | L96: 16 | M96: 3 | Y96: 45879 | AH96: 46172 | AI96: =SUM(J96:K96)-CI96+CJ96 -> 9.6006826 | AJ96: =AI96-CK96+CL96 -> 19.37884 | AK96: =AJ96-CM96+CN96 -> 13.112628 | AL96: =AK96-CO96+CP96 -> 8.9351536 | AM96: =AL96-CQ96+CR96 -> 6.3034834 | AN96: =AM96-CS96+CT96 -> 3.3712111 | AO96: =AN96-CU96+CV96 -> 1.2824739 | AP96: =AO96-CW96+CX96 -> -0.28407904 | AQ96: =AP96-CY96+CZ96 -> -2.8899275 | AS96: =$H$96*月別販売比率!AG25 -> 4.1774744 | AU96: =$H$96*月別販売比率!AL25 -> 2.6316702 | AW96: =$H$96*月別販売比率!AQ25 -> 2.9322723 | AY96: =$H$96*月別販売比率!AV25 -> 2.0887372 | BA96: =$H$96*月別販売比率!BA25 -> 1.5665529 | BC96: =$H$96*月別販売比率!BF25 -> 2.6058484 | BE96: =$H$96*月別販売比率!C25 -> 3.6552901 | BG96: =$H$96*月別販売比率!H25 -> 4.1774744 | BH96: 20 | BI96: =$H$96*月別販売比率!M25 -> 7.3105802 | BK96: =$H$96*月別販売比率!R25 -> 9.3993174 | BM96: =$H$96*月別販売比率!W25 -> 5.221843 | BN96: 10 | BO96: =$H$96*月別販売比率!AB25 -> 6.2662116 | BQ96: =$H$96*月別販売比率!AG25 -> 4.1774744 | BS96: =$H$96*月別販売比率!AL25 -> 2.6316702 | BU96: =$H$96*月別販売比率!AQ25 -> 2.9322723 | BW96: =$H$96*月別販売比率!AV25 -> 2.0887372 | BY96: =$H$96*月別販売比率!BA25 -> 1.5665529 | CA96: =$H$96*月別販売比率!BF25 -> 2.6058484 | CC96: =H96*月別販売比率!$C$25 -> 3.6552901 | CD96: 25 | CE96: =H96*月別販売比率!$H$25 -> 4.1774744 | CG96: =H96*月別販売比率!$M$25 -> 7.3105802 | CH96: 5 | CI96: =H96*月別販売比率!$R$25 -> 9.3993174 | CK96: =H96*月別販売比率!$W$25 -> 5.221843 | CL96: 15 | CM96: =H96*月別販売比率!$AB$25 -> 6.2662116 | CO96: =H96*月別販売比率!$AG$25 -> 4.1774744 | CQ96: =H96*月別販売比率!$AL$25 -> 2.6316702 | CS96: =H96*月別販売比率!$AQ$25 -> 2.9322723 | CU96: =H96*月別販売比率!$AV$25 -> 2.0887372 | CW96: =H96*月別販売比率!$BA$25 -> 1.5665529 | CY96: =H96*月別販売比率!$BF$25 -> 2.6058484
E97: +1.50 | F97: 32 | G97: =F97*7700 -> 246400 | H97: =F97*($H$89/$F$89) -> 92.832765 | I97: =H97*7700 -> 714812.29 | J97: 30 | K97: =SUM(L97:N97) -> 27 | L97: 14 | M97: 13 | Y97: 45879 | AH97: 46172 | AI97: =SUM(J97:K97)-CI97+CJ97 -> 40.290102 | AJ97: =AI97-CK97+CL97 -> 51.006826 | AK97: =AJ97-CM97+CN97 -> 39.866894 | AL97: =AK97-CO97+CP97 -> 32.440273 | AM97: =AL97-CQ97+CR97 -> 27.761748 | AN97: =AM97-CS97+CT97 -> 22.54882 | AO97: =AN97-CU97+CV97 -> 18.835509 | AP97: =AO97-CW97+CX97 -> 16.050526 | AQ97: =AP97-CY97+CZ97 -> 11.417907 | AS97: =$H$97*月別販売比率!AG25 -> 7.4266212 | AU97: =$H$97*月別販売比率!AL25 -> 4.6785248 | AW97: =$H$97*月別販売比率!AQ25 -> 5.2129285 | AY97: =$H$97*月別販売比率!AV25 -> 3.7133106 | BA97: =$H$97*月別販売比率!BA25 -> 2.7849829 | BC97: =$H$97*月別販売比率!BF25 -> 4.6326194 | BE97: =$H$97*月別販売比率!C25 -> 6.4982935 | BG97: =$H$97*月別販売比率!H25 -> 7.4266212 | BH97: 20 | BI97: =$H$97*月別販売比率!M25 -> 12.996587 | BK97: =$H$97*月別販売比率!R25 -> 16.709898 | BM97: =$H$97*月別販売比率!W25 -> 9.2832765 | BN97: 20 | BO97: =$H$97*月別販売比率!AB25 -> 11.139932 | BQ97: =$H$97*月別販売比率!AG25 -> 7.4266212 | BS97: =$H$97*月別販売比率!AL25 -> 4.6785248 | BU97: =$H$97*月別販売比率!AQ25 -> 5.2129285 | BW97: =$H$97*月別販売比率!AV25 -> 3.7133106 | BY97: =$H$97*月別販売比率!BA25 -> 2.7849829 | CA97: =$H$97*月別販売比率!BF25 -> 4.6326194 | CC97: =H97*月別販売比率!$C$25 -> 6.4982935 | CD97: 25 | CE97: =H97*月別販売比率!$H$25 -> 7.4266212 | CG97: =H97*月別販売比率!$M$25 -> 12.996587 | CH97: 44 | CI97: =H97*月別販売比率!$R$25 -> 16.709898 | CK97: =H97*月別販売比率!$W$25 -> 9.2832765 | CL97: 20 | CM97: =H97*月別販売比率!$AB$25 -> 11.139932 | CO97: =H97*月別販売比率!$AG$25 -> 7.4266212 | CQ97: =H97*月別販売比率!$AL$25 -> 4.6785248 | CS97: =H97*月別販売比率!$AQ$25 -> 5.2129285 | CU97: =H97*月別販売比率!$AV$25 -> 3.7133106 | CW97: =H97*月別販売比率!$BA$25 -> 2.7849829 | CY97: =H97*月別販売比率!$BF$25 -> 4.6326194
E98: +2.00 | F98: 29 | G98: =F98*7700 -> 223300 | H98: =F98*($H$89/$F$89) -> 84.129693 | I98: =H98*7700 -> 647798.63 | J98: 15 | K98: 0 | L98: 9 | M98: 10 | AH98: 46172 | AI98: =SUM(J98:K98)-CI98+CJ98 -> -0.14334471 | AJ98: =0-CK98+CL98 -> 6.5870307 | AK98: =AJ98-CM98+CN98 -> -3.5085324 | AL98: =AK98-CO98+CP98 -> -10.238908 | AM98: =AL98-CQ98+CR98 -> -14.478821 | AN98: =AM98-CS98+CT98 -> -19.203037 | AO98: =AN98-CU98+CV98 -> -22.568225 | AP98: =AO98-CW98+CX98 -> -25.092116 | AQ98: =AP98-CY98+CZ98 -> -29.290427 | AS98: =$H$98*月別販売比率!AG25 -> 6.7303754 | AU98: =$H$98*月別販売比率!AL25 -> 4.2399131 | AW98: =$H$98*月別販売比率!AQ25 -> 4.7242165 | AY98: =$H$98*月別販売比率!AV25 -> 3.3651877 | BA98: =$H$98*月別販売比率!BA425 -> 0 | BC98: =$H$98*月別販売比率!BF25 -> 4.1983114 | BE98: =$H$98*月別販売比率!C25 -> 5.8890785 | BG98: =$H$98*月別販売比率!H25 -> 6.7303754 | BH98: 35 | BI98: =$H$98*月別販売比率!M25 -> 11.778157 | BK98: =$H$98*月別販売比率!R25 -> 15.143345 | BM98: =$H$98*月別販売比率!W25 -> 8.4129693 | BN98: 10 | BO98: =$H$98*月別販売比率!AB25 -> 10.095563 | BQ98: =$H$98*月別販売比率!AG25 -> 6.7303754 | BS98: =$H$98*月別販売比率!AL25 -> 4.2399131 | BU98: =$H$98*月別販売比率!AQ25 -> 4.7242165 | BW98: =$H$98*月別販売比率!AV25 -> 3.3651877 | BY98: =$H$98*月別販売比率!BA25 -> 2.5238908 | CA98: =$H$98*月別販売比率!BF25 -> 4.1983114 | CC98: =H98*月別販売比率!$C$25 -> 5.8890785 | CD98: 30 | CE98: =H98*月別販売比率!$H$25 -> 6.7303754 | CG98: =H98*月別販売比率!$M$25 -> 11.778157 | CH98: 34 | CI98: =H98*月別販売比率!$R$25 -> 15.143345 | CK98: =H98*月別販売比率!$W$25 -> 8.4129693 | CL98: 15 | CM98: =H98*月別販売比率!$AB$25 -> 10.095563 | CO98: =H98*月別販売比率!$AG$25 -> 6.7303754 | CQ98: =H98*月別販売比率!$AL$25 -> 4.2399131 | CS98: =H98*月別販売比率!$AQ$25 -> 4.7242165 | CU98: =H98*月別販売比率!$AV$25 -> 3.3651877 | CW98: =H98*月別販売比率!$BA$25 -> 2.5238908 | CY98: =H98*月別販売比率!$BF$25 -> 4.1983114
B99: 8 | C99: si-01sap（EC専売） | F99: =SUM(F100:F111) -> 1200 | G99: =SUM(G100:G111) -> 5280000 | H99: 1200 | I99: =SUM(I100:I111) -> 5280000 | J99: =SUM(J100:J111) -> 442 | K99: =SUM(K100:K111) -> 312 | L99: =SUM(L100:L111) -> 95 | M99: =SUM(M100:M111) -> 217 | N99: =SUM(N100:N111) -> 0 | AS99: =SUM(AS100:AS111) -> 120 | AT99: =SUM(AT100:AT111) -> 0 | AU99: =SUM(AU100:AU111) -> 108 | AV99: =SUM(AV100:AV111) -> 0 | AW99: =SUM(AW100:AW111) -> 120 | AX99: =SUM(AX100:AX111) -> 600 | AY99: =SUM(AY100:AY111) -> 73.073251 | AZ99: =SUM(AZ100:AZ111) -> 0 | ... CH99: =SUM(CH100:CH111) -> 300 | CI99: =H99*月別販売比率!$R$21 -> 96 | CJ99: =SUM(CJ100:CJ111) -> 0 | CK99: =SUM(CK100:CK111) -> 91.400064 | CL99: =SUM(CL100:CL111) -> 0 | CM99: =L99*月別販売比率!$R$21 -> 7.6 | CN99: =SUM(CN100:CN111) -> 0 | CO99: =SUM(CO100:CO111) -> 120 | CP99: =SUM(CP100:CP111) -> 300 | CQ99: =P99*月別販売比率!$R$21 -> 0 | CR99: =SUM(CR100:CR111) -> 0 | CS99: =SUM(CS100:CS111) -> 120 | CT99: =SUM(CT100:CT111) -> 0 | CU99: 73.073251 | CV99: =SUM(CV100:CV111) -> 0 | CW99: =SUM(CW100:CW111) -> 66.747745 | CX99: =SUM(CX100:CX111) -> 0 | CY99: =SUM(CY100:CY111) -> 96 | CZ99: =SUM(CZ100:CZ111) -> 0
C100: 入荷：6月 300枚 10月 300枚 | D100: 1 | E100: +1.50 | F100: 214.42006 | G100: =F100*4400 -> 943448.28 | H100: =F100*($H$99/$F$99) -> 214.42006 | I100: =H100*4400 -> 943448.28 | J100: 133 | K100: =SUM(L100:N100) -> 23 | L100: 9 | M100: 14 | Q100: 45654 | X100: 45860 | AI100: =SUM(J100:K100)-CI100+CJ100 -> 138.84639 | AJ100: =AI100-CK100+CL100 -> 122.51472 | AK100: =AJ100-CM100+CN100 -> 96.784315 | AL100: =AK100-CO100+CP100 -> 145.34231 | AM100: =AL100-CQ100+CR100 -> 126.0445 | AN100: =AM100-CS100+CT100 -> 104.6025 | AO100: =AN100-CU100+CV100 -> 91.545521 | AP100: =AO100-CW100+CX100 -> 79.618807 | AQ100: =AP100-CY100+CZ100 -> 62.465202 | AS100: =$H$100*月別販売比率!AG5 -> 21.442006 | AU100: =$H$100*月別販売比率!AL5 -> 19.297806 | AW100: =$H$100*月別販売比率!AQ5 -> 21.442006 | AX100: 100 | AY100: =$H$100*月別販売比率!AV5 -> 13.056976 | BA100: =$H$100*月別販売比率!BA5 -> 11.926713 | BC100: =$H$100*月別販売比率!BF5 -> 17.153605 | BE100: =$H$100*月別販売比率!C5 -> 15.194717 | BG100: =$H$100*月別販売比率!H5 -> 15.009404 | BI100: =$H$100*月別販売比率!M5 -> 21.670083 | BK100: =$H$100*月別販売比率!R5 -> 17.153605 | BL100: 115 | BM100: =$H$100*月別販売比率!W5 -> 16.331673 | BO100: =$H$100*月別販売比率!AB5 -> 25.730408 | BQ100: =$H$100*月別販売比率!AG5 -> 21.442006 | BR100: 75 | BS100: =$H$100*月別販売比率!AL5 -> 19.297806 | BU100: =$H$100*月別販売比率!AQ5 -> 21.442006 | BW100: =$H$100*月別販売比率!AV5 -> 13.056976 | BY100: =$H$100*月別販売比率!BA5 -> 11.926713 | CA100: =$H$100*月別販売比率!BF5 -> 17.153605 | CC100: =H100*月別販売比率!$C$21 -> 15.194717 | CE100: =H100*月別販売比率!$H$21 -> 15.009404 | CF100: 120 | CG100: =H100*月別販売比率!$M$21 -> 21.670083 | CH100: 70 | CI100: =H100*月別販売比率!$R$21 -> 17.153605 | CK100: =H100*月別販売比率!$W$21 -> 16.331673 | CM100: =H100*月別販売比率!$AB$21 -> 25.730408 | CO100: =H100*月別販売比率!$AG$21 -> 21.442006 | CP100: 70 | CQ100: =H100*月別販売比率!$AL$21 -> 19.297806 | CS100: =H100*月別販売比率!$AQ$21 -> 21.442006 | CU100: =H100*月別販売比率!$AV$21 -> 13.056976 | CW100: =H100*月別販売比率!$BA$21 -> 11.926713 | CY100: =H100*月別販売比率!$BF$21 -> 17.153605
...

Sheet 在庫推移
U1: 欠品
C2: ＊FL-3000の在庫も確認する！（次回発注あるかどうか：振り分け表にて） | AH2: 欠品 | AN2: 7月確認月 | AS2: 入荷済み | AV2: 仕様替え | CI2: 仕様替え | CK2: 納期変更分 | CM2: 入荷済み
C3: 在庫確保による販売試算表 | H3: 2025年12月変更分 | J3: 46224 | AN3: ↓ | BK3: プライムデー | BQ3: プライム感謝祭 | BS3: ブラックフライデー | BU3: スーパーセール
C4: 売上上位品番 | F4: 2024年販売想定ベース | H4: 調整データ | J4: 在庫確保数 | AH4: 補充完了日 | AS4: 45566 | AU4: 45597 | AW4: 45627 | AY4: 45658 | BA4: 45689 | BC4: 45717 | BE4: 45748 | BG4: 45778 | BI4: 45809 | BK4: 45839 | BM4: 45870 | BO4: 45901 | BQ4: 45931 | BS4: 45962 | BU4: 45992 | BW4: 46023 | BY4: 46054 | CA4: 46082 | CC4: 46113 | CE4: 46143 | CG4: 46174 | CI4: 46204 | CK4: 46235 | CM4: 46266 | CO4: 46296 | CQ4: 46327 | CS4: 46357 | CU4: 46388 | CW4: 46054 | CY4: 46082
B5: 優先順位 | C5: 品番 | D5: カラー | E5: 度数 | F5: 年間販売数 | G5: 年間売上額 | H5: 年間販売想定数 | I5: 年間売上想定額 | J5: フリー在庫 | K5: EC合計 | L5: 楽天・Yahoo!・auPAY(RSL) | M5: Amazon(FBA) | N5: ECストック | O5: 10/17~ | P5: 11月 | Q5: 12月 | R5: 1月 | S5: 2月 | T5: 3月 | U5: 4月 | V5: 5月 | W5: 6月 | X5: 7月 | Y5: 8月 | Z5: 9月 | AA5: 10月 | AB5: 11月 | AC5: 12月 | AD5: 1月 | AE5: 2月 | AF5: 3月 | AG5: 4月 | AH5: 5月 | AI5: 7月 | AJ5: 8月 | AK5: 9月 | AL5: 10月 | AM5: 11月 | AN5: 12月 | AO5: 1月 | AP5: 2月 | AQ5: 3月 | AS5: 必要数 | AT5: 入荷品確保 | AU5: 必要数 | AV5: 入荷品確保 | AW5: 必要数 | AX5: 入荷品確保 | AY5: 必要数 | AZ5: 入荷品確保 | BA5: 必要数 | BB5: 入荷品確保 | BC5: 必要数 | BD5: 入荷品確保 | BE5: 必要数 | BF5: 入荷品確保 | BG5: 必要数 | BH5: 入荷品確保 | BI5: 必要数 | BJ5: 入荷品確保 | BK5: 必要数 | BL5: 入荷品確保 | BM5: 必要数 | BN5: 入荷品確保 | BO5: 必要数 | BP5: 入荷品確保 | BQ5: 必要数 | BR5: 入荷品確保 | BS5: 必要数 | BT5: 入荷品確保 | BU5: 必要数 | BV5: 入荷品確保 | BW5: 必要数 | BX5: 入荷品確保 | BY5: 必要数 | BZ5: 入荷品確保 | CA5: 必要数 | CB5: 入荷品確保 | CC5: 必要数 | CD5: 入荷品確保 | CE5: 必要数 | CF5: 入荷品確保 | CG5: 必要数 | CH5: 入荷品確保 | CI5: 必要数 | CJ5: 入荷品確保 | CK5: 必要数 | CL5: 入荷品確保 | CM5: 必要数 | CN5: 入荷品確保 | CO5: 必要数 | CP5: 入荷品確保 | CQ5: 必要数 | CR5: 入荷品確保 | CS5: 必要数 | CT5: 入荷品確保 | CU5: 必要数 | CV5: 入荷品確保 | CW5: 必要数 | CX5: 入荷品確保 | CY5: 必要数 | CZ5: 入荷品確保
B6: 1 | C6: fisi-05 ＊欲しい月の2カ月前入荷想定で考える | F6: =SUM(F7:F26) -> 1314 | G6: =SUM(G7:G26) -> 5781600 | H6: 3500 | I6: =SUM(I7:I26) -> 15400000 | J6: =SUM(J7:J26) -> 95 | K6: =SUM(K7:K26) -> 876 | L6: =SUM(L7:L26) -> 123 | M6: =SUM(M7:M26) -> 55 | N6: =SUM(N7:N26) -> 698 | AS6: =SUM(AS7:AS26) -> 350 | AT6: =SUM(AT7:AT26) -> 0 | AU6: =SUM(AU7:AU26) -> 315 | AV6: =SUM(AV7:AV26) -> 432 | AW6: =SUM(AW7:AW26) -> 350 | AX6: =SUM(AX7:AX26) -> 784 | AY6: =SUM(AY7:AY26) -> 213.13031 | AZ6: =SUM(AZ7:AZ26) -> 0 | ... CZ6: =SUM(CZ7:CZ26) -> 0
C7: 入荷： 7月 1210枚 8月 600枚 11月 600枚 | D7: 1 | E7: +1.00 | F7: 48 | G7: =F7*4400 -> 211200 | H7: =F7*($H$6/$F$6) -> 127.85388 | I7: =H7*4400 -> 562557.08 | J7: 3 | K7: =SUM(L7:N7) -> 35 | L7: 10 | M7: 0 | N7: 25 | P7: 45622 | Q7: 45646 | V7: 45792 | Y7: 45884 | AC7: 45662 | AI7: =SUM(J7:K7)-CI7+CJ7 -> 47.771689 | AJ7: =AI7-CK7+CL7 -> 63.033479 | AK7: =AJ7-CM7+CN7 -> 47.691013 | AL7: =AK7-CO7+CP7 -> 34.905625 | AM7: =AL7-CQ7+CR7 -> 48.398775 | AN7: =AM7-CS7+CT7 -> 35.613387 | AO7: =AN7-CU7+CV7 -> 27.827805 | AP7: =AO7-CW7+CX7 -> 20.716173 | AQ7: =AP7-CY7+CZ7 -> 10.487863 | AS7: =$H$7*月別販売比率!AG5 -> 12.785388 | AU7: =$H$7*月別販売比率!AL5 -> 11.506849 | AV7: 12 | AW7: =$H$7*月別販売比率!AQ5 -> 12.785388 | AX7: 46 | AY7: =$H$7*月別販売比率!AV5 -> 7.7855823 | BA7: =$H$7*月別販売比率!BA5 -> 7.1116319 | BB7: 10 | BC7: =$H$7*月別販売比率!BF5 -> 10.228311 | BE7: =$H$7*月別販売比率!C21 -> 9.0602695 | BG7: =$H$7*月別販売比率!H21 -> 8.9497717 | BH7: 26 | BI7: =$H$7*月別販売比率!M21 -> 12.921385 | BJ7: 30 | BK7: =$H$7*月別販売比率!R21 -> 10.228311 | BM7: =$H$7*月別販売比率!W21 -> 9.7382108 | BN7: 25 | BO7: =$H$7*月別販売比率!AB21 -> 15.342466 | BP7: 20 | BQ7: =$H$7*月別販売比率!AG21 -> 12.785388 | BS7: =$H$7*月別販売比率!AL21 -> 11.506849 | BT7: 40 | BU7: =$H$7*月別販売比率!AQ21 -> 12.785388 | BV7: 10 | BW7: =$H$7*月別販売比率!AV21 -> 7.7855823 | BY7: =$H$7*月別販売比率!BA21 -> 7.1116319 | BZ7: 20 | CA7: =$H$7*月別販売比率!BF21 -> 10.228311 | CC7: =H7*月別販売比率!$C$21 -> 9.0602695 | CE7: =H7*月別販売比率!$H$21 -> 8.9497717 | CF7: 30 | CG7: =$H$7*月別販売比率!M21 -> 12.921385 | CH7: 25 | CI7: =H7*月別販売比率!$R$21 -> 10.228311 | CJ7: 20 | CK7: =H7*月別販売比率!$W$21 -> 9.7382108 | CL7: 25 | CM7: =H7*月別販売比率!$AB$21 -> 15.342466 | CO7: =H7*月別販売比率!$AG$21 -> 12.785388 | CQ7: =H7*月別販売比率!$AL$21 -> 11.506849 | CR7: 25 | CS7: =H7*月別販売比率!$AQ$21 -> 12.785388 | CU7: =H7*月別販売比率!$AV$21 -> 7.7855823 | CW7: =H7*月別販売比率!$BA$21 -> 7.1116319 | CY7: =H7*月別販売比率!$BF$21 -> 10.228311
E8: +1.50 | F8: 144 | G8: =F8*4400 -> 633600 | H8: =F8*($H$6/$F$6) -> 383.56164 | I8: =H8*4400 -> 1687671.2 | J8: 5 | K8: =SUM(L8:N8) -> 85 | L8: 10 | M8: 5 | N8: 70 | P8: 45622 | Q8: 45646 | AB8: 45979 | AI8: =SUM(J8:K8)-CI8+CJ8 -> 124.31507 | AJ8: =AI8-CK8+CL8 -> 185.10044 | AK8: =AJ8-CM8+CN8 -> 139.07304 | AL8: =AK8-CO8+CP8 -> 100.71687 | AM8: =AL8-CQ8+CR8 -> 131.19633 | AN8: =AM8-CS8+CT8 -> 92.840162 | AO8: =AN8-CU8+CV8 -> 69.483415 | AP8: =AO8-CW8+CX8 -> 48.14852 | AQ8: =AP8-CY8+CZ8 -> 17.463588 | AS8: =$H$8*月別販売比率!AG5 -> 38.356164 | AU8: =$H$8*月別販売比率!AL5 -> 34.520548 | AV8: 37 | AW8: =$H$8*月別販売比率!AQ5 -> 38.356164 | AX8: 81 | AY8: =$H$8*月別販売比率!AV5 -> 23.356747 | BA8: =$H$8*月別販売比率!BA5 -> 21.334896 | BB8: 75 | BC8: =$H$8*月別販売比率!BF5 -> 30.684932 | BE8: =$H$8*月別販売比率!C21 -> 27.180809 | BG8: =$H$8*月別販売比率!H21 -> 26.849315 | BH8: 50 | BI8: =$H$8*月別販売比率!M21 -> 38.764155 | BJ8: 55 | BK8: =$H$8*月別販売比率!R21 -> 30.684932 | BM8: =$H$8*月別販売比率!W21 -> 29.214632 | BN8: 30 | BO8: =$H$8*月別販売比率!AB21 -> 46.027397 | BP8: 50 | BQ8: =$H$8*月別販売比率!AG21 -> 38.356164 | BR8: 79 | BS8: =$H$8*月別販売比率!AL21 -> 34.520548 | BT8: 85 | BU8: =$H$8*月別販売比率!AQ21 -> 38.356164 | BV8: 50 | BW8: =$H$8*月別販売比率!AV21 -> 23.356747 | BY8: =$H$8*月別販売比率!BA21 -> 21.334896 | BZ8: 8 | CA8: =$H$8*月別販売比率!BF21 -> 30.684932 | CC8: =H8*月別販売比率!$C$21 -> 27.180809 | CE8: =H8*月別販売比率!$H$21 -> 26.849315 | CF8: 80 | CG8: =$H$8*月別販売比率!M21 -> 38.764155 | CH8: 70 | CI8: =H8*月別販売比率!$R$21 -> 30.684932 | CJ8: 65 | CK8: =H8*月別販売比率!$W$21 -> 29.214632 | CL8: 90 | CM8: =H8*月別販売比率!$AB$21 -> 46.027397 | CO8: =H8*月別販売比率!$AG$21 -> 38.356164 | CQ8: =H8*月別販売比率!$AL$21 -> 34.520548 | CR8: 65 | CS8: =H8*月別販売比率!$AQ$21 -> 38.356164 | CU8: =H8*月別販売比率!$AV$21 -> 23.356747 | CW8: =H8*月別販売比率!$BA$21 -> 21.334896 | CY8: =H8*月別販売比率!$BF$21 -> 30.684932
E9: +2.00 | F9: 127 | G9: =F9*4400 -> 558800 | H9: =F9*($H$6/$F$6) -> 338.28006 | I9: =H9*4400 -> 1488432.3 | J9: 29 | K9: =SUM(L9:N9) -> 134 | L9: 9 | M9: 15 | N9: 110 | P9: 45622 | AB9: 45979 | AI9: =SUM(J9:K9)-CI9+CJ9 -> 160.9376 | AJ9: =AI9-CK9+CL9 -> 200.17191 | AK9: =AJ9-CM9+CN9 -> 159.57831 | AL9: =AK9-CO9+CP9 -> 125.7503 | AM9: =AL9-CQ9+CR9 -> 140.30509 | AN9: =AM9-CS9+CT9 -> 106.47709 | AO9: =AN9-CU9+CV9 -> 85.877734 | AP9: =AO9-CW9+CX9 -> 67.061542 | AQ9: =AP9-CY9+CZ9 -> 39.999137 | AS9: =$H$9*月別販売比率!AG5 -> 33.828006 | AU9: =$H$9*月別販売比率!AL5 -> 30.445205 | AV9: 55 | AW9: =$H$9*月別販売比率!AQ5 -> 33.828006 | AX9: 71 | AY9: =$H$9*月別販売比率!AV5 -> 20.599353 | BA9: =$H$9*月別販売比率!BA5 -> 18.816193 | BB9: 65 | BC9: =$H$9*月別販売比率!BF5 -> 27.062405 | BE9: =$H$9*月別販売比率!C21 -> 23.971963 | BG9: =$H$9*月別販売比率!H21 -> 23.679604 | BH9: 45 | BI9: =$H$9*月別販売比率!M21 -> 34.187831 | BJ9: 45 | BK9: =$H$9*月別販売比率!R21 -> 27.062405 | BM9: =$H$9*月別販売比率!W21 -> 25.765683 | BN9: 10 | BO9: =$H$9*月別販売比率!AB21 -> 40.593607 | BQ9: =$H$9*月別販売比率!AG21 -> 33.828006 | BR9: 90 | BS9: =$H$9*月別販売比率!AL21 -> 30.445205 | BT9: 48 | BU9: =$H$9*月別販売比率!AQ21 -> 33.828006 | BV9: 25 | BW9: =$H$9*月別販売比率!AV21 -> 20.599353 | BY9: =$H$9*月別販売比率!BA21 -> 18.816193 | BZ9: 8 | CA9: =$H$9*月別販売比率!BF21 -> 27.062405 | CC9: =H9*月別販売比率!$C$21 -> 23.971963 | CE9: =H9*月別販売比率!$H$21 -> 23.679604 | CF9: 100 | CG9: =$H$9*月別販売比率!M21 -> 34.187831 | CH9: 65 | CI9: =H9*月別販売比率!$R$21 -> 27.062405 | CJ9: 25 | CK9: =H9*月別販売比率!$W$21 -> 25.765683 | CL9: 65 | CM9: =H9*月別販売比率!$AB$21 -> 40.593607 | CO9: =H9*月別販売比率!$AG$21 -> 33.828006 | CQ9: =H9*月別販売比率!$AL$21 -> 30.445205 | CR9: 45 | CS9: =H9*月別販売比率!$AQ$21 -> 33.828006 | CU9: =H9*月別販売比率!$AV$21 -> 20.599353 | CW9: =H9*月別販売比率!$BA$21 -> 18.816193 | CY9: =H9*月別販売比率!$BF$21 -> 27.062405
E10: +2.50 | F10: 46 | G10: =F10*4400 -> 202400 | H10: =F10*($H$6/$F$6) -> 122.52664 | I10: =H10*4400 -> 539117.2 | J10: 23 | K10: =SUM(L10:N10) -> 35 | L10: 10 | M10: 0 | N10: 25 | P10: 45622 | V10: 45792 | Y10: 45884 | AC10: 46017 | AI10: =SUM(J10:K10)-CI10+CJ10 -> 68.197869 | AJ10: =AI10-CK10+CL10 -> 78.865417 | AK10: =AJ10-CM10+CN10 -> 64.162221 | AL10: =AK10-CO10+CP10 -> 51.909557 | AM10: =AL10-CQ10+CR10 -> 60.88216 | AN10: =AM10-CS10+CT10 -> 48.629496 | AO10: =AN10-CU10+CV10 -> 41.168313 | AP10: =AO10-CW10+CX10 -> 34.352999 | AQ10: =AP10-CY10+CZ10 -> 24.550868 | AS10: =$H$10*月別販売比率!AG5 -> 12.252664 | AU10: =$H$10*月別販売比率!AL5 -> 11.027397 | AV10: 20 | AW10: =$H$10*月別販売比率!AQ5 -> 12.252664 | AX10: 26 | AY10: =$H$10*月別販売比率!AV5 -> 7.461183 | BA10: =$H$10*月別販売比率!BA5 -> 6.8153139 | BB10: 20 | BC10: =$H$10*月別販売比率!BF5 -> 9.8021309 | BE10: =$H$10*月別販売比率!C21 -> 8.6827583 | BG10: =$H$10*月別販売比率!H21 -> 8.5768645 | BH10: 20 | BI10: =$H$10*月別販売比率!M21 -> 12.382994 | BJ10: 20 | BK10: =$H$10*月別販売比率!R21 -> 9.8021309 | BM10: =$H$10*月別販売比率!W21 -> 9.332452 | BN10: 10 | BO10: =$H$10*月別販売比率!AB21 -> 14.703196 | BP10: 35 | BQ10: =$H$10*月別販売比率!AG21 -> 12.252664 | BS10: =$H$10*月別販売比率!AL21 -> 11.027397 | BT10: 17 | BU10: =$H$10*月別販売比率!AQ21 -> 12.252664 | BV10: 10 | BW10: =$H$10*月別販売比率!AV21 -> 7.461183 | BY10: =$H$10*月別販売比率!BA21 -> 6.8153139 | BZ10: 23 | CA10: =$H$10*月別販売比率!BF21 -> 9.8021309 | CC10: =H10*月別販売比率!$C$21 -> 8.6827583 | CE10: =H10*月別販売比率!$H$21 -> 8.5768645 | CF10: 30 | CG10: =$H$10*月別販売比率!M21 -> 12.382994 | CH10: 25 | CI10: =H10*月別販売比率!$R$21 -> 9.8021309 | CJ10: 20 | CK10: =H10*月別販売比率!$W$21 -> 9.332452 | CL10: 20 | CM10: =H10*月別販売比率!$AB$21 -> 14.703196 | CO10: =H10*月別販売比率!$AG$21 -> 12.252664 | CQ10: =H10*月別販売比率!$AL$21 -> 11.027397 | CR10: 20 | CS10: =H10*月別販売比率!$AQ$21 -> 12.252664 | CU10: =H10*月別販売比率!$AV$21 -> 7.461183 | CW10: =H10*月別販売比率!$BA$21 -> 6.8153139 | CY10: =H10*月別販売比率!$BF$21 -> 9.8021309
E11: +3.00 | F11: 30 | G11: =F11*4400 -> 132000 | H11: =F11*($H$6/$F$6) -> 79.908676 | I11: =H11*4400 -> 351598.17 | J11: 0 | K11: =SUM(L11:N11) -> 31 | L11: 7 | M11: 0 | N11: 24 | S11: 45707 | V11: 45792 | AI11: =SUM(J11:K11)-CI11+CJ11 -> 24.607306 | AJ11: =AI11-CK11+CL11 -> 33.520924 | AK11: =AJ11-CM11+CN11 -> 23.931883 | AL11: =AK11-CO11+CP11 -> 15.941015 | AM11: =AL11-CQ11+CR11 -> 23.749235 | AN11: =AM11-CS11+CT11 -> 15.758367 | AO11: =AN11-CU11+CV11 -> 10.892378 | AP11: =AO11-CW11+CX11 -> 6.4476083 | AQ11: =AP11-CY11+CZ11 -> 0.054914204 | AS11: =$H$11*月別販売比率!AG5 -> 7.9908676 | AU11: =$H$11*月別販売比率!AL5 -> 7.1917808 | AW11: =$H$11*月別販売比率!AQ5 -> 7.9908676 | AY11: =$H$11*月別販売比率!AV5 -> 4.8659889 | BA11: =$H$11*月別販売比率!BA5 -> 4.4447699 | BB11: 15 | BC11: =$H$11*月別販売比率!BF5 -> 6.3926941 | BE11: =$H$11*月別販売比率!C21 -> 5.6626685 | BG11: =$H$11*月別販売比率!H21 -> 5.5936073 | BH11: 10 | BI11: =$H$11*月別販売比率!M21 -> 8.0758656 | BJ11: 10 | BK11: =$H$11*月別販売比率!R21 -> 6.3926941 | BM11: =$H$11*月別販売比率!W21 -> 6.0863818 | BN11: 10 | BO11: =$H$11*月別販売比率!AB21 -> 9.5890411 | BP11: 20 | BQ11: =$H$11*月別販売比率!AG21 -> 7.9908676 | BS11: =$H$11*月別販売比率!AL21 -> 7.1917808 | BT11: 30 | BU11: =$H$11*月別販売比率!AQ21 -> 7.9908676 | BV11: 5 | BW11: =$H$11*月別販売比率!AV21 -> 4.8659889 | BY11: =$H$11*月別販売比率!BA21 -> 4.4447699 | BZ11: 5 | CA11: =$H$11*月別販売比率!BF21 -> 6.3926941 | CC11: =H11*月別販売比率!$C$21 -> 5.6626685 | CE11: =H11*月別販売比率!$H$21 -> 5.5936073 | CF11: 20 | CG11: =$H$11*月別販売比率!M21 -> 8.0758656 | CH11: 24 | CI11: =H11*月別販売比率!$R$21 -> 6.3926941 | CK11: =H11*月別販売比率!$W$21 -> 6.0863818 | CL11: 15 | CM11: =H11*月別販売比率!$AB$21 -> 9.5890411 | CO11: =H11*月別販売比率!$AG$21 -> 7.9908676 | CQ11: =H11*月別販売比率!$AL$21 -> 7.1917808 | CR11: 15 | CS11: =H11*月別販売比率!$AQ$21 -> 7.9908676 | CU11: =H11*月別販売比率!$AV$21 -> 4.8659889 | CW11: =H11*月別販売比率!$BA$21 -> 4.4447699 | CY11: =H11*月別販売比率!$BF$21 -> 6.3926941
D12: 2 | E12: +1.00 | F12: 84 | G12: =F12*4400 -> 369600 | H12: =F12*($H$6/$F$6) -> 223.74429 | I12: =H12*4400 -> 984474.89 | J12: 0 | K12: =SUM(L12:N12) -> 45 | L12: 0 | M12: 0 | N12: 45 | P12: 45622 | Q12: 45646 | V12: 45792 | Y12: 45884 | AB12: 45979 | AI12: =SUM(J12:K12)-CI12+CJ12 -> 82.100457 | AJ12: =AI12-CK12+CL12 -> 100.05859 | AK12: =AJ12-CM12+CN12 -> 73.209273 | AL12: =AK12-CO12+CP12 -> 50.834843 | AM12: =AL12-CQ12+CR12 -> 65.697857 | AN12: =AM12-CS12+CT12 -> 43.323428 | AO12: =AN12-CU12+CV12 -> 29.698659 | AP12: =AO12-CW12+CX12 -> 17.253303 | AQ12: =AP12-CY12+CZ12 -> -0.64624023 | AS12: =$H$12*月別販売比率!AG5 -> 22.374429 | AU12: =$H$12*月別販売比率!AL5 -> 20.136986 | AV12: 36 | AW12: =$H$12*月別販売比率!AQ5 -> 22.374429 | AX12: 60 | AY12: =$H$12*月別販売比率!AV5 -> 13.624769 | BA12: =$H$12*月別販売比率!BA5 -> 12.445356 | BB12: 35 | BC12: =$H$12*月別販売比率!BF5 -> 17.899543 | BE12: =$H$12*月別販売比率!C21 -> 15.855472 | BG12: =$H$12*月別販売比率!H21 -> 15.6621 | BH12: 27 | BI12: =$H$12*月別販売比率!M21 -> 22.612424 | BJ12: 20 | BK12: =$H$12*月別販売比率!R21 -> 17.899543 | BM12: =$H$12*月別販売比率!W21 -> 17.041869 | BN12: 35 | BO12: =$H$12*月別販売比率!AB21 -> 26.849315 | BP12: 30 | BQ12: =$H$12*月別販売比率!AG21 -> 22.374429 | BR12: 25 | BS12: =$H$12*月別販売比率!AL21 -> 20.136986 | BT12: 75 | BU12: =$H$12*月別販売比率!AQ21 -> 22.374429 | BV12: 35 | BW12: =$H$12*月別販売比率!AV21 -> 13.624769 | BY12: =$H$12*月別販売比率!BA21 -> 12.445356 | BZ12: 16 | CA12: =$H$12*月別販売比率!BF21 -> 17.899543 | CC12: =H12*月別販売比率!$C$21 -> 15.855472 | CE12: =H12*月別販売比率!$H$21 -> 15.6621 | CF12: 30 | CG12: =$H$12*月別販売比率!M21 -> 22.612424 | CH12: 45 | CI12: =H12*月別販売比率!$R$21 -> 17.899543 | CJ12: 55 | CK12: =H12*月別販売比率!$W$21 -> 17.041869 | CL12: 35 | CM12: =H12*月別販売比率!$AB$21 -> 26.849315 | CO12: =H12*月別販売比率!$AG$21 -> 22.374429 | CQ12: =H12*月別販売比率!$AL$21 -> 20.136986 | CR12: 35 | CS12: =H12*月別販売比率!$AQ$21 -> 22.374429 | CU12: =H12*月別販売比率!$AV$21 -> 13.624769 | CW12: =H12*月別販売比率!$BA$21 -> 12.445356 | CY12: =H12*月別販売比率!$BF$21 -> 17.899543
E13: +1.50 | F13: 116 | G13: =F13*4400 -> 510400 | H13: =F13*($H$6/$F$6) -> 308.98021 | I13: =H13*4400 -> 1359512.9 | J13: 0 | K13: =SUM(L13:N13) -> 29 | L13: 0 | M13: 0 | N13: 29 | P13: 45622 | Q13: 45646 | V13: 45792 | Y13: 45884 | AB13: 45979 | AC13: 45662 | AI13: =SUM(J13:K13)-CI13+CJ13 -> 98.281583 | AJ13: =AI13-CK13+CL13 -> 144.74757 | AK13: =AJ13-CM13+CN13 -> 107.66995 | AL13: =AK13-CO13+CP13 -> 76.771927 | AM13: =AL13-CQ13+CR13 -> 81.963707 | AN13: =AM13-CS13+CT13 -> 51.065686 | AO13: =AN13-CU13+CV13 -> 32.250529 | AP13: =AO13-CW13+CX13 -> 15.064085 | AQ13: =AP13-CY13+CZ13 -> -9.6543317 | AS13: =$H$13*月別販売比率!AG5 -> 30.898021 | AU13: =$H$13*月別販売比率!AL5 -> 27.808219 | AV13: 47 | AW13: =$H$13*月別販売比率!AQ5 -> 30.898021 | AX13: 115 | AY13: =$H$13*月別販売比率!AV5 -> 18.815157 | BA13: =$H$13*月別販売比率!BA5 -> 17.186444 | BB13: 40 | BC13: =$H$13*月別販売比率!BF5 -> 24.718417 | BE13: =$H$13*月別販売比率!C21 -> 21.895651 | BG13: =$H$13*月別販売比率!H21 -> 21.628615 | BH13: 35 | BI13: =$H$13*月別販売比率!M21 -> 31.22668 | BJ13: 25 | BK13: =$H$13*月別販売比率!R21 -> 24.718417 | BM13: =$H$13*月別販売比率!W21 -> 23.534009 | BN13: 80 | BO13: =$H$13*月別販売比率!AB21 -> 37.077626 | BQ13: =$H$13*月別販売比率!AG21 -> 30.898021 | BR13: 60 | BS13: =$H$13*月別販売比率!AL21 -> 27.808219 | BT13: 30 | BU13: =$H$13*月別販売比率!AQ21 -> 30.898021 | BV13: 45 | BW13: =$H$13*月別販売比率!AV21 -> 18.815157 | BY13: =$H$13*月別販売比率!BA21 -> 17.186444 | BZ13: 83 | CA13: =$H$13*月別販売比率!BF21 -> 24.718417 | CC13: =H13*月別販売比率!$C$21 -> 21.895651 | CE13: =H13*月別販売比率!$H$21 -> 21.628615 | CF13: 30 | CG13: =$H$13*月別販売比率!M21 -> 31.22668 | CH13: 29 | CI13: =H13*月別販売比率!$R$21 -> 24.718417 | CJ13: 94 | CK13: =H13*月別販売比率!$W$21 -> 23.534009 | CL13: 70 | CM13: =H13*月別販売比率!$AB$21 -> 37.077626 | CO13: =H13*月別販売比率!$AG$21 -> 30.898021 | CQ13: =H13*月別販売比率!$AL$21 -> 27.808219 | CR13: 33 | CS13: =H13*月別販売比率!$AQ$21 -> 30.898021 | CU13: =H13*月別販売比率!$AV$21 -> 18.815157 | CW13: =H13*月別販売比率!$BA$21 -> 17.186444 | CY13: =H13*月別販売比率!$BF$21 -> 24.718417
E14: +2.00 | F14: 184 | G14: =F14*4400 -> 809600 | H14: =F14*($H$6/$F$6) -> 490.10654 | I14: =H14*4400 -> 2156468.8 | J14: 0 | K14: =SUM(L14:N14) -> 33 | L14: 9 | M14: 2 | N14: 22 | P14: 45622 | Q14: 45646 | AB14: 45979 | AI14: =SUM(J14:K14)-CI14+CJ14 -> 143.79148 | AJ14: =AI14-CK14+CL14 -> 196.46167 | AK14: =AJ14-CM14+CN14 -> 137.64888 | AL14: =AK14-CO14+CP14 -> 88.638228 | AM14: =AL14-CQ14+CR14 -> 149.52864 | AN14: =AM14-CS14+CT14 -> 100.51798 | AO14: =AN14-CU14+CV14 -> 70.673253 | AP14: =AO14-CW14+CX14 -> 43.411997 | AQ14: =AP14-CY14+CZ14 -> 4.2034738 | AS14: =$H$14*月別販売比率!AG5 -> 49.010654 | AU14: =$H$14*月別販売比率!AL5 -> 44.109589 | AV14: 72 | AW14: =$H$14*月別販売比率!AQ5 -> 49.010654 | AX14: 120 | AY14: =$H$14*月別販売比率!AV5 -> 29.844732 | BA14: =$H$14*月別販売比率!BA5 -> 27.261256 | BB14: 90 | BC14: =$H$14*月別販売比率!BF5 -> 39.208524 | BE14: =$H$14*月別販売比率!C21 -> 34.731033 | BG14: =$H$14*月別販売比率!H21 -> 34.307458 | BH14: 65 | BI14: =$H$14*月別販売比率!M21 -> 49.531975 | BJ14: 55 | BK14: =$H$14*月別販売比率!R21 -> 39.208524 | BM14: =$H$14*月別販売比率!W21 -> 37.329808 | BN14: 20 | BO14: =$H$14*月別販売比率!AB21 -> 58.812785 | BP14: 50 | BQ14: =$H$14*月別販売比率!AG21 -> 49.010654 | BR14: 50 | BS14: =$H$14*月別販売比率!AL21 -> 44.109589 | BT14: 124 | BU14: =$H$14*月別販売比率!AQ21 -> 49.010654 | BV14: 105 | BW14: =$H$14*月別販売比率!AV21 -> 29.844732 | BY14: =$H$14*月別販売比率!BA21 -> 27.261256 | BZ14: 33 | CA14: =$H$14*月別販売比率!BF21 -> 39.208524 | CC14: =H14*月別販売比率!$C$21 -> 34.731033 | CE14: =H14*月別販売比率!$H$21 -> 34.307458 | CF14: 70 | CG14: =$H$14*月別販売比率!M21 -> 49.531975 | CH14: 22 | CI14: =H14*月別販売比率!$R$21 -> 39.208524 | CJ14: 150 | CK14: =H14*月別販売比率!$W$21 -> 37.329808 | CL14: 90 | CM14: =H14*月別販売比率!$AB$21 -> 58.812785 | CO14: =H14*月別販売比率!$AG$21 -> 49.010654 | CQ14: =H14*月別販売比率!$AL$21 -> 44.109589 | CR14: 105 | CS14: =H14*月別販売比率!$AQ$21 -> 49.010654 | CU14: =H14*月別販売比率!$AV$21 -> 29.844732 | CW14: =H14*月別販売比率!$BA$21 -> 27.261256 | CY14: =H14*月別販売比率!$BF$21 -> 39.208524
E15: +2.50 | F15: 54 | G15: =F15*4400 -> 237600 | H15: =F15*($H$6/$F$6) -> 143.83562 | I15: =H15*4400 -> 632876.71 | J15: 4 | K15: =SUM(L15:N15) -> 27 | L15: 8 | M15: 4 | N15: 15 | Q15: 45646 | V15: 45792 | Y15: 45884 | AC15: 46017 | AI15: =SUM(J15:K15)-CI15+CJ15 -> 49.493151 | AJ15: =AI15-CK15+CL15 -> 58.537664 | AK15: =AJ15-CM15+CN15 -> 41.27739 | AL15: =AK15-CO15+CP15 -> 26.893828 | AM15: =AL15-CQ15+CR15 -> 43.948622 | AN15: =AM15-CS15+CT15 -> 29.565061 | AO15: =AN15-CU15+CV15 -> 20.806281 | AP15: =AO15-CW15+CX15 -> 12.805695 | AQ15: =AP15-CY15+CZ15 -> 1.2988456 | AS15: =$H$15*月別販売比率!AG5 -> 14.383562 | AU15: =$H$15*月別販売比率!AL5 -> 12.945205 | AV15: 11 | AW15: =$H$15*月別販売比率!AQ5 -> 14.383562 | AX15: 30 | AY15: =$H$15*月別販売比率!AV5 -> 8.75878 | BA15: =$H$15*月別販売比率!BA5 -> 8.0005859 | BB15: 20 | BC15: =$H$15*月別販売比率!BF5 -> 11.506849 | BE15: =$H$15*月別販売比率!C21 -> 10.192803 | BG15: =$H$15*月別販売比率!H21 -> 10.068493 | BH15: 20 | BI15: =$H$15*月別販売比率!M21 -> 14.536558 | BJ15: 25 | BK15: =$H$15*月別販売比率!R21 -> 11.506849 | BM15: =$H$15*月別販売比率!W21 -> 10.955487 | BN15: 20 | BO15: =$H$15*月別販売比率!AB21 -> 17.260274 | BP15: 20 | BQ15: =$H$15*月別販売比率!AG21 -> 14.383562 | BS15: =$H$15*月別販売比率!AL21 -> 12.945205 | BT15: 39 | BU15: =$H$15*月別販売比率!AQ21 -> 14.383562 | BV15: 10 | BW15: =$H$15*月別販売比率!AV21 -> 8.75878 | BY15: =$H$15*月別販売比率!BA21 -> 8.0005859 | BZ15: 40 | CA15: =$H$15*月別販売比率!BF21 -> 11.506849 | CC15: =H15*月別販売比率!$C$21 -> 10.192803 | CE15: =H15*月別販売比率!$H$21 -> 10.068493 | CF15: 40 | CG15: =$H$15*月別販売比率!M21 -> 14.536558 | CH15: 15 | CI15: =H15*月別販売比率!$R$21 -> 11.506849 | CJ15: 30 | CK15: =H15*月別販売比率!$W$21 -> 10.955487 | CL15: 20 | CM15: =H15*月別販売比率!$AB$21 -> 17.260274 | CO15: =H15*月別販売比率!$AG$21 -> 14.383562 | CQ15: =H15*月別販売比率!$AL$21 -> 12.945205 | CR15: 30 | CS15: =H15*月別販売比率!$AQ$21 -> 14.383562 | CU15: =H15*月別販売比率!$AV$21 -> 8.75878 | CW15: =H15*月別販売比率!$BA$21 -> 8.0005859 | CY15: =H15*月別販売比率!$BF$21 -> 11.506849
E16: +3.00 | F16: 26 | G16: =F16*4400 -> 114400 | H16: =F16*($H$6/$F$6) -> 69.254186 | I16: =H16*4400 -> 304718.42 | J16: 0 | K16: =SUM(L16:N16) -> 29 | L16: 6 | M16: 14 | N16: 9 | AC16: 45662 | AI16: =SUM(J16:K16)-CI16+CJ16 -> 28.459665 | AJ16: =AI16-CK16+CL16 -> 38.184801 | AK16: =AJ16-CM16+CN16 -> 29.874299 | AL16: =AK16-CO16+CP16 -> 22.94888 | AM16: =AL16-CQ16+CR16 -> 31.716003 | AN16: =AM16-CS16+CT16 -> 24.790585 | AO16: =AN16-CU16+CV16 -> 20.573394 | AP16: =AO16-CW16+CX16 -> 16.72126 | AQ16: =AP16-CY16+CZ16 -> 11.180926 | AS16: =$H$16*月別販売比率!AG5 -> 6.9254186 | AU16: =$H$16*月別販売比率!AL5 -> 6.2328767 | AV16: 10 | AW16: =$H$16*月別販売比率!AQ5 -> 6.9254186 | AY16: =$H$16*月別販売比率!AV5 -> 4.2171904 | BA16: =$H$16*月別販売比率!BA5 -> 3.8521339 | BC16: =$H$16*月別販売比率!BF5 -> 5.5403349 | BE16: =$H$16*月別販売比率!C21 -> 4.907646 | BG16: =$H$16*月別販売比率!H21 -> 4.847793 | BH16: 5 | BI16: =$H$16*月別販売比率!M21 -> 6.9990835 | BJ16: 5 | BK16: =$H$16*月別販売比率!R21 -> 5.5403349 | BM16: =$H$16*月別販売比率!W21 -> 5.2748642 | BN16: 5 | BO16: =$H$16*月別販売比率!AB21 -> 8.3105023 | BP16: 20 | BQ16: =$H$16*月別販売比率!AG21 -> 6.9254186 | BS16: =$H$16*月別販売比率!AL21 -> 6.2328767 | BT16: 15 | BU16: =$H$16*月別販売比率!AQ21 -> 6.9254186 | BV16: 5 | BW16: =$H$16*月別販売比率!AV21 -> 4.2171904 | BY16: =$H$16*月別販売比率!BA21 -> 3.8521339 | BZ16: 5 | CA16: =$H$16*月別販売比率!BF21 -> 5.5403349 | CC16: =H16*月別販売比率!$C$21 -> 4.907646 | CE16: =H16*月別販売比率!$H$21 -> 4.847793 | CF16: 20 | CG16: =$H$16*月別販売比率!M21 -> 6.9990835 | CH16: 9 | CI16: =H16*月別販売比率!$R$21 -> 5.5403349 | CJ16: 5 | CK16: =H16*月別販売比率!$W$21 -> 5.2748642 | CL16: 15 | CM16: =H16*月別販売比率!$AB$21 -> 8.3105023 | CO16: =H16*月別販売比率!$AG$21 -> 6.9254186 | CQ16: =H16*月別販売比率!$AL$21 -> 6.2328767 | CR16: 15 | CS16: =H16*月別販売比率!$AQ$21 -> 6.9254186 | CU16: =H16*月別販売比率!$AV$21 -> 4.2171904 | CW16: =H16*月別販売比率!$BA$21 -> 3.8521339 | CY16: =H16*月別販売比率!$BF$21 -> 5.5403349
D17: 3 (廃番) | E17: +1.00 | F17: 25 | G17: =F17*4400 -> 110000 | H17: =F17*($H$6/$F$6) -> 66.590563 | I17: =H17*4400 -> 292998.48 | J17: 0 | K17: =SUM(L17:N17) -> 34 | L17: 0 | M17: 0 | N17: 34 | S17: 45707 | Y17: 45884 | AB17: 45979 | AI17: =SUM(J17:K17)-CI17+CJ17 -> 28.672755 | AJ17: =AI17-CK17+CL17 -> 23.60077 | AK17: =AJ17-CM17+CN17 -> 15.609903 | AL17: =AK17-CO17+CP17 -> 8.9508462 | AM17: =AL17-CQ17+CR17 -> 2.9576956 | AN17: =AM17-CS17+CT17 -> -3.7013608 | AO17: =AN17-CU17+CV17 -> -7.7563515 | AP17: =AO17-CW17+CX17 -> -11.460326 | AQ17: =AP17-CY17+CZ17 -> -16.787571 | AS17: =$H$17*月別販売比率!AG5 -> 6.6590563 | AU17: =$H$17*月別販売比率!AL5 -> 5.9931507 | AW17: =$H$17*月別販売比率!AQ5 -> 6.6590563 | AY17: =$H$17*月別販売比率!AV5 -> 4.0549908 | BA17: =$H$17*月別販売比率!BA5 -> 3.7039749 | BB17: 40 | BC17: =$H$17*月別販売比率!BF5 -> 5.3272451 | BE17: =$H$17*月別販売比率!C21 -> 4.7188904 | BG17: =$H$17*月別販売比率!H21 -> 4.6613394 | BI17: =$H$17*月別販売比率!M21 -> 6.729888 | BK17: =$H$17*月別販売比率!R21 -> 5.3272451 | BM17: =$H$17*月別販売比率!W21 -> 5.0719848 | BN17: 15 | BO17: =$H$17*月別販売比率!AB21 -> 7.9908676 | BP17: 15 | BQ17: =$H$17*月別販売比率!AG21 -> 6.6590563 | BS17: =$H$17*月別販売比率!AL21 -> 5.9931507 | BT17: 20 | BU17: =$H$17*月別販売比率!AQ21 -> 6.6590563 | BW17: =$H$17*月別販売比率!AV21 -> 4.0549908 | BY17: =$H$17*月別販売比率!BA21 -> 3.7039749 | CA17: =$H$17*月別販売比率!BF21 -> 5.3272451 | CC17: =H17*月別販売比率!$C$21 -> 4.7188904 | CE17: =H17*月別販売比率!$H$21 -> 4.6613394 | CG17: =$H$17*月別販売比率!M21 -> 6.729888 | CH17: 35 | CI17: =H17*月別販売比率!$R$21 -> 5.3272451 | CK17: =H17*月別販売比率!$W$21 -> 5.0719848 | CM17: =H17*月別販売比率!$AB$21 -> 7.9908676 | CO17: =H17*月別販売比率!$AG$21 -> 6.6590563 | CQ17: =H17*月別販売比率!$AL$21 -> 5.9931507 | CS17: =H17*月別販売比率!$AQ$21 -> 6.6590563 | CU17: =H17*月別販売比率!$AV$21 -> 4.0549908 | CW17: =H17*月別販売比率!$BA$21 -> 3.7039749 | CY17: =H17*月別販売比率!$BF$21 -> 5.3272451
E18: +1.50 | F18: 10 | G18: =F18*4400 -> 44000 | H18: =F18*($H$6/$F$6) -> 26.636225 | I18: =H18*4400 -> 117199.39 | J18: 0 | K18: =SUM(L18:N18) -> 15 | L18: 0 | M18: 0 | N18: 15 | S18: 45707 | V18: 45792 | Y18: 45884 | AB18: 45979 | AI18: =SUM(J18:K18)-CI18+CJ18 -> 12.869102 | AJ18: =AI18-CK18+CL18 -> 10.840308 | AK18: =AJ18-CM18+CN18 -> 7.643961 | AL18: =AK18-CO18+CP18 -> 4.9803385 | AM18: =AL18-CQ18+CR18 -> 2.5830782 | AN18: =AM18-CS18+CT18 -> -0.080544301 | AO18: =AN18-CU18+CV18 -> -1.7025406 | AP18: =AO18-CW18+CX18 -> -3.1841306 | AQ18: =AP18-CY18+CZ18 -> -5.3150286 | AS18: =$H$18*月別販売比率!AG5 -> 2.6636225 | AU18: =$H$18*月別販売比率!AL5 -> 2.3972603 | AW18: =$H$18*月別販売比率!AQ5 -> 2.6636225 | AY18: =$H$18*月別販売比率!AV5 -> 1.6219963 | BA18: =$H$18*月別販売比率!BA5 -> 1.48159 | BB18: 30 | BC18: =$H$18*月別販売比率!BF5 -> 2.130898 | BE18: =$H$18*月別販売比率!C21 -> 1.8875562 | BG18: =$H$18*月別販売比率!H21 -> 1.8645358 | BI18: =$H$18*月別販売比率!M21 -> 2.6919552 | BK18: =$H$18*月別販売比率!R21 -> 2.130898 | BM18: =$H$18*月別販売比率!W21 -> 2.0287939 | BN18: 10 | BO18: =$H$18*月別販売比率!AB21 -> 3.196347 | BP18: 15 | BQ18: =$H$18*月別販売比率!AG21 -> 2.6636225 | BS18: =$H$18*月別販売比率!AL21 -> 2.3972603 | BT18: 25 | BU18: =$H$18*月別販売比率!AQ21 -> 2.6636225 | BW18: =$H$18*月別販売比率!AV21 -> 1.6219963 | BY18: =$H$18*月別販売比率!BA21 -> 1.48159 | CA18: =$H$18*月別販売比率!BF21 -> 2.130898 | CC18: =H18*月別販売比率!$C$21 -> 1.8875562 | CE18: =H18*月別販売比率!$H$21 -> 1.8645358 | CG18: =$H$18*月別販売比率!M21 -> 2.6919552 | CH18: 15 | CI18: =H18*月別販売比率!$R$21 -> 2.130898 | CK18: =H18*月別販売比率!$W$21 -> 2.0287939 | CM18: =H18*月別販売比率!$AB$21 -> 3.196347 | CO18: =H18*月別販売比率!$AG$21 -> 2.6636225 | CQ18: =H18*月別販売比率!$AL$21 -> 2.3972603 | CS18: =H18*月別販売比率!$AQ$21 -> 2.6636225 | CU18: =H18*月別販売比率!$AV$21 -> 1.6219963 | CW18: =H18*月別販売比率!$BA$21 -> 1.48159 | CY18: =H18*月別販売比率!$BF$21 -> 2.130898
E19: +2.00 | F19: 15 | G19: =F19*4400 -> 66000 | H19: =F19*($H$6/$F$6) -> 39.954338 | I19: =H19*4400 -> 175799.09 | J19: 0 | K19: =SUM(L19:N19) -> 20 | L19: 0 | M19: 0 | N19: 20 | S19: 45707 | Y19: 45884 | AB19: 45979 | AI19: =SUM(J19:K19)-CI19+CJ19 -> 16.803653 | AJ19: =AI19-CK19+CL19 -> 13.760462 | AK19: =AJ19-CM19+CN19 -> 8.9659415 | AL19: =AK19-CO19+CP19 -> 4.9705077 | AM19: =AL19-CQ19+CR19 -> 1.3746173 | AN19: =AM19-CS19+CT19 -> -2.6208165 | AO19: =AN19-CU19+CV19 -> -5.0538109 | AP19: =AO19-CW19+CX19 -> -7.2761959 | AQ19: =AP19-CY19+CZ19 -> -10.472543 | AS19: =$H$19*月別販売比率!AG5 -> 3.9954338 | AU19: =$H$19*月別販売比率!AL5 -> 3.5958904 | AW19: =$H$19*月別販売比率!AQ5 -> 3.9954338 | AY19: =$H$19*月別販売比率!AV5 -> 2.4329945 | BA19: =$H$19*月別販売比率!BA5 -> 2.222385 | BB19: 30 | BC19: =$H$19*月別販売比率!BF5 -> 3.196347 | BE19: =$H$19*月別販売比率!C21 -> 2.8313342 | BG19: =$H$19*月別販売比率!H21 -> 2.7968037 | BI19: =$H$19*月別販売比率!M21 -> 4.0379328 | BK19: =$H$19*月別販売比率!R21 -> 3.196347 | BM19: =$H$19*月別販売比率!W21 -> 3.0431909 | BN19: 20 | BO19: =$H$19*月別販売比率!AB21 -> 4.7945205 | BP19: 10 | BQ19: =$H$19*月別販売比率!AG21 -> 3.9954338 | BS19: =$H$19*月別販売比率!AL21 -> 3.5958904 | BT19: 25 | BU19: =$H$19*月別販売比率!AQ21 -> 3.9954338 | BW19: =$H$19*月別販売比率!AV21 -> 2.4329945 | BY19: =$H$19*月別販売比率!BA21 -> 2.222385 | CA19: =$H$19*月別販売比率!BF21 -> 3.196347 | CC19: =H19*月別販売比率!$C$21 -> 2.8313342 | CE19: =H19*月別販売比率!$H$21 -> 2.7968037 | CG19: =$H$19*月別販売比率!M21 -> 4.0379328 | CH19: 20 | CI19: =H19*月別販売比率!$R$21 -> 3.196347 | CK19: =H19*月別販売比率!$W$21 -> 3.0431909 | CM19: =H19*月別販売比率!$AB$21 -> 4.7945205 | CO19: =H19*月別販売比率!$AG$21 -> 3.9954338 | CQ19: =H19*月別販売比率!$AL$21 -> 3.5958904 | CS19: =H19*月別販売比率!$AQ$21 -> 3.9954338 | CU19: =H19*月別販売比率!$AV$21 -> 2.4329945 | CW19: =H19*月別販売比率!$BA$21 -> 2.222385 | CY19: =H19*月別販売比率!$BF$21 -> 3.196347
E20: +2.50 | F20: 29 | G20: =F20*4400 -> 127600 | H20: =F20*($H$6/$F$6) -> 77.245053 | I20: =H20*4400 -> 339878.23 | J20: 0 | K20: =SUM(L20:N20) -> 33 | L20: 4 | M20: 0 | N20: 29 | S20: 45707 | AI20: =SUM(J20:K20)-CI20+CJ20 -> 26.820396 | AJ20: =AI20-CK20+CL20 -> 20.936893 | AK20: =AJ20-CM20+CN20 -> 11.667487 | AL20: =AK20-CO20+CP20 -> 3.9429816 | AM20: =AL20-CQ20+CR20 -> -3.0090731 | AN20: =AM20-CS20+CT20 -> -10.733578 | AO20: =AN20-CU20+CV20 -> -15.437368 | AP20: =AO20-CW20+CX20 -> -19.733979 | AQ20: =AP20-CY20+CZ20 -> -25.913583 | AS20: =$H$20*月別販売比率!AG5 -> 7.7245053 | AU20: =$H$20*月別販売比率!AL5 -> 6.9520548 | AW20: =$H$20*月別販売比率!AQ5 -> 7.7245053 | AY20: =$H$20*月別販売比率!AV5 -> 4.7037893 | BA20: =$H$20*月別販売比率!BA5 -> 4.2966109 | BB20: 40 | BC20: =$H$20*月別販売比率!BF5 -> 6.1796043 | BE20: =$H$20*月別販売比率!C21 -> 5.4739129 | BG20: =$H$20*月別販売比率!H21 -> 5.4071537 | BI20: =$H$20*月別販売比率!M21 -> 7.8066701 | BK20: =$H$20*月別販売比率!R21 -> 6.1796043 | BM20: =$H$20*月別販売比率!W21 -> 5.8835024 | BN20: 55 | BO20: =$H$20*月別販売比率!AB21 -> 9.2694064 | BP20: 5 | BQ20: =$H$20*月別販売比率!AG21 -> 7.7245053 | BS20: =$H$20*月別販売比率!AL21 -> 6.9520548 | BT20: 10 | BU20: =$H$20*月別販売比率!AQ21 -> 7.7245053 | BW20: =$H$20*月別販売比率!AV21 -> 4.7037893 | BY20: =$H$20*月別販売比率!BA21 -> 4.2966109 | CA20: =$H$20*月別販売比率!BF21 -> 6.1796043 | CC20: =H20*月別販売比率!$C$21 -> 5.4739129 | CE20: =H20*月別販売比率!$H$21 -> 5.4071537 | CG20: =$H$20*月別販売比率!M21 -> 7.8066701 | CH20: 30 | CI20: =H20*月別販売比率!$R$21 -> 6.1796043 | CK20: =H20*月別販売比率!$W$21 -> 5.8835024 | CM20: =H20*月別販売比率!$AB$21 -> 9.2694064 | CO20: =H20*月別販売比率!$AG$21 -> 7.7245053 | CQ20: =H20*月別販売比率!$AL$21 -> 6.9520548 | CS20: =H20*月別販売比率!$AQ$21 -> 7.7245053 | CU20: =H20*月別販売比率!$AV$21 -> 4.7037893 | CW20: =H20*月別販売比率!$BA$21 -> 4.2966109 | CY20: =H20*月別販売比率!$BF$21 -> 6.1796043
E21: +3.00 | F21: 18 | G21: =F21*4400 -> 79200 | H21: =F21*($H$6/$F$6) -> 47.945205 | I21: =H21*4400 -> 210958.9 | J21: 0 | K21: =SUM(L21:N21) -> 13 | L21: 4 | M21: 0 | N21: 9 | S21: 45707 | Y21: 45884 | AI21: =SUM(J21:K21)-CI21+CJ21 -> 9.1643836 | AJ21: =AI21-CK21+CL21 -> 5.5125545 | AK21: =AJ21-CM21+CN21 -> -0.24087015 | AL21: =AK21-CO21+CP21 -> -5.0353907 | AM21: =AL21-CQ21+CR21 -> -9.3504592 | AN21: =AM21-CS21+CT21 -> -14.14498 | AO21: =AN21-CU21+CV21 -> -17.064573 | AP21: =AO21-CW21+CX21 -> -19.731435 | AQ21: =AP21-CY21+CZ21 -> -23.567051 | AS21: =$H$21*月別販売比率!AG5 -> 4.7945205 | AU21: =$H$21*月別販売比率!AL5 -> 4.3150685 | AW21: =$H$21*月別販売比率!AQ5 -> 4.7945205 | AY21: =$H$21*月別販売比率!AV5 -> 2.9195933 | BA21: =$H$21*月別販売比率!BA5 -> 2.666862 | BB21: 15 | BC21: =$H$21*月別販売比率!BF5 -> 3.8356164 | BE21: =$H$21*月別販売比率!C21 -> 3.3976011 | BG21: =$H$21*月別販売比率!H21 -> 3.3561644 | BI21: =$H$21*月別販売比率!M21 -> 4.8455193 | BK21: =$H$21*月別販売比率!R21 -> 3.8356164 | BM21: =$H$21*月別販売比率!W21 -> 3.6518291 | BN21: 35 | BO21: =$H$21*月別販売比率!AB21 -> 5.7534247 | BQ21: =$H$21*月別販売比率!AG21 -> 4.7945205 | BS21: =$H$21*月別販売比率!AL21 -> 4.3150685 | BT21: 10 | BU21: =$H$21*月別販売比率!AQ21 -> 4.7945205 | BW21: =$H$21*月別販売比率!AV21 -> 2.9195933 | BY21: =$H$21*月別販売比率!BA21 -> 2.666862 | CA21: =$H$21*月別販売比率!BF21 -> 3.8356164 | CC21: =H21*月別販売比率!$C$21 -> 3.3976011 | CE21: =H21*月別販売比率!$H$21 -> 3.3561644 | CG21: =$H$21*月別販売比率!M21 -> 4.8455193 | CH21: 15 | CI21: =H21*月別販売比率!$R$21 -> 3.8356164 | CK21: =H21*月別販売比率!$W$21 -> 3.6518291 | CM21: =H21*月別販売比率!$AB$21 -> 5.7534247 | CO21: =H21*月別販売比率!$AG$21 -> 4.7945205 | CQ21: =H21*月別販売比率!$AL$21 -> 4.3150685 | CS21: =H21*月別販売比率!$AQ$21 -> 4.7945205 | CU21: =H21*月別販売比率!$AV$21 -> 2.9195933 | CW21: =H21*月別販売比率!$BA$21 -> 2.666862 | CY21: =H21*月別販売比率!$BF$21 -> 3.8356164
